Workbook

Sheet C1 Summary
B1: ='C1 System Weights'!E11 -> Subsystem Count | C1: ='C1 System Weights'!E12 -> Deployment Burden | D1: ='C1 System Weights'!E13 -> Operational Flexibility | E1: ='C1 System Weights'!E14 -> Maintenance Demands | F1: ='C1 System Weights'!E15 -> Refuel/Replenish Burden | G1: ='C1 System Weights'!E16 -> Autonomy/Supervision Required
A2: Weights | B2: ='C1 System Weights'!F11 -> 0.16417655 | C2: ='C1 System Weights'!F12 -> 0.18897825 | D2: ='C1 System Weights'!F13 -> 0.21073817 | E2: ='C1 System Weights'!F14 -> 0.12390809 | F2: ='C1 System Weights'!F15 -> 0.051576953 | G2: ='C1 System Weights'!F16 -> 0.26062198 | I2: Ranking
A3: ='DSM Elements'!A1 -> Very Large Air Tankers | B3: 9 | C3: 9 | D3: 5 | E3: 8 | F3: 9 | G3: 6 | I3: =(B3-1)/8*$B$2+(C3-1)/8*$C$2+(D3-1)/8*$D$2+(E3-1)/8*$E$2+(F3-1)/8*$F$2+(G3-1)/8*$G$2 -> 0.78140916 | J3: 0.2
A4: ='DSM Elements'!A2 -> Large Air Tankers | B4: 8 | C4: 8 | D4: 4 | E4: 7 | F4: 8 | G4: 6 | I4: =(B4-1)/8*$B$2+(C4-1)/8*$C$2+(D4-1)/8*$D$2+(E4-1)/8*$E$2+(F4-1)/8*$F$2+(G4-1)/8*$G$2 -> 0.68898691 | J4: 0.2
A5: ='DSM Elements'!A3 -> Single Engine Airtankers | B5: 4 | C5: 4 | D5: 3 | E5: 5 | F5: 6 | G5: 5 | I5: =(B5-1)/8*$B$2+(C5-1)/8*$C$2+(D5-1)/8*$D$2+(E5-1)/8*$E$2+(F5-1)/8*$F$2+(G5-1)/8*$G$2 -> 0.40961823 | J5: 0.2
A6: ='DSM Elements'!A4 -> Water Scoopers | B6: 6 | C6: 5 | D6: 4 | E6: 6 | F6: 5 | G6: 4 | I6: =(B6-1)/8*$B$2+(C6-1)/8*$C$2+(D6-1)/8*$D$2+(E6-1)/8*$E$2+(F6-1)/8*$F$2+(G6-1)/8*$G$2 -> 0.47709056 | J6: 0.2
A7: ='DSM Elements'!A5 -> Military Airborne Firefighting System | B7: 9 | C7: 8 | D7: 3 | E7: 8 | F7: 8 | G7: 7 | I7: =(B7-1)/8*$B$2+(C7-1)/8*$C$2+(D7-1)/8*$D$2+(E7-1)/8*$E$2+(F7-1)/8*$F$2+(G7-1)/8*$G$2 -> 0.73123296 | J7: 0.2
A8: ='DSM Elements'!A6 -> Helicopters Type I | B8: 8 | C8: 6 | D8: 2 | E8: 7 | F8: 7 | G8: 6 | I8: =(B8-1)/8*$B$2+(C8-1)/8*$C$2+(D8-1)/8*$D$2+(E8-1)/8*$E$2+(F8-1)/8*$F$2+(G8-1)/8*$G$2 -> 0.58261068 | J8: 0.2
A9: ='DSM Elements'!A7 -> Helicopters Type II | B9: 6 | C9: 5 | D9: 3 | E9: 6 | F9: 6 | G9: 5 | I9: =(B9-1)/8*$B$2+(C9-1)/8*$C$2+(D9-1)/8*$D$2+(E9-1)/8*$E$2+(F9-1)/8*$F$2+(G9-1)/8*$G$2 -> 0.48977315 | J9: 0.2
A10: ='DSM Elements'!A8 -> Helicopters Type III | B10: 5 | C10: 4 | D10: 4 | E10: 5 | F10: 5 | G10: 4 | I10: =(B10-1)/8*$B$2+(C10-1)/8*$C$2+(D10-1)/8*$D$2+(E10-1)/8*$E$2+(F10-1)/8*$F$2+(G10-1)/8*$G$2 -> 0.4174577 | J10: 0.2
A11: ='DSM Elements'!A9 -> Tactical Lead Planes | B11: 6 | C11: 5 | D11: 2 | E11: 6 | F11: 7 | G11: 5 | I11: =(B11-1)/8*$B$2+(C11-1)/8*$C$2+(D11-1)/8*$D$2+(E11-1)/8*$E$2+(F11-1)/8*$F$2+(G11-1)/8*$G$2 -> 0.469878 | J11: 0.2
A12: ='DSM Elements'!A10 -> Air Attack Group Supervisor (AAGS) | B12: 5 | C12: 4 | D12: 1 | E12: 5 | F12: 6 | G12: 5 | I12: =(B12-1)/8*$B$2+(C12-1)/8*$C$2+(D12-1)/8*$D$2+(E12-1)/8*$E$2+(F12-1)/8*$F$2+(G12-1)/8*$G$2 -> 0.37745575 | J12: 0.2
A13: ='DSM Elements'!A11 -> Smokejumper Aircraft | B13: 5 | C13: 5 | D13: 4 | E13: 6 | F13: 7 | G13: 4 | I13: =(B13-1)/8*$B$2+(C13-1)/8*$C$2+(D13-1)/8*$D$2+(E13-1)/8*$E$2+(F13-1)/8*$F$2+(G13-1)/8*$G$2 -> 0.46946273 | J13: 0.2
A14: ='DSM Elements'!A12 -> Tactical UAS | B14: 6 | C14: 3 | D14: 3 | E14: 4 | F14: 4 | G14: 3 | I14: =(B14-1)/8*$B$2+(C14-1)/8*$C$2+(D14-1)/8*$D$2+(E14-1)/8*$E$2+(F14-1)/8*$F$2+(G14-1)/8*$G$2 -> 0.33350184 | J14: 0.2
... A22: ='DSM Elements'!A20 -> C3 Systems | B22: 9 | C22: 2 | D22: 2 | E22: 6 | F22: 5 | G22: 5 | I22: =(B22-1)/8*$B$2+(C22-1)/8*$C$2+(D22-1)/8*$D$2+(E22-1)/8*$E$2+(F22-1)/8*$F$2+(G22-1)/8*$G$2 -> 0.44768312 | J22: 0.2
B25: ='C1 System Weights'!E22 -> Cognitive Load | C25: ='C1 System Weights'!E23 -> Temporal Criticality | D25: ='C1 System Weights'!E24 -> Interdependency/Process Coupling | E25: ='C1 System Weights'!E25 -> Execution Steps | F25: ='C1 System Weights'!E26 -> Resource Footprint | G25: ='C1 System Weights'!E27 -> Operational Risk
A26: Weights | B26: ='C1 System Weights'!F22 -> 0.20182026 | C26: ='C1 System Weights'!F23 -> 0.24094347 | D26: ='C1 System Weights'!F24 -> 0.066358507 | E26: ='C1 System Weights'!F25 -> 0.033021901 | F26: ='C1 System Weights'!F26 -> 0.096869567 | G26: ='C1 System Weights'!F27 -> 0.36098629 | I26: Ranking
A27: ='DSM Elements'!A21 -> Deploy Air Assets | B27: 5 | C27: 8 | D27: 7 | E27: 6 | F27: 7 | G27: 8 | I27: =(B27-1)/8*$B$26+(C27-1)/8*$C$26+(D27-1)/8*$D$26+(E27-1)/8*$E$26+(F27-1)/8*$F$26+(G27-1)/8*$G$26 -> 0.77065842 | J27: 1
A28: ='DSM Elements'!A22 -> Lead Tankers | B28: 7 | C28: 9 | D28: 8 | E28: 7 | F28: 8 | G28: 9 | I28: =(B28-1)/8*$B$26+(C28-1)/8*$C$26+(D28-1)/8*$D$26+(E28-1)/8*$E$26+(F28-1)/8*$F$26+(G28-1)/8*$G$26 -> 0.92088595 | J28: 1
A29: ='DSM Elements'!A23 -> Supervise Air Attacks (AAGs) | B29: 8 | C29: 9 | D29: 9 | E29: 8 | F29: 8 | G29: 9 | I29: =(B29-1)/8*$B$26+(C29-1)/8*$C$26+(D29-1)/8*$D$26+(E29-1)/8*$E$26+(F29-1)/8*$F$26+(G29-1)/8*$G$26 -> 0.95853603 | J29: 1
A30: ='DSM Elements'!A24 -> Drop Water | B30: 3 | C30: 9 | D30: 6 | E30: 3 | F30: 6 | G30: 7 | I30: =(B30-1)/8*$B$26+(C30-1)/8*$C$26+(D30-1)/8*$D$26+(E30-1)/8*$E$26+(F30-1)/8*$F$26+(G30-1)/8*$G$26 -> 0.67241128 | J30: 1
A31: ='DSM Elements'!A25 -> Drop Fire Retardant | B31: 3 | C31: 9 | D31: 6 | E31: 3 | F31: 6 | G31: 7 | I31: =(B31-1)/8*$B$26+(C31-1)/8*$C$26+(D31-1)/8*$D$26+(E31-1)/8*$E$26+(F31-1)/8*$F$26+(G31-1)/8*$G$26 -> 0.67241128 | J31: 1
A32: ='DSM Elements'!A26 -> Perform Post-Drop Assessment | B32: 5 | C32: 6 | D32: 7 | E32: 5 | F32: 5 | G32: 5 | I32: =(B32-1)/8*$B$26+(C32-1)/8*$C$26+(D32-1)/8*$D$26+(E32-1)/8*$E$26+(F32-1)/8*$F$26+(G32-1)/8*$G$26 -> 0.54670756 | J32: 1
A33: ='DSM Elements'!A27 -> Dispatch To Reloading Base | B33: 2 | C33: 5 | D33: 5 | E33: 3 | F33: 4 | G33: 4 | I33: =(B33-1)/8*$B$26+(C33-1)/8*$C$26+(D33-1)/8*$D$26+(E33-1)/8*$E$26+(F33-1)/8*$F$26+(G33-1)/8*$G$26 -> 0.35882994 | J33: 1
A34: ='DSM Elements'!A28 -> Deploy Ground Assets | B34: 4 | C34: 7 | D34: 7 | E34: 6 | F34: 7 | G34: 7 | I34: =(B34-1)/8*$B$26+(C34-1)/8*$C$26+(D34-1)/8*$D$26+(E34-1)/8*$E$26+(F34-1)/8*$F$26+(G34-1)/8*$G$26 -> 0.67018966 | J34: 1
A35: ='DSM Elements'!A29 -> Establish Containment Lines | B35: 6 | C35: 8 | D35: 8 | E35: 7 | F35: 8 | G35: 8 | I35: =(B35-1)/8*$B$26+(C35-1)/8*$C$26+(D35-1)/8*$D$26+(E35-1)/8*$E$26+(F35-1)/8*$F$26+(G35-1)/8*$G$26 -> 0.8204172 | J35: 1
A36: ='DSM Elements'!A30 -> Spill Water from Ground Assets | B36: 2 | C36: 7 | D36: 5 | E36: 3 | F36: 4 | G36: 5 | I36: =(B36-1)/8*$B$26+(C36-1)/8*$C$26+(D36-1)/8*$D$26+(E36-1)/8*$E$26+(F36-1)/8*$F$26+(G36-1)/8*$G$26 -> 0.4641891 | J36: 1
A37: ='DSM Elements'!A31 -> Tactically Monitor Fires | B37: 6 | C37: 7 | D37: 6 | E37: 6 | F37: 6 | G37: 6 | I37: =(B37-1)/8*$B$26+(C37-1)/8*$C$26+(D37-1)/8*$D$26+(E37-1)/8*$E$26+(F37-1)/8*$F$26+(G37-1)/8*$G$26 -> 0.65511793 | J37: 1
A38: ='DSM Elements'!A32 -> Predict New Fires | B38: 7 | C38: 5 | D38: 6 | E38: 5 | F38: 5 | G38: 6 | I38: =(B38-1)/8*$B$26+(C38-1)/8*$C$26+(D38-1)/8*$D$26+(E38-1)/8*$E$26+(F38-1)/8*$F$26+(G38-1)/8*$G$26 -> 0.60387317 | J38: 1
... A57: ='DSM Elements'!A51 -> Provide Logistic Support to Crews | B57: 4 | C57: 6 | D57: 6 | E57: 6 | F57: 6 | G57: 6 | I57: =(B57-1)/8*$B$26+(C57-1)/8*$C$26+(D57-1)/8*$D$26+(E57-1)/8*$E$26+(F57-1)/8*$F$26+(G57-1)/8*$G$26 -> 0.57454493 | J57: 1
B60: ='C1 System Weights'!E32 -> Jurisdictional Breadth | C60: ='C1 System Weights'!E33 -> Coordination Span | D60: ='C1 System Weights'!E34 -> Legal/Bureaucratic Constraints | E60: ='C1 System Weights'!E35 -> Mandate Breadth | F60: ='C1 System Weights'!E36 -> Resource Management Burden | G60: ='C1 System Weights'!E37 -> Policy/Political Sensitivity | H60: ='C1 System Weights'!E38 -> Activation/Response Latency
A61: Weights | B61: ='C1 System Weights'!F32 -> 0.171078 | C61: ='C1 System Weights'!F33 -> 0.1551578 | D61: ='C1 System Weights'!F34 -> 0.056705039 | E61: ='C1 System Weights'!F35 -> 0.19479604 | F61: ='C1 System Weights'!F36 -> 0.22053918 | G61: ='C1 System Weights'!F37 -> 0.15599746 | H61: ='C1 System Weights'!F38 -> 0.045726469 | I61: Ranking
A62: ='DSM Elements'!A52 -> Federal Emergency Management Agency | B62: 8 | C62: 9 | D62: 7 | E62: 8 | F62: 8 | G62: 8 | H62: 6 | I62: =(B62-1)/8*$B$61+(C62-1)/8*$C$61+(D62-1)/8*$D$61+(E62-1)/8*$E$61+(F62-1)/8*$F$61+(G62-1)/8*$G$61+(H62-1)/8*$H$61 -> 0.87587498 | J62: 0.4
A63: ='DSM Elements'!A53 -> National Interagency Fire Center | B63: 7 | C63: 8 | D63: 6 | E63: 7 | F63: 7 | G63: 6 | H63: 5 | I63: =(B63-1)/8*$B$61+(C63-1)/8*$C$61+(D63-1)/8*$D$61+(E63-1)/8*$E$61+(F63-1)/8*$F$61+(G63-1)/8*$G$61+(H63-1)/8*$H$61 -> 0.73137529 | J63: 0.4
A64: ='DSM Elements'!A54 -> Environmental Protection Agency | B64: 6 | C64: 7 | D64: 8 | E64: 5 | F64: 5 | G64: 9 | H64: 7 | I64: =(B64-1)/8*$B$61+(C64-1)/8*$C$61+(D64-1)/8*$D$61+(E64-1)/8*$E$61+(F64-1)/8*$F$61+(G64-1)/8*$G$61+(H64-1)/8*$H$61 -> 0.67086894 | J64: 0.4
A65: ='DSM Elements'!A55 -> Military Organizations (US National Guard/DOD) | B65: 9 | C65: 9 | D65: 9 | E65: 9 | F65: 9 | G65: 9 | H65: 8 | I65: =(B65-1)/8*$B$61+(C65-1)/8*$C$61+(D65-1)/8*$D$61+(E65-1)/8*$E$61+(F65-1)/8*$F$61+(G65-1)/8*$G$61+(H65-1)/8*$H$61 -> 0.99428419 | J65: 0.4
A66: ='DSM Elements'!A56 -> Manufacturers Of VLAT/LAT | B66: 3 | C66: 3 | D66: 2 | E66: 3 | F66: 4 | G66: 2 | H66: 2 | I66: =(B66-1)/8*$B$61+(C66-1)/8*$C$61+(D66-1)/8*$D$61+(E66-1)/8*$E$61+(F66-1)/8*$F$61+(G66-1)/8*$G$61+(H66-1)/8*$H$61 -> 0.24526378 | J66: 0.4
A67: ='DSM Elements'!A57 -> Manufacturers Of Lead Plane & AAGS | B67: 3 | C67: 3 | D67: 2 | E67: 3 | F67: 3 | G67: 2 | H67: 2 | I67: =(B67-1)/8*$B$61+(C67-1)/8*$C$61+(D67-1)/8*$D$61+(E67-1)/8*$E$61+(F67-1)/8*$F$61+(G67-1)/8*$G$61+(H67-1)/8*$H$61 -> 0.21769638 | J67: 0.4
A68: ='DSM Elements'!A58 -> Satellite Manufacturers | B68: 6 | C68: 5 | D68: 3 | E68: 4 | F68: 6 | G68: 3 | H68: 3 | I68: =(B68-1)/8*$B$61+(C68-1)/8*$C$61+(D68-1)/8*$D$61+(E68-1)/8*$E$61+(F68-1)/8*$F$61+(G68-1)/8*$G$61+(H68-1)/8*$H$61 -> 0.4599954 | J68: 0.4
A69: ='DSM Elements'!A59 -> UAS Manufacturers | B69: 4 | C69: 5 | D69: 3 | E69: 3 | F69: 5 | G69: 3 | H69: 3 | I69: =(B69-1)/8*$B$61+(C69-1)/8*$C$61+(D69-1)/8*$D$61+(E69-1)/8*$E$61+(F69-1)/8*$F$61+(G69-1)/8*$G$61+(H69-1)/8*$H$61 -> 0.365309 | J69: 0.4
A70: ='DSM Elements'!A60 -> C3 Systems Suppliers | B70: 4 | C70: 6 | D70: 4 | E70: 5 | F70: 6 | G70: 5 | H70: 4 | I70: =(B70-1)/8*$B$61+(C70-1)/8*$C$61+(D70-1)/8*$D$61+(E70-1)/8*$E$61+(F70-1)/8*$F$61+(G70-1)/8*$G$61+(H70-1)/8*$H$61 -> 0.51277343 | J70: 0.4
A71: ='DSM Elements'!A61 -> Communication Systems Suppliers | B71: 4 | C71: 6 | D71: 4 | E71: 5 | F71: 6 | G71: 5 | H71: 4 | I71: =(B71-1)/8*$B$61+(C71-1)/8*$C$61+(D71-1)/8*$D$61+(E71-1)/8*$E$61+(F71-1)/8*$F$61+(G71-1)/8*$G$61+(H71-1)/8*$H$61 -> 0.51277343 | J71: 0.4
A72: ='DSM Elements'!A62 -> Geospatial Information System Companies | B72: 4 | C72: 6 | D72: 5 | E72: 5 | F72: 5 | G72: 4 | H72: 4 | I72: =(B72-1)/8*$B$61+(C72-1)/8*$C$61+(D72-1)/8*$D$61+(E72-1)/8*$E$61+(F72-1)/8*$F$61+(G72-1)/8*$G$61+(H72-1)/8*$H$61 -> 0.47279448 | J72: 0.4
A73: ='DSM Elements'!A63 -> Cloud Service Providers | B73: 5 | C73: 6 | D73: 3 | E73: 5 | F73: 4 | G73: 4 | H73: 3 | I73: =(B73-1)/8*$B$61+(C73-1)/8*$C$61+(D73-1)/8*$D$61+(E73-1)/8*$E$61+(F73-1)/8*$F$61+(G73-1)/8*$G$61+(H73-1)/8*$H$61 -> 0.44671977 | J73: 0.4
... A94: ='DSM Elements'!A84 -> Government of Canada | B94: 9 | C94: 9 | D94: 9 | E94: 9 | F94: 9 | G94: 9 | H94: 8 | I94: =(B94-1)/8*$B$61+(C94-1)/8*$C$61+(D94-1)/8*$D$61+(E94-1)/8*$E$61+(F94-1)/8*$F$61+(G94-1)/8*$G$61+(H94-1)/8*$H$61 -> 0.99428419 | J94: 0.4

Sheet C1 System Weights
B2: Rankings | E2: Key Note:
B3: Importance | C3: Definition | E3: Type metric name in gray
B4: 1 | C4: Equal Complexity | E4: Only type comparison values in white areas
B5: 3 | C5: Moderate Complexity
B6: 5 | C6: Strong Complexity | E6: You have to open in the desktop app to copy and paste with the formulas
B7: 7 | C7: Very Strong Complexity
B8: 9 | C8: Extreme Complexity
E10: Metric | F10: Criticality Weights | G10: =E11 -> Subsystem Count | H10: =E12 -> Deployment Burden | I10: =E13 -> Operational Flexibility | J10: =E14 -> Maintenance Demands | K10: =E15 -> Refuel/Replenish Burden | L10: =E16 -> Autonomy/Supervision Required | O10: Metric | P10: Relative Importance
E11: Subsystem Count | F11: =AVERAGE(R11:W11) -> 0.16417655 | G11: 1 | H11: 2 | I11: 0.33333333 | J11: 1 | K11: 3 | L11: 1 | O11: =E11 -> Subsystem Count | P11: =F11 -> 0.16417655 | R11: =G11/SUM(G$11:G$16) -> 0.14634146 | S11: =H11/SUM(H$11:H$16) -> 0.26845638 | T11: =I11/SUM(I$11:I$16) -> 0.055555556 | U11: =J11/SUM(J$11:J$16) -> 0.088235294 | V11: =K11/SUM(K$11:K$16) -> 0.17647059 | W11: =L11/SUM(L$11:L$16) -> 0.25
E12: Deployment Burden | F12: =AVERAGE(R12:W12) -> 0.18897825 | G12: {=1/INDEX($H$11:$M$11, 1, ROW(A1))} -> 0.5 | H12: 1 | I12: 1 | J12: 5 | K12: 4 | L12: 0.33333333 | O12: =E12 -> Deployment Burden | P12: =F12 -> 0.18897825 | R12: =G12/SUM(G$11:G$16) -> 0.073170732 | S12: =H12/SUM(H$11:H$16) -> 0.13422819 | T12: =I12/SUM(I$11:I$16) -> 0.16666667 | U12: =J12/SUM(J$11:J$16) -> 0.44117647 | V12: =K12/SUM(K$11:K$16) -> 0.23529412 | W12: =L12/SUM(L$11:L$16) -> 0.083333333
E13: Operational Flexibility | F13: =AVERAGE(R13:W13) -> 0.21073817 | G13: {=1/INDEX($H$11:$M$11, 1, ROW(A2))} -> 3 | H13: {=1/INDEX($I$12:$M$12, 1, ROW(A1))} -> 1 | I13: 1 | J13: 3 | K13: 3 | L13: 0.33333333 | O13: =E13 -> Operational Flexibility | P13: =F13 -> 0.21073817 | R13: =G13/SUM(G$11:G$16) -> 0.43902439 | S13: =H13/SUM(H$11:H$16) -> 0.13422819 | T13: =I13/SUM(I$11:I$16) -> 0.16666667 | U13: =J13/SUM(J$11:J$16) -> 0.26470588 | V13: =K13/SUM(K$11:K$16) -> 0.17647059 | W13: =L13/SUM(L$11:L$16) -> 0.083333333
E14: Maintenance Demands | F14: =AVERAGE(R14:W14) -> 0.12390809 | G14: {=1/INDEX($H$11:$M$11, 1, ROW(A3))} -> 1 | H14: {=1/INDEX($I$12:$M$12, 1, ROW(A2))} -> 0.2 | I14: {=1/INDEX($J$13:$M$13, 1, ROW(A1))} -> 0.33333333 | J14: 1 | K14: 3 | L14: 1 | O14: =E14 -> Maintenance Demands | P14: =F14 -> 0.12390809 | R14: =G14/SUM(G$11:G$16) -> 0.14634146 | S14: =H14/SUM(H$11:H$16) -> 0.026845638 | T14: =I14/SUM(I$11:I$16) -> 0.055555556 | U14: =J14/SUM(J$11:J$16) -> 0.088235294 | V14: =K14/SUM(K$11:K$16) -> 0.17647059 | W14: =L14/SUM(L$11:L$16) -> 0.25
E15: Refuel/Replenish Burden | F15: =AVERAGE(R15:W15) -> 0.051576953 | G15: {=1/INDEX($H$11:$M$11, 1, ROW(A4))} -> 0.33333333 | H15: {=1/INDEX($I$12:$M$12, 1, ROW(A3))} -> 0.25 | I15: {=1/INDEX($J$13:$M$13, 1, ROW(A2))} -> 0.33333333 | J15: {=1/INDEX($K$14:$M$14, 1, ROW(A1))} -> 0.33333333 | K15: 1 | L15: 0.33333333 | O15: =E15 -> Refuel/Replenish Burden | P15: =F15 -> 0.051576953 | R15: =G15/SUM(G$11:G$16) -> 0.048780488 | S15: =H15/SUM(H$11:H$16) -> 0.033557047 | T15: =I15/SUM(I$11:I$16) -> 0.055555556 | U15: =J15/SUM(J$11:J$16) -> 0.029411765 | V15: =K15/SUM(K$11:K$16) -> 0.058823529 | W15: =L15/SUM(L$11:L$16) -> 0.083333333
E16: Autonomy/Supervision Required | F16: =AVERAGE(R16:W16) -> 0.26062198 | G16: {=1/INDEX($H$11:$M$11, 1, ROW(A5))} -> 1 | H16: {=1/INDEX($I$12:$M$12, 1, ROW(A4))} -> 3 | I16: {=1/INDEX($J$13:$M$13, 1, ROW(A3))} -> 3 | J16: {=1/INDEX($K$14:$M$14, 1, ROW(A2))} -> 1 | K16: {=1/INDEX($L$15:$M$15, 1, ROW(A1))} -> 3 | L16: 1 | O16: =E16 -> Autonomy/Supervision Required | P16: =F16 -> 0.26062198 | R16: =G16/SUM(G$11:G$16) -> 0.14634146 | S16: =H16/SUM(H$11:H$16) -> 0.40268456 | T16: =I16/SUM(I$11:I$16) -> 0.5 | U16: =J16/SUM(J$11:J$16) -> 0.088235294 | V16: =K16/SUM(K$11:K$16) -> 0.17647059 | W16: =L16/SUM(L$11:L$16) -> 0.25
F17: =SUM(F11:F16) -> 1
E21: Metric | F21: Criticality Weights | G21: =E22 -> Cognitive Load | H21: =E23 -> Temporal Criticality | I21: =E24 -> Interdependency/Process Coupling | J21: =E25 -> Execution Steps | K21: =E26 -> Resource Footprint | L21: =E27 -> Operational Risk | O21: Metric | P21: Relative Importance
E22: Cognitive Load | F22: =AVERAGE(R22:W22) -> 0.20182026 | G22: 1 | H22: 0.33333333 | I22: 3 | J22: 5 | K22: 3 | L22: 1 | O22: =E22 -> Cognitive Load | P22: =F22 -> 0.20182026 | R22: =G22/SUM(G$22:G$27) -> 0.17045455 | S22: =H22/SUM(H$22:H$27) -> 0.064102564 | T22: =I22/SUM(I$22:I$27) -> 0.19565217 | U22: =J22/SUM(J$22:J$27) -> 0.19230769 | V22: =K22/SUM(K$22:K$27) -> 0.23684211 | W22: =L22/SUM(L$22:L$27) -> 0.3515625
E23: Temporal Criticality | F23: =AVERAGE(R23:W23) -> 0.24094347 | G23: {=1/INDEX($H$22:$M$22, 1, ROW($A1))} -> 3 | H23: 1 | I23: 3 | J23: 5 | K23: 3 | L23: 0.33333333 | O23: =E23 -> Temporal Criticality | P23: =F23 -> 0.24094347 | R23: =G23/SUM(G$22:G$27) -> 0.51136364 | S23: =H23/SUM(H$22:H$27) -> 0.19230769 | T23: =I23/SUM(I$22:I$27) -> 0.19565217 | U23: =J23/SUM(J$22:J$27) -> 0.19230769 | V23: =K23/SUM(K$22:K$27) -> 0.23684211 | W23: =L23/SUM(L$22:L$27) -> 0.1171875
E24: Interdependency/Process Coupling | F24: =AVERAGE(R24:W24) -> 0.066358507 | G24: {=1/INDEX($H$22:$M$22, 1, ROW($A2))} -> 0.33333333 | H24: {=1/INDEX($I$23:$M$23, 1, ROW($A1))} -> 0.33333333 | I24: 1 | J24: 3 | K24: 0.33333333 | L24: 0.2 | O24: =E24 -> Interdependency/Process Coupling | P24: =F24 -> 0.066358507 | R24: =G24/SUM(G$22:G$27) -> 0.056818182 | S24: =H24/SUM(H$22:H$27) -> 0.064102564 | T24: =I24/SUM(I$22:I$27) -> 0.065217391 | U24: =J24/SUM(J$22:J$27) -> 0.11538462 | V24: =K24/SUM(K$22:K$27) -> 0.026315789 | W24: =L24/SUM(L$22:L$27) -> 0.0703125
E25: Execution Steps | F25: =AVERAGE(R25:W25) -> 0.033021901 | G25: {=1/INDEX($H$22:$M$22, 1, ROW($A3))} -> 0.2 | H25: {=1/INDEX($I$23:$M$23, 1, ROW($A2))} -> 0.2 | I25: {=1/INDEX($J$24:$M$24, 1, ROW($A1))} -> 0.33333333 | J25: 1 | K25: 0.33333333 | L25: =1/9 -> 0.11111111 | O25: =E25 -> Execution Steps | P25: =F25 -> 0.033021901 | R25: =G25/SUM(G$22:G$27) -> 0.034090909 | S25: =H25/SUM(H$22:H$27) -> 0.038461538 | T25: =I25/SUM(I$22:I$27) -> 0.02173913 | U25: =J25/SUM(J$22:J$27) -> 0.038461538 | V25: =K25/SUM(K$22:K$27) -> 0.026315789 | W25: =L25/SUM(L$22:L$27) -> 0.0390625
E26: Resource Footprint | F26: =AVERAGE(R26:W26) -> 0.096869567 | G26: {=1/INDEX($H$22:$M$22, 1, ROW($A4))} -> 0.33333333 | H26: {=1/INDEX($I$23:$M$23, 1, ROW($A3))} -> 0.33333333 | I26: {=1/INDEX($J$24:$M$24, 1, ROW($A2))} -> 3 | J26: {=1/INDEX($K$25:$M$25, 1, ROW($A1))} -> 3 | K26: 1 | L26: 0.2 | O26: =E26 -> Resource Footprint | P26: =F26 -> 0.096869567 | R26: =G26/SUM(G$22:G$27) -> 0.056818182 | S26: =H26/SUM(H$22:H$27) -> 0.064102564 | T26: =I26/SUM(I$22:I$27) -> 0.19565217 | U26: =J26/SUM(J$22:J$27) -> 0.11538462 | V26: =K26/SUM(K$22:K$27) -> 0.078947368 | W26: =L26/SUM(L$22:L$27) -> 0.0703125
E27: Operational Risk | F27: =AVERAGE(R27:W27) -> 0.36098629 | G27: {=1/INDEX($H$22:$M$22, 1, ROW($A5))} -> 1 | H27: {=1/INDEX($I$23:$M$23, 1, ROW($A4))} -> 3 | I27: {=1/INDEX($J$24:$M$24, 1, ROW($A3))} -> 5 | J27: {=1/INDEX($K$25:$M$25, 1, ROW($A2))} -> 9 | K27: {=1/INDEX($L$26:$M$26, 1, ROW($A1))} -> 5 | L27: 1 | O27: =E27 -> Operational Risk | P27: =F27 -> 0.36098629 | R27: =G27/SUM(G$22:G$27) -> 0.17045455 | S27: =H27/SUM(H$22:H$27) -> 0.57692308 | T27: =I27/SUM(I$22:I$27) -> 0.32608696 | U27: =J27/SUM(J$22:J$27) -> 0.34615385 | V27: =K27/SUM(K$22:K$27) -> 0.39473684 | W27: =L27/SUM(L$22:L$27) -> 0.3515625
F28: =SUM(F22:F27) -> 1
E31: Metric | F31: Criticality Weights | G31: =E32 -> Jurisdictional Breadth | H31: =E33 -> Coordination Span | I31: =E34 -> Legal/Bureaucratic Constraints | J31: =E35 -> Mandate Breadth | K31: =E36 -> Resource Management Burden | L31: =E37 -> Policy/Political Sensitivity | M31: =E38 -> Activation/Response Latency | O31: Metric | P31: Relative Importance
E32: Jurisdictional Breadth | F32: =AVERAGE(R32:X32) -> 0.171078 | G32: 1 | H32: 1 | I32: 5 | J32: 1 | K32: 1 | L32: 1 | M32: 3 | O32: =E32 -> Jurisdictional Breadth | P32: =F32 -> 0.171078 | R32: =G32/SUM(G$32:G$38) -> 0.18072289 | S32: =H32/SUM(H$32:H$38) -> 0.13274336 | T32: =I32/SUM(I$32:I$38) -> 0.26315789 | U32: =J32/SUM(J$32:J$38) -> 0.14563107 | V32: =K32/SUM(K$32:K$38) -> 0.21126761 | W32: =L32/SUM(L$32:L$38) -> 0.12765957 | X32: =M32/SUM(M$32:M$38) -> 0.13636364
E33: Coordination Span | F33: =AVERAGE(R33:X33) -> 0.1551578 | G33: {=1/INDEX($H$32:$M$32, 1, ROW($A1))} -> 1 | H33: 1 | I33: 3 | J33: 0.33333333 | K33: 1 | L33: 1 | M33: 5 | O33: =E33 -> Coordination Span | P33: =F33 -> 0.1551578 | R33: =G33/SUM(G$32:G$38) -> 0.18072289 | S33: =H33/SUM(H$32:H$38) -> 0.13274336 | T33: =I33/SUM(I$32:I$38) -> 0.15789474 | U33: =J33/SUM(J$32:J$38) -> 0.048543689 | V33: =K33/SUM(K$32:K$38) -> 0.21126761 | W33: =L33/SUM(L$32:L$38) -> 0.12765957 | X33: =M33/SUM(M$32:M$38) -> 0.22727273
E34: Legal/Bureaucratic Constraints | F34: =AVERAGE(R34:X34) -> 0.056705039 | G34: {=1/INDEX($H$32:$M$32, 1, ROW($A2))} -> 0.2 | H34: {=1/INDEX($I$33:$M$33, 1, ROW($A1))} -> 0.33333333 | I34: 1 | J34: 0.33333333 | K34: 0.2 | L34: 1 | M34: 1 | O34: =E34 -> Legal/Bureaucratic Constraints | P34: =F34 -> 0.056705039 | R34: =G34/SUM(G$32:G$38) -> 0.036144578 | S34: =H34/SUM(H$32:H$38) -> 0.044247788 | T34: =I34/SUM(I$32:I$38) -> 0.052631579 | U34: =J34/SUM(J$32:J$38) -> 0.048543689 | V34: =K34/SUM(K$32:K$38) -> 0.042253521 | W34: =L34/SUM(L$32:L$38) -> 0.12765957 | X34: =M34/SUM(M$32:M$38) -> 0.045454545
E35: Mandate Breadth | F35: =AVERAGE(R35:X35) -> 0.19479604 | G35: {=1/INDEX($H$32:$M$32, 1, ROW($A3))} -> 1 | H35: {=1/INDEX($I$33:$M$33, 1, ROW($A2))} -> 3 | I35: {=1/INDEX($J$34:$M$34, 1, ROW($A1))} -> 3 | J35: 1 | K35: 1 | L35: 0.33333333 | M35: 5 | O35: =E35 -> Mandate Breadth | P35: =F35 -> 0.19479604 | R35: =G35/SUM(G$32:G$38) -> 0.18072289 | S35: =H35/SUM(H$32:H$38) -> 0.39823009 | T35: =I35/SUM(I$32:I$38) -> 0.15789474 | U35: =J35/SUM(J$32:J$38) -> 0.14563107 | V35: =K35/SUM(K$32:K$38) -> 0.21126761 | W35: =L35/SUM(L$32:L$38) -> 0.042553191 | X35: =M35/SUM(M$32:M$38) -> 0.22727273
E36: Resource Management Burden | F36: =AVERAGE(R36:X36) -> 0.22053918 | G36: {=1/INDEX($H$32:$M$32, 1, ROW($A4))} -> 1 | H36: {=1/INDEX($I$33:$M$33, 1, ROW($A3))} -> 1 | I36: {=1/INDEX($J$34:$M$34, 1, ROW($A2))} -> 5 | J36: {=1/INDEX($K$35:$M$35, 1, ROW($A1))} -> 1 | K36: 1 | L36: 3 | M36: 5 | O36: =E36 -> Resource Management Burden | P36: =F36 -> 0.22053918 | R36: =G36/SUM(G$32:G$38) -> 0.18072289 | S36: =H36/SUM(H$32:H$38) -> 0.13274336 | T36: =I36/SUM(I$32:I$38) -> 0.26315789 | U36: =J36/SUM(J$32:J$38) -> 0.14563107 | V36: =K36/SUM(K$32:K$38) -> 0.21126761 | W36: =L36/SUM(L$32:L$38) -> 0.38297872 | X36: =M36/SUM(M$32:M$38) -> 0.22727273
E37: Policy/Political Sensitivity | F37: =AVERAGE(R37:X37) -> 0.15599746 | G37: {=1/INDEX($H$32:$M$32, 1, ROW($A5))} -> 1 | H37: {=1/INDEX($I$33:$M$33, 1, ROW($A4))} -> 1 | I37: {=1/INDEX($J$34:$M$34, 1, ROW($A3))} -> 1 | J37: {=1/INDEX($K$35:$M$35, 1, ROW($A2))} -> 3 | K37: {=1/INDEX($L$36:$M$36, 1, ROW($A1))} -> 0.33333333 | L37: 1 | M37: 2 | O37: =E37 -> Policy/Political Sensitivity | P37: =F37 -> 0.15599746 | R37: =G37/SUM(G$32:G$38) -> 0.18072289 | S37: =H37/SUM(H$32:H$38) -> 0.13274336 | T37: =I37/SUM(I$32:I$38) -> 0.052631579 | U37: =J37/SUM(J$32:J$38) -> 0.4368932 | V37: =K37/SUM(K$32:K$38) -> 0.070422535 | W37: =L37/SUM(L$32:L$38) -> 0.12765957 | X37: =M37/SUM(M$32:M$38) -> 0.090909091
E38: Activation/Response Latency | F38: =AVERAGE(R38:X38) -> 0.045726469 | G38: {=1/INDEX($H$32:$M$32, 1, ROW($A6))} -> 0.33333333 | H38: {=1/INDEX($I$33:$M$33, 1, ROW($A5))} -> 0.2 | I38: {=1/INDEX($J$34:$M$34, 1, ROW($A4))} -> 1 | J38: {=1/INDEX($K$35:$M$35, 1, ROW($A3))} -> 0.2 | K38: {=1/INDEX($L$36:$M$36, 1, ROW($A2))} -> 0.2 | L38: {=1/INDEX($M$37:$M$37, 1, ROW($A1))} -> 0.5 | M38: 1 | O38: =E38 -> Activation/Response Latency | P38: =F38 -> 0.045726469 | R38: =G38/SUM(G$32:G$38) -> 0.060240964 | S38: =H38/SUM(H$32:H$38) -> 0.026548673 | T38: =I38/SUM(I$32:I$38) -> 0.052631579 | U38: =J38/SUM(J$32:J$38) -> 0.029126214 | V38: =K38/SUM(K$32:K$38) -> 0.042253521 | W38: =L38/SUM(L$32:L$38) -> 0.063829787 | X38: =M38/SUM(M$32:M$38) -> 0.045454545
F39: =SUM(F32:F38) -> 1

Sheet C1 Metric Descriptions
A1: Element Type | B1: Metric | C1: Description
A2: Structural | B2: Subsystem Count | C2: Number and diversity of onboard subsystems (avionics, propulsion, sensors, etc.). More = higher complexity.
A3: Structural | B3: Deployment Burden | C3: Difficulty in deploying or positioning the asset (e.g., launch, airlift, driving terrain).
A4: Structural | B4: Operational Flexibility | C4: Number of distinct roles it can fulfill (e.g., surveillance, suppression, transport).
A5: Structural | B5: Maintenance Demands | C5: Frequency, difficulty, and time required for upkeep or repair.
A6: Structural | B6: Refueling / Replenishment Burden | C6: Logistics of keeping the asset mission-ready (e.g., fueling, retardant loading).
A7: Structural | B7: Autonomy / Supervision Requirement | C7: Level of human supervision or remote control required (e.g., satellite = low, drone = high).
A8: Functional | B8: Cognitive Load | C8: Complexity of human decision-making or judgment needed to perform the task.
A9: Functional | B9: Temporal Criticality | C9: How time-sensitive the function is for mission success (e.g., suppression vs. comms).
A10: Functional | B10: Interdependency / Process Coupling | C10: Degree of dependency on other functions to execute effectively.
A11: Functional | B11: Execution Steps | C11: Number of steps, phases, or sub-functions involved.
A12: Functional | B12: Resource Footprint | C12: Quantity and diversity of assets required (e.g., aircraft, personnel, data links).
... A20: Organizational | B20: Activation / Response Latency | C20: Time and effort required to mobilize the organization into active operations.

Sheet DSM Elements
A1: Very Large Air Tankers
A2: Large Air Tankers
A3: Single Engine Airtankers
A4: Water Scoopers
A5: Military Airborne Firefighting System
A6: Helicopters Type I
A7: Helicopters Type II
A8: Helicopters Type III
A9: Tactical Lead Planes
A10: Air Attack Group Supervisor (AAGS)
A11: Smokejumper Aircraft
A12: Tactical UAS
... A84: Government of Canada

Sheet C2 Interface Weights
B2: Rankings | E2: Key Note:
B3: Importance | C3: Definition | E3: Type metric name in gray
B4: 1 | C4: Equal Complexity | E4: Only type comparison values in white areas
B5: 3 | C5: Moderate Complexity
B6: 5 | C6: Strong Complexity | E6: You have to open in the desktop app to copy and paste with the formulas
B7: 7 | C7: Very Strong Complexity
B8: 9 | C8: Extreme Complexity
E10: Functions | F10: Criticality Weights | G10: =E11 -> Mass | H10: =E12 -> Information | I10: =E13 -> Physical | J10: =E14 -> Energy | K10: =E15 -> Contribution | L10: =E16 -> Development | M10: =E17 -> Operation | N10: =E18 -> Service | O10: =E19 -> Prerequisite | P10: =E20 -> Coordination | Q10: =E21 -> Definition | R10: =E22 -> Contractual | S10: =E23 -> Deliverable | T10: =E24 -> Financial | U10: =E25 -> Legal | V10: =E26 -> Political | X10: Interface | Y10: Complexity "Importance"
E11: Mass | F11: =AVERAGE(AA11:AP11) -> 0.013877066 | G11: 1 | H11: =1/3 -> 0.33333333 | I11: 1 | J11: =1/2 -> 0.5 | K11: =1/4 -> 0.25 | L11: =1/5 -> 0.2 | M11: =1/3 -> 0.33333333 | N11: =1/2 -> 0.5 | O11: =1/2 -> 0.5 | P11: =1/5 -> 0.2 | Q11: =1/2 -> 0.5 | R11: =1/5 -> 0.2 | S11: =1/2 -> 0.5 | T11: =1/7 -> 0.14285714 | U11: =1/7 -> 0.14285714 | V11: =1/9 -> 0.11111111 | X11: =E11 -> Mass | Y11: =F11 -> 0.013877066 | AA11: =G11/SUM(G$11:G$26) -> 0.016666667 | AB11: =H11/SUM(H$11:H$26) -> 0.0093457944 | AC11: =I11/SUM(I$11:I$26) -> 0.016666667 | AD11: =J11/SUM(J$11:J$26) -> 0.0087719298 | AE11: =K11/SUM(K$11:K$26) -> 0.0050251256 | AF11: =L11/SUM(L$11:L$26) -> 0.012145749 | AG11: =M11/SUM(M$11:M$26) -> 0.01055409 | AH11: =N11/SUM(N$11:N$26) -> 0.015625 | ... AP11: =V11/SUM(V$11:V$26) -> 0.033524904
E12: Information | F12: =AVERAGE(AA12:AP12) -> 0.028774565 | G12: {=1/INDEX($H$11:$V$11, 1, ROW(A1))} -> 3 | H12: 1 | I12: 3 | J12: 2 | K12: 1 | L12: =1/3 -> 0.33333333 | M12: =1/2 -> 0.5 | N12: 1 | O12: 1 | P12: =1/3 -> 0.33333333 | Q12: 2 | R12: =1/3 -> 0.33333333 | S12: =1/2 -> 0.5 | T12: =1/5 -> 0.2 | U12: =1/5 -> 0.2 | V12: =1/7 -> 0.14285714 | X12: =E12 -> Information | Y12: =F12 -> 0.028774565 | AA12: =G12/SUM(G$11:G$26) -> 0.05 | AB12: =H12/SUM(H$11:H$26) -> 0.028037383 | AC12: =I12/SUM(I$11:I$26) -> 0.05 | AD12: =J12/SUM(J$11:J$26) -> 0.035087719 | AE12: =K12/SUM(K$11:K$26) -> 0.020100503 | AF12: =L12/SUM(L$11:L$26) -> 0.020242915 | AG12: =M12/SUM(M$11:M$26) -> 0.015831135 | AH12: =N12/SUM(N$11:N$26) -> 0.03125 | ... AP12: =V12/SUM(V$11:V$26) -> 0.043103448
E13: Physical | F13: =AVERAGE(AA13:AP13) -> 0.013877066 | G13: {=1/INDEX($H$11:$V$11, 1, ROW(A2))} -> 1 | H13: {=1/INDEX($I$12:$V$12, 1, ROW(A1))} -> 0.33333333 | I13: 1 | J13: =1/2 -> 0.5 | K13: =1/4 -> 0.25 | L13: =1/5 -> 0.2 | M13: =1/3 -> 0.33333333 | N13: =1/2 -> 0.5 | O13: =1/2 -> 0.5 | P13: =1/5 -> 0.2 | Q13: =1/2 -> 0.5 | R13: =1/5 -> 0.2 | S13: =1/2 -> 0.5 | T13: =1/7 -> 0.14285714 | U13: =1/7 -> 0.14285714 | V13: =1/9 -> 0.11111111 | X13: =E13 -> Physical | Y13: =F13 -> 0.013877066 | AA13: =G13/SUM(G$11:G$26) -> 0.016666667 | AB13: =H13/SUM(H$11:H$26) -> 0.0093457944 | AC13: =I13/SUM(I$11:I$26) -> 0.016666667 | AD13: =J13/SUM(J$11:J$26) -> 0.0087719298 | AE13: =K13/SUM(K$11:K$26) -> 0.0050251256 | AF13: =L13/SUM(L$11:L$26) -> 0.012145749 | AG13: =M13/SUM(M$11:M$26) -> 0.01055409 | AH13: =N13/SUM(N$11:N$26) -> 0.015625 | ... AP13: =V13/SUM(V$11:V$26) -> 0.033524904
E14: Energy | F14: =AVERAGE(AA14:AP14) -> 0.016800701 | G14: {=1/INDEX($H$11:$V$11, 1, ROW(A3))} -> 2 | H14: {=1/INDEX($I$12:$V$12, 1, ROW(A2))} -> 0.5 | I14: {=1/INDEX($J$13:$V$13, 1, ROW(A1))} -> 2 | J14: 1 | K14: =1/4 -> 0.25 | L14: =1/5 -> 0.2 | M14: =1/3 -> 0.33333333 | N14: =1/2 -> 0.5 | O14: =1/2 -> 0.5 | P14: =1/5 -> 0.2 | Q14: =1/2 -> 0.5 | R14: =1/5 -> 0.2 | S14: =1/2 -> 0.5 | T14: =1/7 -> 0.14285714 | U14: =1/7 -> 0.14285714 | V14: =1/9 -> 0.11111111 | X14: =E14 -> Energy | Y14: =F14 -> 0.016800701 | AA14: =G14/SUM(G$11:G$26) -> 0.033333333 | AB14: =H14/SUM(H$11:H$26) -> 0.014018692 | AC14: =I14/SUM(I$11:I$26) -> 0.033333333 | AD14: =J14/SUM(J$11:J$26) -> 0.01754386 | AE14: =K14/SUM(K$11:K$26) -> 0.0050251256 | AF14: =L14/SUM(L$11:L$26) -> 0.012145749 | AG14: =M14/SUM(M$11:M$26) -> 0.01055409 | AH14: =N14/SUM(N$11:N$26) -> 0.015625 | ... AP14: =V14/SUM(V$11:V$26) -> 0.033524904
E15: Contribution | F15: =AVERAGE(AA15:AP15) -> 0.027463825 | G15: {=1/INDEX($H$11:$V$11, 1, ROW(A4))} -> 4 | H15: {=1/INDEX($I$12:$V$12, 1, ROW(A3))} -> 1 | I15: {=1/INDEX($J$13:$V$13, 1, ROW(A2))} -> 4 | J15: {=1/INDEX($K$14:$V$14, 1, ROW(A1))} -> 4 | K15: 1 | L15: =1/5 -> 0.2 | M15: =1/3 -> 0.33333333 | N15: =1/2 -> 0.5 | O15: 1 | P15: =1/5 -> 0.2 | Q15: 1 | R15: =1/5 -> 0.2 | S15: =1/2 -> 0.5 | T15: =1/7 -> 0.14285714 | U15: =1/7 -> 0.14285714 | V15: =1/9 -> 0.11111111 | X15: =E15 -> Contribution | Y15: =F15 -> 0.027463825 | AA15: =G15/SUM(G$11:G$26) -> 0.066666667 | AB15: =H15/SUM(H$11:H$26) -> 0.028037383 | AC15: =I15/SUM(I$11:I$26) -> 0.066666667 | AD15: =J15/SUM(J$11:J$26) -> 0.070175439 | AE15: =K15/SUM(K$11:K$26) -> 0.020100503 | AF15: =L15/SUM(L$11:L$26) -> 0.012145749 | AG15: =M15/SUM(M$11:M$26) -> 0.01055409 | AH15: =N15/SUM(N$11:N$26) -> 0.015625 | ... AP15: =V15/SUM(V$11:V$26) -> 0.033524904
E16: Development | F16: =AVERAGE(AA16:AP16) -> 0.072329609 | G16: {=1/INDEX($H$11:$V$11, 1, ROW(A5))} -> 5 | H16: {=1/INDEX($I$12:$V$12, 1, ROW(A4))} -> 3 | I16: {=1/INDEX($J$13:$V$13, 1, ROW(A3))} -> 5 | J16: {=1/INDEX($K$14:$V$14, 1, ROW(A2))} -> 5 | K16: {=1/INDEX($L$15:$V$15, 1, ROW(A1))} -> 5 | L16: 1 | M16: 3 | N16: 3 | O16: 3 | P16: 2 | Q16: 2 | R16: =1/2 -> 0.5 | S16: 3 | T16: =1/2 -> 0.5 | U16: =1/3 -> 0.33333333 | V16: =1/5 -> 0.2 | X16: =E16 -> Development | Y16: =F16 -> 0.072329609 | AA16: =G16/SUM(G$11:G$26) -> 0.083333333 | AB16: =H16/SUM(H$11:H$26) -> 0.08411215 | AC16: =I16/SUM(I$11:I$26) -> 0.083333333 | AD16: =J16/SUM(J$11:J$26) -> 0.087719298 | AE16: =K16/SUM(K$11:K$26) -> 0.10050251 | AF16: =L16/SUM(L$11:L$26) -> 0.060728745 | AG16: =M16/SUM(M$11:M$26) -> 0.094986807 | AH16: =N16/SUM(N$11:N$26) -> 0.09375 | ... AP16: =V16/SUM(V$11:V$26) -> 0.060344828
E17: Operation | F17: =AVERAGE(AA17:AP17) -> 0.039499062 | G17: {=1/INDEX($H$11:$V$11, 1, ROW(A6))} -> 3 | H17: {=1/INDEX($I$12:$V$12, 1, ROW(A5))} -> 2 | I17: {=1/INDEX($J$13:$V$13, 1, ROW(A4))} -> 3 | J17: {=1/INDEX($K$14:$V$14, 1, ROW(A3))} -> 3 | K17: {=1/INDEX($L$15:$V$15, 1, ROW(A2))} -> 3 | L17: {=1/INDEX($M$16:$V$16, 1, ROW(A1))} -> 0.33333333 | M17: 1 | N17: =1/2 -> 0.5 | O17: 4 | P17: =1/2 -> 0.5 | Q17: 2 | R17: =1/3 -> 0.33333333 | S17: 1 | T17: =1/5 -> 0.2 | U17: =1/5 -> 0.2 | V17: =1/7 -> 0.14285714 | X17: =E17 -> Operation | Y17: =F17 -> 0.039499062 | AA17: =G17/SUM(G$11:G$26) -> 0.05 | AB17: =H17/SUM(H$11:H$26) -> 0.056074766 | AC17: =I17/SUM(I$11:I$26) -> 0.05 | AD17: =J17/SUM(J$11:J$26) -> 0.052631579 | AE17: =K17/SUM(K$11:K$26) -> 0.060301508 | AF17: =L17/SUM(L$11:L$26) -> 0.020242915 | AG17: =M17/SUM(M$11:M$26) -> 0.031662269 | AH17: =N17/SUM(N$11:N$26) -> 0.015625 | ... AP17: =V17/SUM(V$11:V$26) -> 0.043103448
E18: Service | F18: =AVERAGE(AA18:AP18) -> 0.032182246 | G18: {=1/INDEX($H$11:$V$11, 1, ROW(A7))} -> 2 | H18: {=1/INDEX($I$12:$V$12, 1, ROW(A6))} -> 1 | I18: {=1/INDEX($J$13:$V$13, 1, ROW(A5))} -> 2 | J18: {=1/INDEX($K$14:$V$14, 1, ROW(A4))} -> 2 | K18: {=1/INDEX($L$15:$V$15, 1, ROW(A3))} -> 2 | L18: {=1/INDEX($M$16:$V$16, 1, ROW(A2))} -> 0.33333333 | M18: {=1/INDEX($N$17:$V$17, 1, ROW(A1))} -> 2 | N18: 1 | O18: 2 | P18: =1/2 -> 0.5 | Q18: 1 | R18: =1/3 -> 0.33333333 | S18: 1 | T18: =1/5 -> 0.2 | U18: =1/5 -> 0.2 | V18: =1/7 -> 0.14285714 | X18: =E18 -> Service | Y18: =F18 -> 0.032182246 | AA18: =G18/SUM(G$11:G$26) -> 0.033333333 | AB18: =H18/SUM(H$11:H$26) -> 0.028037383 | AC18: =I18/SUM(I$11:I$26) -> 0.033333333 | AD18: =J18/SUM(J$11:J$26) -> 0.035087719 | AE18: =K18/SUM(K$11:K$26) -> 0.040201005 | AF18: =L18/SUM(L$11:L$26) -> 0.020242915 | AG18: =M18/SUM(M$11:M$26) -> 0.063324538 | AH18: =N18/SUM(N$11:N$26) -> 0.03125 | ... AP18: =V18/SUM(V$11:V$26) -> 0.043103448
E19: Prerequisite | F19: =AVERAGE(AA19:AP19) -> 0.025862154 | G19: {=1/INDEX($H$11:$V$11, 1, ROW(A8))} -> 2 | H19: {=1/INDEX($I$12:$V$12, 1, ROW(A7))} -> 1 | I19: {=1/INDEX($J$13:$V$13, 1, ROW(A6))} -> 2 | J19: {=1/INDEX($K$14:$V$14, 1, ROW(A5))} -> 2 | K19: {=1/INDEX($L$15:$V$15, 1, ROW(A4))} -> 1 | L19: {=1/INDEX($M$16:$V$16, 1, ROW(A3))} -> 0.33333333 | M19: {=1/INDEX($N$17:$V$17, 1, ROW(A2))} -> 0.25 | N19: {=1/INDEX($O$18:$V$18, 1, ROW(A1))} -> 0.5 | O19: 1 | P19: =1/2 -> 0.5 | Q19: 3 | R19: =1/4 -> 0.25 | S19: 1 | T19: =1/9 -> 0.11111111 | U19: =1/9 -> 0.11111111 | V19: =1/9 -> 0.11111111 | X19: =E19 -> Prerequisite | Y19: =F19 -> 0.025862154 | AA19: =G19/SUM(G$11:G$26) -> 0.033333333 | AB19: =H19/SUM(H$11:H$26) -> 0.028037383 | AC19: =I19/SUM(I$11:I$26) -> 0.033333333 | AD19: =J19/SUM(J$11:J$26) -> 0.035087719 | AE19: =K19/SUM(K$11:K$26) -> 0.020100503 | AF19: =L19/SUM(L$11:L$26) -> 0.020242915 | AG19: =M19/SUM(M$11:M$26) -> 0.0079155673 | AH19: =N19/SUM(N$11:N$26) -> 0.015625 | ... AP19: =V19/SUM(V$11:V$26) -> 0.033524904
E20: Coordination | F20: =AVERAGE(AA20:AP20) -> 0.059569888 | G20: {=1/INDEX($H$11:$V$11, 1, ROW(A9))} -> 5 | H20: {=1/INDEX($I$12:$V$12, 1, ROW(A8))} -> 3 | I20: {=1/INDEX($J$13:$V$13, 1, ROW(A7))} -> 5 | J20: {=1/INDEX($K$14:$V$14, 1, ROW(A6))} -> 5 | K20: {=1/INDEX($L$15:$V$15, 1, ROW(A5))} -> 5 | L20: {=1/INDEX($M$16:$V$16, 1, ROW(A4))} -> 0.5 | M20: {=1/INDEX($N$17:$V$17, 1, ROW(A3))} -> 2 | N20: {=1/INDEX($O$18:$V$18, 1, ROW(A2))} -> 2 | O20: {=1/INDEX($P$19:$V$19, 1, ROW(A1))} -> 2 | P20: 1 | Q20: 5 | R20: =1/3 -> 0.33333333 | S20: 2 | T20: =1/5 -> 0.2 | U20: =1/7 -> 0.14285714 | V20: =1/9 -> 0.11111111 | X20: =E20 -> Coordination | Y20: =F20 -> 0.059569888 | AA20: =G20/SUM(G$11:G$26) -> 0.083333333 | AB20: =H20/SUM(H$11:H$26) -> 0.08411215 | AC20: =I20/SUM(I$11:I$26) -> 0.083333333 | AD20: =J20/SUM(J$11:J$26) -> 0.087719298 | AE20: =K20/SUM(K$11:K$26) -> 0.10050251 | AF20: =L20/SUM(L$11:L$26) -> 0.030364372 | AG20: =M20/SUM(M$11:M$26) -> 0.063324538 | AH20: =N20/SUM(N$11:N$26) -> 0.0625 | ... AP20: =V20/SUM(V$11:V$26) -> 0.033524904
E21: Definition | F21: =AVERAGE(AA21:AP21) -> 0.023287782 | G21: {=1/INDEX($H$11:$V$11, 1, ROW(A10))} -> 2 | H21: {=1/INDEX($I$12:$V$12, 1, ROW(A9))} -> 0.5 | I21: {=1/INDEX($J$13:$V$13, 1, ROW(A8))} -> 2 | J21: {=1/INDEX($K$14:$V$14, 1, ROW(A7))} -> 2 | K21: {=1/INDEX($L$15:$V$15, 1, ROW(A6))} -> 1 | L21: {=1/INDEX($M$16:$V$16, 1, ROW(A5))} -> 0.5 | M21: {=1/INDEX($N$17:$V$17, 1, ROW(A4))} -> 0.5 | N21: {=1/INDEX($O$18:$V$18, 1, ROW(A3))} -> 1 | O21: {=1/INDEX($P$19:$V$19, 1, ROW(A2))} -> 0.33333333 | P21: {=1/INDEX($Q$20:$V$20, 1, ROW(A1))} -> 0.2 | Q21: 1 | R21: =1/3 -> 0.33333333 | S21: =1/4 -> 0.25 | T21: =1/5 -> 0.2 | U21: =1/5 -> 0.2 | V21: =1/7 -> 0.14285714 | X21: =E21 -> Definition | Y21: =F21 -> 0.023287782 | AA21: =G21/SUM(G$11:G$26) -> 0.033333333 | AB21: =H21/SUM(H$11:H$26) -> 0.014018692 | AC21: =I21/SUM(I$11:I$26) -> 0.033333333 | AD21: =J21/SUM(J$11:J$26) -> 0.035087719 | AE21: =K21/SUM(K$11:K$26) -> 0.020100503 | AF21: =L21/SUM(L$11:L$26) -> 0.030364372 | AG21: =M21/SUM(M$11:M$26) -> 0.015831135 | AH21: =N21/SUM(N$11:N$26) -> 0.03125 | ... AP21: =V21/SUM(V$11:V$26) -> 0.043103448
E22: Contractual | F22: =AVERAGE(AA22:AP22) -> 0.08252224 | G22: {=1/INDEX($H$11:$V$11, 1, ROW(A11))} -> 5 | H22: {=1/INDEX($I$12:$V$12, 1, ROW(A10))} -> 3 | I22: {=1/INDEX($J$13:$V$13, 1, ROW(A9))} -> 5 | J22: {=1/INDEX($K$14:$V$14, 1, ROW(A8))} -> 5 | K22: {=1/INDEX($L$15:$V$15, 1, ROW(A7))} -> 5 | L22: {=1/INDEX($M$16:$V$16, 1, ROW(A6))} -> 2 | M22: {=1/INDEX($N$17:$V$17, 1, ROW(A5))} -> 3 | N22: {=1/INDEX($O$18:$V$18, 1, ROW(A4))} -> 3 | O22: {=1/INDEX($P$19:$V$19, 1, ROW(A3))} -> 4 | P22: {=1/INDEX($Q$20:$V$20, 1, ROW(A2))} -> 3 | Q22: {=1/INDEX($R$21:$V$21, 1, ROW(A1))} -> 3 | R22: 1 | S22: 2 | T22: =1/2 -> 0.5 | U22: =1/2 -> 0.5 | V22: =1/5 -> 0.2 | X22: =E22 -> Contractual | Y22: =F22 -> 0.08252224 | AA22: =G22/SUM(G$11:G$26) -> 0.083333333 | AB22: =H22/SUM(H$11:H$26) -> 0.08411215 | AC22: =I22/SUM(I$11:I$26) -> 0.083333333 | AD22: =J22/SUM(J$11:J$26) -> 0.087719298 | AE22: =K22/SUM(K$11:K$26) -> 0.10050251 | AF22: =L22/SUM(L$11:L$26) -> 0.12145749 | AG22: =M22/SUM(M$11:M$26) -> 0.094986807 | AH22: =N22/SUM(N$11:N$26) -> 0.09375 | ... AP22: =V22/SUM(V$11:V$26) -> 0.060344828
E23: Deliverable | F23: =AVERAGE(AA23:AP23) -> 0.036576736 | G23: {=1/INDEX($H$11:$V$11, 1, ROW(A12))} -> 2 | H23: {=1/INDEX($I$12:$V$12, 1, ROW(A11))} -> 2 | I23: {=1/INDEX($J$13:$V$13, 1, ROW(A10))} -> 2 | J23: {=1/INDEX($K$14:$V$14, 1, ROW(A9))} -> 2 | K23: {=1/INDEX($L$15:$V$15, 1, ROW(A8))} -> 2 | L23: {=1/INDEX($M$16:$V$16, 1, ROW(A7))} -> 0.33333333 | M23: {=1/INDEX($N$17:$V$17, 1, ROW(A6))} -> 1 | N23: {=1/INDEX($O$18:$V$18, 1, ROW(A5))} -> 1 | O23: {=1/INDEX($P$19:$V$19, 1, ROW(A4))} -> 1 | P23: {=1/INDEX($Q$20:$V$20, 1, ROW(A3))} -> 0.5 | Q23: {=1/INDEX($R$21:$V$21, 1, ROW(A2))} -> 4 | R23: {=1/INDEX($S$22:$V$22, 1, ROW(A1))} -> 0.5 | S23: 1 | T23: =1/3 -> 0.33333333 | U23: =1/5 -> 0.2 | V23: =1/7 -> 0.14285714 | X23: =E23 -> Deliverable | Y23: =F23 -> 0.036576736 | AA23: =G23/SUM(G$11:G$26) -> 0.033333333 | AB23: =H23/SUM(H$11:H$26) -> 0.056074766 | AC23: =I23/SUM(I$11:I$26) -> 0.033333333 | AD23: =J23/SUM(J$11:J$26) -> 0.035087719 | AE23: =K23/SUM(K$11:K$26) -> 0.040201005 | AF23: =L23/SUM(L$11:L$26) -> 0.020242915 | AG23: =M23/SUM(M$11:M$26) -> 0.031662269 | AH23: =N23/SUM(N$11:N$26) -> 0.03125 | ... AP23: =V23/SUM(V$11:V$26) -> 0.043103448
E24: Financial | F24: =AVERAGE(AA24:AP24) -> 0.12592554 | G24: {=1/INDEX($H$11:$V$11, 1, ROW(A13))} -> 7 | H24: {=1/INDEX($I$12:$V$12, 1, ROW(A12))} -> 5 | I24: {=1/INDEX($J$13:$V$13, 1, ROW(A11))} -> 7 | J24: {=1/INDEX($K$14:$V$14, 1, ROW(A10))} -> 7 | K24: {=1/INDEX($L$15:$V$15, 1, ROW(A9))} -> 7 | L24: {=1/INDEX($M$16:$V$16, 1, ROW(A8))} -> 2 | M24: {=1/INDEX($N$17:$V$17, 1, ROW(A7))} -> 5 | N24: {=1/INDEX($O$18:$V$18, 1, ROW(A6))} -> 5 | O24: {=1/INDEX($P$19:$V$19, 1, ROW(A5))} -> 9 | P24: {=1/INDEX($Q$20:$V$20, 1, ROW(A4))} -> 5 | Q24: {=1/INDEX($R$21:$V$21, 1, ROW(A3))} -> 5 | R24: {=1/INDEX($S$22:$V$22, 1, ROW(A2))} -> 2 | S24: {=1/INDEX($T$23:$V$23, 1, ROW(A1))} -> 3 | T24: 1 | U24: =1/2 -> 0.5 | V24: =1/5 -> 0.2 | X24: =E24 -> Financial | Y24: =F24 -> 0.12592554 | AA24: =G24/SUM(G$11:G$26) -> 0.11666667 | AB24: =H24/SUM(H$11:H$26) -> 0.14018692 | AC24: =I24/SUM(I$11:I$26) -> 0.11666667 | AD24: =J24/SUM(J$11:J$26) -> 0.12280702 | AE24: =K24/SUM(K$11:K$26) -> 0.14070352 | AF24: =L24/SUM(L$11:L$26) -> 0.12145749 | AG24: =M24/SUM(M$11:M$26) -> 0.15831135 | AH24: =N24/SUM(N$11:N$26) -> 0.15625 | ... AP24: =V24/SUM(V$11:V$26) -> 0.060344828
E25: Legal | F25: =AVERAGE(AA25:AP25) -> 0.15074309 | G25: {=1/INDEX($H$11:$V$11, 1, ROW(A14))} -> 7 | H25: {=1/INDEX($I$12:$V$12, 1, ROW(A13))} -> 5 | I25: {=1/INDEX($J$13:$V$13, 1, ROW(A12))} -> 7 | J25: {=1/INDEX($K$14:$V$14, 1, ROW(A11))} -> 7 | K25: {=1/INDEX($L$15:$V$15, 1, ROW(A10))} -> 7 | L25: {=1/INDEX($M$16:$V$16, 1, ROW(A9))} -> 3 | M25: {=1/INDEX($N$17:$V$17, 1, ROW(A8))} -> 5 | N25: {=1/INDEX($O$18:$V$18, 1, ROW(A7))} -> 5 | O25: {=1/INDEX($P$19:$V$19, 1, ROW(A6))} -> 9 | P25: {=1/INDEX($Q$20:$V$20, 1, ROW(A5))} -> 7 | Q25: {=1/INDEX($R$21:$V$21, 1, ROW(A4))} -> 5 | R25: {=1/INDEX($S$22:$V$22, 1, ROW(A3))} -> 2 | S25: {=1/INDEX($T$23:$V$23, 1, ROW(A2))} -> 5 | T25: {=1/INDEX($U$24:$V$24, 1, ROW(A1))} -> 2 | U25: 1 | V25: =1/3 -> 0.33333333 | X25: =E25 -> Legal | Y25: =F25 -> 0.15074309 | AA25: =G25/SUM(G$11:G$26) -> 0.11666667 | AB25: =H25/SUM(H$11:H$26) -> 0.14018692 | AC25: =I25/SUM(I$11:I$26) -> 0.11666667 | AD25: =J25/SUM(J$11:J$26) -> 0.12280702 | AE25: =K25/SUM(K$11:K$26) -> 0.14070352 | AF25: =L25/SUM(L$11:L$26) -> 0.18218623 | AG25: =M25/SUM(M$11:M$26) -> 0.15831135 | AH25: =N25/SUM(N$11:N$26) -> 0.15625 | ... AP25: =V25/SUM(V$11:V$26) -> 0.10057471
E26: Political | F26: =AVERAGE(AA26:AP26) -> 0.25070842 | G26: {=1/INDEX($H$11:$V$11, 1, ROW(A15))} -> 9 | H26: {=1/INDEX($I$12:$V$12, 1, ROW(A14))} -> 7 | I26: {=1/INDEX($J$13:$V$13, 1, ROW(A13))} -> 9 | J26: {=1/INDEX($K$14:$V$14, 1, ROW(A12))} -> 9 | K26: {=1/INDEX($L$15:$V$15, 1, ROW(A11))} -> 9 | L26: {=1/INDEX($M$16:$V$16, 1, ROW(A10))} -> 5 | M26: {=1/INDEX($N$17:$V$17, 1, ROW(A9))} -> 7 | N26: {=1/INDEX($O$18:$V$18, 1, ROW(A8))} -> 7 | O26: {=1/INDEX($P$19:$V$19, 1, ROW(A7))} -> 9 | P26: {=1/INDEX($Q$20:$V$20, 1, ROW(A6))} -> 9 | Q26: {=1/INDEX($R$21:$V$21, 1, ROW(A5))} -> 7 | R26: {=1/INDEX($S$22:$V$22, 1, ROW(A4))} -> 5 | S26: {=1/INDEX($T$23:$V$23, 1, ROW(A3))} -> 7 | T26: {=1/INDEX($U$24:$V$24, 1, ROW(A2))} -> 5 | U26: {=1/INDEX($V$25:$V$25, 1, ROW(A1))} -> 3 | V26: 1 | X26: =E26 -> Political | Y26: =F26 -> 0.25070842 | AA26: =G26/SUM(G$11:G$26) -> 0.15 | AB26: =H26/SUM(H$11:H$26) -> 0.19626168 | AC26: =I26/SUM(I$11:I$26) -> 0.15 | AD26: =J26/SUM(J$11:J$26) -> 0.15789474 | AE26: =K26/SUM(K$11:K$26) -> 0.18090452 | AF26: =L26/SUM(L$11:L$26) -> 0.30364372 | AG26: =M26/SUM(M$11:M$26) -> 0.22163588 | AH26: =N26/SUM(N$11:N$26) -> 0.21875 | ... AP26: =V26/SUM(V$11:V$26) -> 0.30172414
F27: =SUM(F11:F26) -> 1

Sheet Financial Interface
A1: Compared Interface | B1: Saaty Score | C1: Explanation
A2: Legal | B2: 1/2 | C2: Legal interfaces include regulatory enforcement and compliance regimes that often govern financial mechanisms, making them slightly more complex. | E2: 1/2 | F2: 1/5
A3: Political | B3: 1/5 | C3: Political interfaces add instability, jurisdictional overlap, and stakeholder-driven conflict, making them significantly more complex than financial structures.

Sheet Legal Interface
A1: Compared Interface | B1: Saaty Score | C1: Explanation
A2: Political | B2: 1/3 | C2: Legal interfaces are structured around defined rules and compliance processes, while political interfaces introduce uncertainty, stakeholder conflict, and dynamic jurisdictional challenges—making them more complex overall.

Sheet Operation Interface
A1: Compared Interface | B1: Saaty Score | C1: Explanation
A2: Service | B2: 1/2 | C2: Service interfaces introduce maintenance scheduling and dependency management, which adds more lifecycle complexity than real-time operations alone. | E2: 1/2 | F2: 3 | G2: 1/2 | H2: 1/2 | I2: 1/3 | J2: 1 | K2: 1/5 | L2: 1/5 | M2: 1/7
A3: Prerequisite | B3: 3 | C3: Operations are dynamic and involve decision-making and execution, whereas prerequisites are static temporal conditions.
A4: Coordination | B4: 1/2 | C4: While operations are complex, coordination involves dynamic synchronization across domains, often making it slightly more complex.
A5: Definition | B5: 1/2 | C5: Definition interfaces determine the scope and control of operations; they shape them but are often more abstract and systemic.
A6: Contractual | B6: 1/3 | C6: Contracts govern who operates what, with embedded legal and financial structures, introducing significantly more oversight complexity.
A7: Deliverable | B7: 1 | C7: Deliverables and operations are similar in structure and execution demands, with neither clearly more complex in all cases.
A8: Financial | B8: 1/5 | C8: Financial interfaces involve budget cycles, reimbursements, and governance, far more complex than executing plans.
A9: Legal | B9: 1/5 | C9: Legal constraints can block, enable, or complicate operations — often introducing layers of complexity beyond tactical execution.
A10: Political | B10: 1/7 | C10: Political factors dictate operational authority and can override plans, making them significantly more complex than operational logic.

Sheet Service Interface
A1: Compared Interface | B1: Saaty Score | C1: Explanation
A2: Prerequisite | B2: 5 | C2: Prerequisite interfaces are logical orderings, while service interfaces involve lifecycle dependencies, maintenance timing, and platform access, which are significantly more complex. | E2: 5 | F2: 1/2 | G2: 1/2 | H2: 1/3 | I2: 1 | J2: 1/5 | K2: 1/5 | L2: 1/7
A3: Coordination | B3: 1/2 | C3: Coordination involves real-time, multi-party alignment, often surpassing the logistical complexity of service activities.
A4: Definition | B4: 1/2 | C4: Definitions shape expectations, processes, and compliance across systems, introducing abstract and far-reaching complexity compared to service logistics.
A5: Contractual | B5: 1/3 | C5: Contracts embed formal expectations, penalties, and legal boundaries, adding more complexity than routine or scheduled service interactions.
A6: Deliverable | B6: 1 | C6: Deliverables and services both require timing, quality assurance, and transfer mechanisms, with comparable complexity.
A7: Financial | B7: 1/5 | C7: Financial interfaces involve budget allocations, cross-jurisdiction agreements, and reimbursement logistics—more complex than service provision.
A8: Legal | B8: 1/5 | C8: Legal interfaces require compliance with regulatory frameworks and audits, adding complexity far beyond physical maintenance.
A9: Political | B9: 1/7 | C9: Political interfaces involve authority negotiations and decision overrides, significantly more complex than executing scheduled services.

Sheet Prereq Interface
A1: Compared Interface | B1: Saaty Score | C1: Explanation
A2: Coordination | B2: 1/5 | C2: Coordination involves dynamic task, timing, and spatial alignment, which adds significantly more complexity than static sequencing logic. | E2: 1/5 | F2: 1/3 | G2: 1/7 | H2: 1/2 | I2: 1/9 | J2: 1/9 | K2: 1/9
A3: Definition | B3: 1/3 | C3: Definitions set standards and execution rules across organizations, adding more systemic complexity than a simple prerequisite condition.
A4: Contractual | B4: 1/7 | C4: Contracts govern rights, obligations, and penalties, introducing legal and organizational complexity far beyond functional dependencies.
A5: Deliverable | B5: 1/2 | C5: Deliverables involve format, content, timing, and quality control, making them moderately more complex than temporal preconditions.
A6: Financial | B6: 1/9 | C6: Financial agreements span budgeting, reimbursement, and multilateral funding structures, introducing deep systemic complexity.
A7: Legal | B7: 1/9 | C7: Legal constraints affect compliance, policy interpretation, and enforcement, far more complex than functional logic sequencing.
A8: Political | B8: 1/9 | C8: Political interfaces involve authority struggles, prioritization shifts, and jurisdictional disputes—orders of magnitude more complex.

Sheet Coordination Interface
A1: Compared Interface | B1: Saaty Score | C1: Explanation
A2: Definition | B2: 1 | C2: Both coordination and definition shape how functions operate—coordination dynamically aligns execution, while definition frames it structurally. | E2: 1 | F2: 1/3 | G2: 2 | H2: 1/5 | I2: 1/7 | J2: 1/9
A3: Contractual | B3: 1/3 | C3: Contracts carry legal weight, compliance monitoring, and risk management—adding more complexity than dynamic task alignment.
A4: Deliverable | B4: 2 | C4: Deliverables are output-specific and bounded, whereas coordination spans timing, location, and interdependencies across systems.
A5: Financial | B5: 1/5 | C5: Financial structures involve authority, timelines, and often politics—adding deeply embedded complexity compared to synchronization efforts.
A6: Legal | B6: 1/7 | C6: Legal systems include constraints, enforcement mechanisms, and regulation, introducing more systemic burden than coordination.
A7: Political | B7: 1/9 | C7: Political dynamics bring unpredictability, competing interests, and jurisdictional overlays, far more complex than operational coordination.

Sheet Definition Interface
A1: Compared Interface | B1: Saaty Score | C1: Explanation
A2: Contractual | B2: 1/3 | C2: Contracts introduce legal enforceability, obligations, and penalties, making them more complex than the structural role of definitions. | E2: 1/3 | F2: 2 | G2: 1/5 | H2: 1/5 | I2: 1/7
A3: Deliverable | B3: 2 | C3: Definitions set the scope and frequency of deliverables, but deliverables are bounded tasks, giving definitions more systemic influence.
A4: Financial | B4: 1/5 | C4: Financial interfaces involve multi-party funding flows and controls—more layered and bureaucratic than scope-setting definitions.
A5: Legal | B5: 1/5 | C5: Legal interfaces carry regulatory enforcement, which can override or restrict definitions and create institutional complexity.
A6: Political | B6: 1/7 | C6: Political interfaces introduce dynamic and unpredictable authority conflicts that far exceed the procedural role of definitions.

Sheet Contractual Interface
A1: Compared Interface | B1: Saaty Score | C1: Explanation
A2: Deliverable | B2: 2 | C2: Contracts define expectations, timelines, penalties, and enforcement, which makes them more complex than bounded output-based deliverables. | E2: 2 | F2: 1/2 | G2: 1/2 | H2: 1/5
A3: Financial | B3: 1/2 | C3: Financial interfaces can be more complex due to budget cycles, cost-sharing arrangements, and reimbursement procedures crossing agencies and fiscal systems.
A4: Legal | B4: 1/2 | C4: While contracts may be legally binding, legal interfaces span laws, enforcement, and compliance audits—often more systemically complex.
A5: Political | B5: 1/5 | C5: Political interfaces involve stakeholder power, negotiations, and external overrides, making them significantly more complex than contractual agreements.

Sheet Energy Interface
A1: Compared Interface | B1: Saaty Score | C1: Explanation
A2: Contribution | B2: 1 | C2: Energy and contribution interfaces both support other systems, but energy requires technical integration and reliability management. | E2: 1 | F2: 1/5 | G2: 1/3 | H2: 1/2 | I2: 2 | J2: 1/5 | K2: 1/3 | L2: 1/5 | M2: 1/2 | N2: 1/7 | O2: 1/7 | P2: 1/9
A3: Development | B3: 1/5 | C3: Co-development introduces long-term architectural, institutional, and scheduling complexity far beyond energy supply interfaces.
A4: Operation | B4: 1/3 | C4: Operational interfaces involve control, execution, and authority complexity, which is higher than technical power transfer.
A5: Service | B5: 1/2 | C5: Service includes diagnostic, scheduling, and physical access complexity, making it somewhat more complex than energy flow.
A6: Prerequisite | B6: 2 | C6: Sequencing interfaces are simpler logic constructs compared to continuous technical energy delivery.
A7: Coordination | B7: 1/5 | C7: Coordinating across domains and timescales introduces dynamic complexity well beyond power provisioning.
A8: Definition | B8: 1/3 | C8: Defining functional boundaries and performance scope can impact multiple systems and introduce more abstract complexity than energy delivery.
A9: Contractual | B9: 1/5 | C9: Contracts bring in legal, operational, and financial implications, significantly more complex than technical power interfaces.
A10: Deliverable | B10: 1/2 | C10: Deliverables often bundle outputs and may involve multiple systems, making them more complex than steady energy exchange.
A11: Financial | B11: 1/7 | C11: Financial interfaces require budget alignment and authority, adding complexity layers energy transfer lacks.
A12: Legal | B12: 1/7 | C12: Legal restrictions, enforcement, and liability structures add far more systemic complexity than technical power coupling.
A13: Political | B13: 1/9 | C13: Power dynamics, jurisdictional control, and unpredictability in political interfaces vastly exceed technical energy concerns.

Sheet Contribution Interface
A1: Compared Interface | B1: Saaty Score | C1: Explanation
A2: Development | B2: 1/5 | C2: Development involves co-creation and architectural integration over time, making it significantly more complex than simple functional contribution. | E2: 1/5 | F2: 1/3 | G2: 1/2 | H2: 2 | I2: 1/5 | J2: 1/3 | K2: 1/5 | L2: 1/2 | M2: 1/7 | N2: 1/7 | O2: 1/9
A3: Operation | B3: 1/3 | C3: Operational interfaces require dynamic execution and shared control, which is more complex than enabling support through contribution.
A4: Service | B4: 1/2 | C4: Services involve logistics, maintenance schedules, and system compatibility, which add more complexity than static contribution relationships.
A5: Prerequisite | B5: 2 | C5: Sequencing logic is simpler than a structural or enabling function, making contribution moderately more complex.
A6: Coordination | B6: 1/5 | C6: Coordination requires synchronization across elements, teams, or timelines, making it far more complex than a one-way contribution.
A7: Definition | B7: 1/3 | C7: Definition impacts purpose, scope, and standardization, introducing higher-level complexity than enabling a function.
A8: Contractual | B8: 1/5 | C8: Contracts embed legal, financial, and operational constraints that exceed the complexity of enabling contribution.
A9: Deliverable | B9: 1/2 | C9: Deliverables typically specify timing and format, adding a structured complexity greater than ongoing functional contribution.
A10: Financial | B10: 1/7 | C10: Financial flows span multiple levels of abstraction — funding, control, and reimbursement — far more complex than functional support.
A11: Legal | B11: 1/7 | C11: Legal constraints can change over time, limit behavior, and add documentation requirements, which go beyond contributions.
A12: Political | B12: 1/9 | C12: Political interfaces involve ambiguity, control struggles, and stakeholder coordination, which are orders of magnitude more complex.

Sheet Development Interface
A1: Compared Interface | B1: Saaty Score | C1: Explanation
A2: Operation | B2: 3 | C2: Operations involve execution and control, but development involves multi-phase collaboration, technical integration, and long-term co-design, which adds more systemic complexity. | E2: 3 | F2: 3 | G2: 7 | H2: 2 | I2: 2 | J2: 1/2 | K2: 3 | L2: 1/2 | M2: 1/3 | N2: 1/5
A3: Service | B3: 3 | C3: While services involve lifecycle management, development introduces strategic and architectural alignment, which is more complex over time.
A4: Prerequisite | B4: 7 | C4: A prerequisite is a simple temporal logic, while development requires deep integration and planning, making it significantly more complex.
A5: Coordination | B5: 2 | C5: Coordination requires dynamic alignment, but development carries multi-stage, multi-stakeholder technical and organizational complexity.
A6: Definition | B6: 2 | C6: Definitions formalize scope and behavior, but development requires execution of that scope collaboratively, which adds implementation complexity.
A7: Contractual | B7: 1/2 | C7: Contracts can enforce and govern development work, and may add compliance and negotiation layers that outpace even technical complexity.
A8: Deliverable | B8: 3 | C8: A deliverable is a bounded output, while development is iterative, ongoing, and requires feedback, making it structurally more complex.
A9: Financial | B9: 1/2 | C9: Financial structures can be multi-tiered and politically influenced, sometimes making them even more complex than development agreements.
A10: Legal | B10: 1/3 | C10: Legal frameworks include enforcement, regulation, and documentation that often span and constrain development itself.
A11: Political | B11: 1/5 | C11: Political interfaces are highly unpredictable and involve power struggles, making them more complex than even multilateral development.

Sheet Mass Interface
A1: Compared Interface | B1: Saaty Score | C1: Explanation
A2: Information | B2: 1/3 | C2: Mass flows are typically more tangible and discrete, while information flows add complexity via routing, interpretation, and latency. | E2: 1/3 | F2: 1 | G2: 1/2 | H2: 1/2 | I2: 1/5 | J2: 1/3 | K2: 1/2 | L2: 2 | M2: 1/5 | N2: 1/5 | O2: 1/5 | P2: 1/2 | Q2: 1/7 | R2: 1/7 | S2: 1/9
A3: Physical | B3: 1 | C3: Both involve physical interaction; neither is significantly more complex than the other in most scenarios.
A4: Energy | B4: 1/2 | C4: Energy interfaces require compatibility and continuous management (e.g., power compatibility), making them slightly more complex.
A5: Contribution | B5: 1/2 | C5: Contribution interfaces add semantic and architectural dependencies, introducing more abstract complexity.
A6: Development | B6: 1/5 | C6: Co-development requires IP alignment, timeline sync, and architectural integration, adding far more complexity than physical mass transfer.
A7: Operation | B7: 1/3 | C7: Shared or delegated operations add organizational coordination complexity.
A8: Service | B8: 1/2 | C8: Service interfaces involve scheduling, maintenance cycles, and hardware access, which can be more complex than one-way mass flow.
A9: Prerequisite | B9: 2 | C9: A prerequisite is just a sequencing logic and generally simpler than physical exchange interfaces.
A10: Coordination | B10: 1/5 | C10: Cross-domain coordination (timing/location) introduces far more complexity than physical transport.
A11: Definition | B11: 1/5 | C11: Defining a function's scope/purpose impacts many elements and introduces policy and documentation complexity.
A12: Contractual | B12: 1/5 | C12: Formal contracts embed legal, operational, and financial terms, much more complex than physical delivery.
A13: Deliverable | B13: 1/2 | C13: Deliverables can span digital/physical and are often embedded in broader workflows, slightly more complex than mass.
A14: Financial | B14: 1/7 | C14: Funding agreements span agencies and timelines — significantly more complex than physical exchange.
... A16: Political | B16: 1/9 | C16: Political interfaces involve stakeholders, power dynamics, and unpredictability — the most complex domain.

Sheet Information Interface
A1: Compared Interface | B1: Saaty Score | C1: Explanation
A2: Physical | B2: 3 | C2: Information flows are more abstract and often require integration with networks, software, and interpretation layers, adding more complexity than simple physical interfaces. | E2: 3 | F2: 2 | G2: 2 | H2: 1/3 | I2: 1/2 | J2: 1 | K2: 3 | L2: 1/3 | M2: 1/2 | N2: 1/3 | O2: 1/2 | P2: 1/5 | Q2: 1/5 | R2: 1/7
A3: Energy | B3: 2 | C3: Energy flows require hardware compatibility and continuous delivery, but information interfaces often involve data models, latency, and protocol management.
A4: Contribution | B4: 2 | C4: Contributing functions can be abstract, but they usually don't involve the same integration and data processing layers as information interfaces.
A5: Development | B5: 1/3 | C5: Co-development introduces architectural integration and long-term complexity, often exceeding that of information flows.
A6: Operation | B6: 1/2 | C6: Joint or delegated operations involve command, control, and responsibility handoffs, which can exceed the complexity of pure information exchange.
A7: Service | B7: 1 | C7: Both information and service interfaces depend on timing and access; neither is clearly more complex in all contexts.
A8: Prerequisite | B8: 3 | C8: Sequencing constraints are simple compared to managing data interpretation, latency, and continuous flow.
A9: Coordination | B9: 1/3 | C9: Cross-domain coordination adds dynamic, time-critical complexity that exceeds that of typical data exchange.
A10: Definition | B10: 1/2 | C10: Defining a function adds institutional, semantic, and structural constraints that often affect downstream systems more than data flow.
A11: Contractual | B11: 1/3 | C11: Contracts include legal and performance implications beyond those of data transmission, making them more complex.
A12: Deliverable | B12: 1/2 | C12: Deliverables can be information-based, but are bounded and structured, whereas raw information flow often lacks that clarity.
A13: Financial | B13: 1/5 | C13: Financial agreements span timelines, stakeholders, and budgets, adding substantially more complexity than data interfaces.
A14: Legal | B14: 1/5 | C14: Legal interfaces include regulations, enforcement, and compliance structures, making them more complex than data flows.
A15: Political | B15: 1/7 | C15: Political dynamics add unpredictability and stakeholder conflicts that far exceed the structured nature of data exchange.

Sheet Physical Interface
A1: Compared Interface | B1: Saaty Score | C1: Explanation
A2: Energy | B2: 1/2 | C2: Energy transfers require technical compatibility and management of supply continuity, which introduces more complexity than physical co-location or docking. | E2: 1/2 | F2: 1 | G2: 1/5 | H2: 1/3 | I2: 1/2 | J2: 2 | K2: 1/5 | L2: 1/3 | M2: 1/5 | N2: 1/2 | O2: 1/7 | P2: 1/7 | Q2: 1/9
A3: Contribution | B3: 1 | C3: Physical and contribution interfaces can both be foundational but are relatively bounded in scope and complexity.
A4: Development | B4: 1/5 | C4: Development interfaces involve long-term co-creation, integration, and architectural dependencies, far more complex than physical proximity.
A5: Operation | B5: 1/3 | C5: Operations involve real-time control, authority delegation, and task execution complexity beyond mere physical interaction.
A6: Service | B6: 1/2 | C6: Service requires access timing, tools, and knowledge for maintenance, which adds a layer of complexity beyond physical interfaces.
A7: Prerequisite | B7: 2 | C7: Sequencing interfaces are logic-based and relatively simple compared to coordinating physical connection or access.
A8: Coordination | B8: 1/5 | C8: Cross-domain synchronization is abstract, continuous, and dynamic—much more complex than physical spatial interaction.
A9: Definition | B9: 1/3 | C9: Setting definitions affects institutional procedures and information structures, exceeding the static nature of physical interfaces.
A10: Contractual | B10: 1/5 | C10: Formal contracts imply legal, financial, and performance oversight — significantly more complex than physical interfaces.
A11: Deliverable | B11: 1/2 | C11: Deliverables are bounded outputs, often integrating multiple flows, and are typically more complex than physical actions alone.
A12: Financial | B12: 1/7 | C12: Financial interfaces include funding structures, reimbursement, and authority issues—well beyond physical coupling.
A13: Legal | B13: 1/7 | C13: Legal constraints require compliance and often restrict physical interaction itself, adding significant oversight complexity.
A14: Political | B14: 1/9 | C14: Political interfaces introduce authority conflict, stakeholder negotiation, and ambiguity, making them far more complex.

Sheet Deliverable Interface
A1: Compared Interface | B1: Saaty Score | C1: Explanation
A2: Financial | B2: 1/3 | C2: Financial interfaces involve funding cycles, cost allocation, and reimbursement protocols, which generally introduce more systemic complexity than producing and transferring deliverables. | E2: 1/3 | F2: 1/5 | G2: 1/7
A3: Legal | B3: 1/5 | C3: Legal interfaces require compliance, monitoring, enforcement, and interpretation—far beyond the scope of routine output delivery.
A4: Political | B4: 1/7 | C4: Political interfaces involve jurisdictional control, authority struggles, and shifting stakeholder influence, making them significantly more complex than deliverable handoffs.

Sheet C2 Interface Weights Summary
A1: Interface | B1: Complexity "Importance"
A2: ='C2 Interface Weights'!E26 -> Political | B2: ='C2 Interface Weights'!F26 -> 0.25070842
A3: ='C2 Interface Weights'!E25 -> Legal | B3: ='C2 Interface Weights'!F25 -> 0.15074309
A4: ='C2 Interface Weights'!E24 -> Financial | B4: ='C2 Interface Weights'!F24 -> 0.12592554
A5: ='C2 Interface Weights'!E22 -> Contractual | B5: ='C2 Interface Weights'!F22 -> 0.08252224
A6: ='C2 Interface Weights'!E16 -> Development | B6: ='C2 Interface Weights'!F16 -> 0.072329609
A7: ='C2 Interface Weights'!E20 -> Coordination | B7: ='C2 Interface Weights'!F20 -> 0.059569888
A8: ='C2 Interface Weights'!E17 -> Operation | B8: ='C2 Interface Weights'!F17 -> 0.039499062
A9: ='C2 Interface Weights'!E23 -> Deliverable | B9: ='C2 Interface Weights'!F23 -> 0.036576736
A10: ='C2 Interface Weights'!E18 -> Service | B10: ='C2 Interface Weights'!F18 -> 0.032182246
A11: ='C2 Interface Weights'!E12 -> Information | B11: ='C2 Interface Weights'!F12 -> 0.028774565
A12: ='C2 Interface Weights'!E15 -> Contribution | B12: ='C2 Interface Weights'!F15 -> 0.027463825
A13: ='C2 Interface Weights'!E19 -> Prerequisite | B13: ='C2 Interface Weights'!F19 -> 0.025862154
A14: ='C2 Interface Weights'!E21 -> Definition | B14: ='C2 Interface Weights'!F21 -> 0.023287782
A15: ='C2 Interface Weights'!E14 -> Energy | B15: ='C2 Interface Weights'!F14 -> 0.016800701
A16: ='C2 Interface Weights'!E13 -> Physical | B16: ='C2 Interface Weights'!F13 -> 0.013877066
A17: ='C2 Interface Weights'!E11 -> Mass | B17: ='C2 Interface Weights'!F11 -> 0.013877066

Sheet Function Criticality
B2: Rankings | E2: Key Note:
B3: Importance | C3: Definition | E3: Type metric name in gray
B4: 1 | C4: Equal Importance | E4: Only type comparison values in white areas
B5: 3 | C5: Moderate Importance
B6: 5 | C6: Strong Importance | E6: You have to open in the desktop app to copy and paste with the formulas
B7: 7 | C7: Very Strong Importance
B8: 9 | C8: Extreme Importance
E10: Functions | F10: Criticality Weights | G10: =E11 -> Deploy Air Assets | H10: =E12 -> Lead Tankers | I10: =E13 -> Supervise Air Attacks (AAGs) | J10: =E14 -> Drop Water | K10: =E15 -> Drop Fire Retardant | L10: =E16 -> Perform Post-Drop Assessment | M10: =E17 -> Dispatch To Reloading Base | N10: =E18 -> Deploy Ground Assets | O10: =E19 -> Establish Containment Lines | P10: =E20 -> Spill Water from Ground Assets | Q10: =E21 -> Tactically Monitor Fires | R10: =E22 -> Predict New Fires | S10: =E23 -> Detect Fires | T10: =E24 -> Visually Confirm Fires | U10: =E25 -> Predict Fire Paths/Behavior | V10: =E26 -> Strategically Monitor Fires | W10: =E27 -> Gather Real Time Data from Assets | X10: =E28 -> Build Real Time Situational Awareness | Y10: =E29 -> Coordinate Air & Ground Resources | Z10: =E30 -> Dynamically Allocate Resources | AA10: =E31 -> Issue Commands to Assets | AB10: =E32 -> Communicate to Resources | AC10: =E33 -> Maintain Communication Among Assets | AD10: =E34 -> Maintain Communication Between Assets and C3 | AE10: =E35 -> Deploy First Response Ground Assets | AF10: =E36 -> Deploy Smokejumpers | AG10: =E37 -> Activate MAFFS | AH10: =E38 -> Refuel Airborne Assets | AI10: =E39 -> Provide MRO for Assets | AJ10: =E40 -> Refill Water and Fire Retardants | AK10: =E41 -> Provide Logistic Support to Crews | AM10: Function | AN10: Value
E11: Deploy Air Assets | F11: =AVERAGE(AP11:BT11) -> 0.035885211 | G11: 1 | H11: 2 | I11: 2 | J11: 2 | K11: 2 | L11: =1/5 -> 0.2 | M11: 2 | N11: 1 | O11: 1 | P11: =1/3 -> 0.33333333 | Q11: 1 | R11: =1/2 -> 0.5 | S11: =1/2 -> 0.5 | T11: 2 | U11: =0.5 -> 0.5 | V11: 1 | W11: 1 | X11: 1 | Y11: 1 | Z11: 1 | AA11: =1/2 -> 0.5 | AB11: =1/2 -> 0.5 | AC11: =1/2 -> 0.5 | AD11: =1/3 -> 0.33333333 | AE11: 1 | AF11: 2 | AG11: 3 | AH11: 2 | AI11: 3 | AJ11: 3 | AK11: 5 | AM11: =E11 -> Deploy Air Assets | AN11: =F11 -> 0.035885211 | AP11: =G11/SUM(G$11:G$41) -> 0.02617801 | AQ11: =H11/SUM(H$11:H$41) -> 0.048 | AR11: =I11/SUM(I$11:I$41) -> 0.054054054 | AS11: =J11/SUM(J$11:J$41) -> 0.063424947 | AT11: =K11/SUM(K$11:K$41) -> 0.063424947 | AU11: =L11/SUM(L$11:L$41) -> 0.0039840637 | AV11: =M11/SUM(M$11:M$41) -> 0.042105263 | AW11: =N11/SUM(N$11:N$41) -> 0.038461538 | ... BT11: =AK11/SUM(AK$11:AK$41) -> 0.084745763
E12: Lead Tankers | F12: =AVERAGE(AP12:BT12) -> 0.034871282 | G12: {=1/INDEX($H$11:$AK$11, 1, ROW(A1))} -> 0.5 | H12: 1 | I12: 3 | J12: 4 | K12: 4 | L12: 3 | M12: 3 | N12: =1*1/2 -> 0.5 | O12: =1*1/2 -> 0.5 | P12: 3 | Q12: 1 | R12: =0.5 -> 0.5 | S12: =1/2 -> 0.5 | T12: =1/3 -> 0.33333333 | U12: =1/2 -> 0.5 | V12: =1/2 -> 0.5 | W12: =0.5 -> 0.5 | X12: =0.5 -> 0.5 | Y12: =1*1/2 -> 0.5 | Z12: =1*1/2 -> 0.5 | AA12: =1*1/2 -> 0.5 | AB12: =1*1/2 -> 0.5 | AC12: =1*1/2 -> 0.5 | AD12: =1*1/2 -> 0.5 | AE12: 1 | AF12: 1 | AG12: 1 | AH12: 2 | AI12: 2 | AJ12: 2 | AK12: 3 | AM12: =E12 -> Lead Tankers | AN12: =F12 -> 0.034871282 | AP12: =G12/SUM(G$11:G$41) -> 0.013089005 | AQ12: =H12/SUM(H$11:H$41) -> 0.024 | AR12: =I12/SUM(I$11:I$41) -> 0.081081081 | AS12: =J12/SUM(J$11:J$41) -> 0.12684989 | AT12: =K12/SUM(K$11:K$41) -> 0.12684989 | AU12: =L12/SUM(L$11:L$41) -> 0.059760956 | AV12: =M12/SUM(M$11:M$41) -> 0.063157895 | AW12: =N12/SUM(N$11:N$41) -> 0.019230769 | ... BT12: =AK12/SUM(AK$11:AK$41) -> 0.050847458
E13: Supervise Air Attacks (AAGs) | F13: =AVERAGE(AP13:BT13) -> 0.027309127 | G13: {=1/INDEX($H$11:$AK$11, 1, ROW(A2))} -> 0.5 | H13: {=1/INDEX($I$12:$AK$12, 1, ROW(A1))} -> 0.33333333 | I13: 1 | J13: 1 | K13: 1 | L13: 2 | M13: 2 | N13: 1 | O13: 1 | P13: 2 | Q13: 1 | R13: =0.5 -> 0.5 | S13: =1*1/3 -> 0.33333333 | T13: =1*1/2 -> 0.5 | U13: =1*1/2 -> 0.5 | V13: 1 | W13: 1 | X13: 1 | Y13: 1 | Z13: 1 | AA13: 1 | AB13: 1 | AC13: 1 | AD13: 1 | AE13: 1 | AF13: 1 | AG13: 1 | AH13: 1 | AI13: 1 | AJ13: 1 | AK13: 2 | AM13: =E13 -> Supervise Air Attacks (AAGs) | AN13: =F13 -> 0.027309127 | AP13: =G13/SUM(G$11:G$41) -> 0.013089005 | AQ13: =H13/SUM(H$11:H$41) -> 0.008 | AR13: =I13/SUM(I$11:I$41) -> 0.027027027 | AS13: =J13/SUM(J$11:J$41) -> 0.031712474 | AT13: =K13/SUM(K$11:K$41) -> 0.031712474 | AU13: =L13/SUM(L$11:L$41) -> 0.039840637 | AV13: =M13/SUM(M$11:M$41) -> 0.042105263 | AW13: =N13/SUM(N$11:N$41) -> 0.038461538 | ... BT13: =AK13/SUM(AK$11:AK$41) -> 0.033898305
E14: Drop Water | F14: =AVERAGE(AP14:BT14) -> 0.034905052 | G14: {=1/INDEX($H$11:$AK$11, 1, ROW(A3))} -> 0.5 | H14: {=1/INDEX($I$12:$AK$12, 1, ROW(A2))} -> 0.25 | I14: {=1/INDEX($J$13:$AK$13, 1, ROW(A1))} -> 1 | J14: 1 | K14: 1 | L14: 5 | M14: 3 | N14: 1 | O14: 1 | P14: 2 | Q14: 1 | R14: 1 | S14: 1 | T14: =1*1/2 -> 0.5 | U14: 1 | V14: 1 | W14: 1 | X14: 1 | Y14: 1 | Z14: 1 | AA14: 1 | AB14: 1 | AC14: 1 | AD14: 1 | AE14: 1 | AF14: 1 | AG14: 1 | AH14: 3 | AI14: 3 | AJ14: 2 | AK14: 3 | AM14: =E14 -> Drop Water | AN14: =F14 -> 0.034905052 | AP14: =G14/SUM(G$11:G$41) -> 0.013089005 | AQ14: =H14/SUM(H$11:H$41) -> 0.006 | AR14: =I14/SUM(I$11:I$41) -> 0.027027027 | AS14: =J14/SUM(J$11:J$41) -> 0.031712474 | AT14: =K14/SUM(K$11:K$41) -> 0.031712474 | AU14: =L14/SUM(L$11:L$41) -> 0.099601594 | AV14: =M14/SUM(M$11:M$41) -> 0.063157895 | AW14: =N14/SUM(N$11:N$41) -> 0.038461538 | ... BT14: =AK14/SUM(AK$11:AK$41) -> 0.050847458
E15: Drop Fire Retardant | F15: =AVERAGE(AP15:BT15) -> 0.034905052 | G15: {=1/INDEX($H$11:$AK$11, 1, ROW(A4))} -> 0.5 | H15: {=1/INDEX($I$12:$AK$12, 1, ROW(A3))} -> 0.25 | I15: {=1/INDEX($J$13:$AK$13, 1, ROW(A2))} -> 1 | J15: {=1/INDEX($K$14:$AK$14, 1, ROW(A1))} -> 1 | K15: 1 | L15: 5 | M15: 3 | N15: 1 | O15: 1 | P15: 2 | Q15: 1 | R15: 1 | S15: 1 | T15: =1*1/2 -> 0.5 | U15: 1 | V15: 1 | W15: 1 | X15: 1 | Y15: 1 | Z15: 1 | AA15: 1 | AB15: 1 | AC15: 1 | AD15: 1 | AE15: 1 | AF15: 1 | AG15: 1 | AH15: 3 | AI15: 3 | AJ15: 2 | AK15: 3 | AM15: =E15 -> Drop Fire Retardant | AN15: =F15 -> 0.034905052 | AP15: =G15/SUM(G$11:G$41) -> 0.013089005 | AQ15: =H15/SUM(H$11:H$41) -> 0.006 | AR15: =I15/SUM(I$11:I$41) -> 0.027027027 | AS15: =J15/SUM(J$11:J$41) -> 0.031712474 | AT15: =K15/SUM(K$11:K$41) -> 0.031712474 | AU15: =L15/SUM(L$11:L$41) -> 0.099601594 | AV15: =M15/SUM(M$11:M$41) -> 0.063157895 | AW15: =N15/SUM(N$11:N$41) -> 0.038461538 | ... BT15: =AK15/SUM(AK$11:AK$41) -> 0.050847458
E16: Perform Post-Drop Assessment | F16: =AVERAGE(AP16:BT16) -> 0.024850734 | G16: {=1/INDEX($H$11:$AK$11, 1, ROW(A5))} -> 5 | H16: {=1/INDEX($I$12:$AK$12, 1, ROW(A4))} -> 0.33333333 | I16: {=1/INDEX($J$13:$AK$13, 1, ROW(A3))} -> 0.5 | J16: {=1/INDEX($K$14:$AK$14, 1, ROW(A2))} -> 0.2 | K16: {=1/INDEX($L$15:$AK$15, 1, ROW(A1))} -> 0.2 | L16: 1 | M16: =1*1/2 -> 0.5 | N16: =1*1/3 -> 0.33333333 | O16: =1*1/3 -> 0.33333333 | P16: =1*1/2 -> 0.5 | Q16: =1*1/2 -> 0.5 | R16: 1 | S16: 1 | T16: 1 | U16: 1 | V16: 1 | W16: 1 | X16: 1 | Y16: 1 | Z16: 1 | AA16: 1 | AB16: 1 | AC16: 1 | AD16: 1 | AE16: =1*1/2 -> 0.5 | AF16: 1 | AG16: 1 | AH16: 1 | AI16: 1 | AJ16: 1 | AK16: =1*1/2 -> 0.5 | AM16: =E16 -> Perform Post-Drop Assessment | AN16: =F16 -> 0.024850734 | AP16: =G16/SUM(G$11:G$41) -> 0.13089005 | AQ16: =H16/SUM(H$11:H$41) -> 0.008 | AR16: =I16/SUM(I$11:I$41) -> 0.013513514 | AS16: =J16/SUM(J$11:J$41) -> 0.0063424947 | AT16: =K16/SUM(K$11:K$41) -> 0.0063424947 | AU16: =L16/SUM(L$11:L$41) -> 0.019920319 | AV16: =M16/SUM(M$11:M$41) -> 0.010526316 | AW16: =N16/SUM(N$11:N$41) -> 0.012820513 | ... BT16: =AK16/SUM(AK$11:AK$41) -> 0.0084745763
E17: Dispatch To Reloading Base | F17: =AVERAGE(AP17:BT17) -> 0.021583962 | G17: {=1/INDEX($H$11:$AK$11, 1, ROW(A6))} -> 0.5 | H17: {=1/INDEX($I$12:$AK$12, 1, ROW(A5))} -> 0.33333333 | I17: {=1/INDEX($J$13:$AK$13, 1, ROW(A4))} -> 0.5 | J17: {=1/INDEX($K$14:$AK$14, 1, ROW(A3))} -> 0.33333333 | K17: {=1/INDEX($L$15:$AK$15, 1, ROW(A2))} -> 0.33333333 | L17: {=1/INDEX($M$16:$AK$16, 1, ROW(A1))} -> 2 | M17: 1 | N17: =1*1/3 -> 0.33333333 | O17: =1*1/3 -> 0.33333333 | P17: =1*1/2 -> 0.5 | Q17: =1*1/2 -> 0.5 | R17: 1 | S17: 1 | T17: =1/2 -> 0.5 | U17: 1 | V17: 1 | W17: 1 | X17: 1 | Y17: 1 | Z17: 1 | AA17: 1 | AB17: 1 | AC17: 1 | AD17: 1 | AE17: =1*1/2 -> 0.5 | AF17: =1*1/2 -> 0.5 | AG17: 1 | AH17: 1 | AI17: 1 | AJ17: 1 | AK17: 1 | AM17: =E17 -> Dispatch To Reloading Base | AN17: =F17 -> 0.021583962 | AP17: =G17/SUM(G$11:G$41) -> 0.013089005 | AQ17: =H17/SUM(H$11:H$41) -> 0.008 | AR17: =I17/SUM(I$11:I$41) -> 0.013513514 | AS17: =J17/SUM(J$11:J$41) -> 0.010570825 | AT17: =K17/SUM(K$11:K$41) -> 0.010570825 | AU17: =L17/SUM(L$11:L$41) -> 0.039840637 | AV17: =M17/SUM(M$11:M$41) -> 0.021052632 | AW17: =N17/SUM(N$11:N$41) -> 0.012820513 | ... BT17: =AK17/SUM(AK$11:AK$41) -> 0.016949153
E18: Deploy Ground Assets | F18: =AVERAGE(AP18:BT18) -> 0.036459978 | G18: {=1/INDEX($H$11:$AK$11, 1, ROW(A7))} -> 1 | H18: {=1/INDEX($I$12:$AK$12, 1, ROW(A6))} -> 2 | I18: {=1/INDEX($J$13:$AK$13, 1, ROW(A5))} -> 1 | J18: {=1/INDEX($K$14:$AK$14, 1, ROW(A4))} -> 1 | K18: {=1/INDEX($L$15:$AK$15, 1, ROW(A3))} -> 1 | L18: {=1/INDEX($M$16:$AK$16, 1, ROW(A2))} -> 3 | M18: {=1/INDEX($N$17:$AK$17, 1, ROW(A1))} -> 3 | N18: 1 | O18: 1 | P18: 1 | Q18: 1 | R18: 1 | S18: 1 | T18: 1 | U18: 1 | V18: 1 | W18: 1 | X18: 1 | Y18: 1 | Z18: 1 | AA18: 1 | AB18: 1 | AC18: 2 | AD18: 3 | AE18: 1 | AF18: 2 | AG18: 2 | AH18: 2 | AI18: 1 | AJ18: 1 | AK18: 2 | AM18: =E18 -> Deploy Ground Assets | AN18: =F18 -> 0.036459978 | AP18: =G18/SUM(G$11:G$41) -> 0.02617801 | AQ18: =H18/SUM(H$11:H$41) -> 0.048 | AR18: =I18/SUM(I$11:I$41) -> 0.027027027 | AS18: =J18/SUM(J$11:J$41) -> 0.031712474 | AT18: =K18/SUM(K$11:K$41) -> 0.031712474 | AU18: =L18/SUM(L$11:L$41) -> 0.059760956 | AV18: =M18/SUM(M$11:M$41) -> 0.063157895 | AW18: =N18/SUM(N$11:N$41) -> 0.038461538 | ... BT18: =AK18/SUM(AK$11:AK$41) -> 0.033898305
E19: Establish Containment Lines | F19: =AVERAGE(AP19:BT19) -> 0.032282337 | G19: {=1/INDEX($H$11:$AK$11, 1, ROW(A8))} -> 1 | H19: {=1/INDEX($I$12:$AK$12, 1, ROW(A7))} -> 2 | I19: {=1/INDEX($J$13:$AK$13, 1, ROW(A6))} -> 1 | J19: {=1/INDEX($K$14:$AK$14, 1, ROW(A5))} -> 1 | K19: {=1/INDEX($L$15:$AK$15, 1, ROW(A4))} -> 1 | L19: {=1/INDEX($M$16:$AK$16, 1, ROW(A3))} -> 3 | M19: {=1/INDEX($N$17:$AK$17, 1, ROW(A2))} -> 3 | N19: {=1/INDEX($O$18:$AK$18, 1, ROW(A1))} -> 1 | O19: 1 | P19: 1 | Q19: 1 | R19: 2 | S19: =0.5 -> 0.5 | T19: =0.5 -> 0.5 | U19: 1 | V19: 1 | W19: 1 | X19: 1 | Y19: 1 | Z19: 1 | AA19: 1 | AB19: 1 | AC19: 1 | AD19: 1 | AE19: 1 | AF19: 2 | AG19: 2 | AH19: 1 | AI19: 1 | AJ19: 1 | AK19: 1 | AM19: =E19 -> Establish Containment Lines | AN19: =F19 -> 0.032282337 | AP19: =G19/SUM(G$11:G$41) -> 0.02617801 | AQ19: =H19/SUM(H$11:H$41) -> 0.048 | AR19: =I19/SUM(I$11:I$41) -> 0.027027027 | AS19: =J19/SUM(J$11:J$41) -> 0.031712474 | AT19: =K19/SUM(K$11:K$41) -> 0.031712474 | AU19: =L19/SUM(L$11:L$41) -> 0.059760956 | AV19: =M19/SUM(M$11:M$41) -> 0.063157895 | AW19: =N19/SUM(N$11:N$41) -> 0.038461538 | ... BT19: =AK19/SUM(AK$11:AK$41) -> 0.016949153
E20: Spill Water from Ground Assets | F20: =AVERAGE(AP20:BT20) -> 0.031946995 | G20: {=1/INDEX($H$11:$AK$11, 1, ROW(A9))} -> 3 | H20: {=1/INDEX($I$12:$AK$12, 1, ROW(A8))} -> 0.33333333 | I20: {=1/INDEX($J$13:$AK$13, 1, ROW(A7))} -> 0.5 | J20: {=1/INDEX($K$14:$AK$14, 1, ROW(A6))} -> 0.5 | K20: {=1/INDEX($L$15:$AK$15, 1, ROW(A5))} -> 0.5 | L20: {=1/INDEX($M$16:$AK$16, 1, ROW(A4))} -> 2 | M20: {=1/INDEX($N$17:$AK$17, 1, ROW(A3))} -> 2 | N20: {=1/INDEX($O$18:$AK$18, 1, ROW(A2))} -> 1 | O20: {=1/INDEX($P$19:$AK$19, 1, ROW(A1))} -> 1 | P20: 1 | Q20: 1 | R20: 2 | S20: 2 | T20: 1 | U20: 2 | V20: 1 | W20: 1 | X20: 1 | Y20: 1 | Z20: 1 | AA20: 1 | AB20: 1 | AC20: 1 | AD20: 1 | AE20: 1 | AF20: 1 | AG20: 1 | AH20: 1 | AI20: 1 | AJ20: 1 | AK20: 1 | AM20: =E20 -> Spill Water from Ground Assets | AN20: =F20 -> 0.031946995 | AP20: =G20/SUM(G$11:G$41) -> 0.078534031 | AQ20: =H20/SUM(H$11:H$41) -> 0.008 | AR20: =I20/SUM(I$11:I$41) -> 0.013513514 | AS20: =J20/SUM(J$11:J$41) -> 0.015856237 | AT20: =K20/SUM(K$11:K$41) -> 0.015856237 | AU20: =L20/SUM(L$11:L$41) -> 0.039840637 | AV20: =M20/SUM(M$11:M$41) -> 0.042105263 | AW20: =N20/SUM(N$11:N$41) -> 0.038461538 | ... BT20: =AK20/SUM(AK$11:AK$41) -> 0.016949153
E21: Tactically Monitor Fires | F21: =AVERAGE(AP21:BT21) -> 0.033290765 | G21: {=1/INDEX($H$11:$AK$11, 1, ROW(A10))} -> 1 | H21: {=1/INDEX($I$12:$AK$12, 1, ROW(A9))} -> 1 | I21: {=1/INDEX($J$13:$AK$13, 1, ROW(A8))} -> 1 | J21: {=1/INDEX($K$14:$AK$14, 1, ROW(A7))} -> 1 | K21: {=1/INDEX($L$15:$AK$15, 1, ROW(A6))} -> 1 | L21: {=1/INDEX($M$16:$AK$16, 1, ROW(A5))} -> 2 | M21: {=1/INDEX($N$17:$AK$17, 1, ROW(A4))} -> 2 | N21: {=1/INDEX($O$18:$AK$18, 1, ROW(A3))} -> 1 | O21: {=1/INDEX($P$19:$AK$19, 1, ROW(A2))} -> 1 | P21: {=1/INDEX($Q$20:$AK$20, 1, ROW(A1))} -> 1 | Q21: 1 | R21: 2 | S21: 2 | T21: 1 | U21: 3 | V21: 1 | W21: 1 | X21: 1 | Y21: 1 | Z21: 1 | AA21: 1 | AB21: 1 | AC21: 1 | AD21: 1 | AE21: 1 | AF21: 1 | AG21: 1 | AH21: 1 | AI21: 1 | AJ21: 1 | AK21: 1 | AM21: =E21 -> Tactically Monitor Fires | AN21: =F21 -> 0.033290765 | AP21: =G21/SUM(G$11:G$41) -> 0.02617801 | AQ21: =H21/SUM(H$11:H$41) -> 0.024 | AR21: =I21/SUM(I$11:I$41) -> 0.027027027 | AS21: =J21/SUM(J$11:J$41) -> 0.031712474 | AT21: =K21/SUM(K$11:K$41) -> 0.031712474 | AU21: =L21/SUM(L$11:L$41) -> 0.039840637 | AV21: =M21/SUM(M$11:M$41) -> 0.042105263 | AW21: =N21/SUM(N$11:N$41) -> 0.038461538 | ... BT21: =AK21/SUM(AK$11:AK$41) -> 0.016949153
E22: Predict New Fires | F22: =AVERAGE(AP22:BT22) -> 0.026479119 | G22: {=1/INDEX($H$11:$AK$11, 1, ROW(A11))} -> 2 | H22: {=1/INDEX($I$12:$AK$12, 1, ROW(A10))} -> 2 | I22: {=1/INDEX($J$13:$AK$13, 1, ROW(A9))} -> 2 | J22: {=1/INDEX($K$14:$AK$14, 1, ROW(A8))} -> 1 | K22: {=1/INDEX($L$15:$AK$15, 1, ROW(A7))} -> 1 | L22: {=1/INDEX($M$16:$AK$16, 1, ROW(A6))} -> 1 | M22: {=1/INDEX($N$17:$AK$17, 1, ROW(A5))} -> 1 | N22: {=1/INDEX($O$18:$AK$18, 1, ROW(A4))} -> 1 | O22: {=1/INDEX($P$19:$AK$19, 1, ROW(A3))} -> 0.5 | P22: {=1/INDEX($Q$20:$AK$20, 1, ROW(A2))} -> 0.5 | Q22: {=1/INDEX($R$21:$AK$21, 1, ROW(A1))} -> 0.5 | R22: 1 | S22: =1*1/4 -> 0.25 | T22: 1 | U22: 1 | V22: 1 | W22: 1 | X22: 1 | Y22: 1 | Z22: 1 | AA22: 1 | AB22: 1 | AC22: 1 | AD22: 1 | AE22: =1*1/2 -> 0.5 | AF22: =1*1/2 -> 0.5 | AG22: 2 | AH22: =1*1/2 -> 0.5 | AI22: =1*1/2 -> 0.5 | AJ22: =1*1/2 -> 0.5 | AK22: =1*1/2 -> 0.5 | AM22: =E22 -> Predict New Fires | AN22: =F22 -> 0.026479119 | AP22: =G22/SUM(G$11:G$41) -> 0.052356021 | AQ22: =H22/SUM(H$11:H$41) -> 0.048 | AR22: =I22/SUM(I$11:I$41) -> 0.054054054 | AS22: =J22/SUM(J$11:J$41) -> 0.031712474 | AT22: =K22/SUM(K$11:K$41) -> 0.031712474 | AU22: =L22/SUM(L$11:L$41) -> 0.019920319 | AV22: =M22/SUM(M$11:M$41) -> 0.021052632 | AW22: =N22/SUM(N$11:N$41) -> 0.038461538 | ... BT22: =AK22/SUM(AK$11:AK$41) -> 0.0084745763
E23: Detect Fires | F23: =AVERAGE(AP23:BT23) -> 0.041210309 | G23: {=1/INDEX($H$11:$AK$11, 1, ROW(A12))} -> 2 | H23: {=1/INDEX($I$12:$AK$12, 1, ROW(A11))} -> 2 | I23: {=1/INDEX($J$13:$AK$13, 1, ROW(A10))} -> 3 | J23: {=1/INDEX($K$14:$AK$14, 1, ROW(A9))} -> 1 | K23: {=1/INDEX($L$15:$AK$15, 1, ROW(A8))} -> 1 | L23: {=1/INDEX($M$16:$AK$16, 1, ROW(A7))} -> 1 | M23: {=1/INDEX($N$17:$AK$17, 1, ROW(A6))} -> 1 | N23: {=1/INDEX($O$18:$AK$18, 1, ROW(A5))} -> 1 | O23: {=1/INDEX($P$19:$AK$19, 1, ROW(A4))} -> 2 | P23: {=1/INDEX($Q$20:$AK$20, 1, ROW(A3))} -> 0.5 | Q23: {=1/INDEX($R$21:$AK$21, 1, ROW(A2))} -> 0.5 | R23: {=1/INDEX($S$22:$AK$22, 1, ROW(A1))} -> 4 | S23: 1 | T23: 2 | U23: 2 | V23: 2 | W23: 1 | X23: 1 | Y23: 1 | Z23: 1 | AA23: 1 | AB23: 1 | AC23: 1 | AD23: 1 | AE23: 2 | AF23: 2 | AG23: 2 | AH23: 2 | AI23: 2 | AJ23: 2 | AK23: 2 | AM23: =E23 -> Detect Fires | AN23: =F23 -> 0.041210309 | AP23: =G23/SUM(G$11:G$41) -> 0.052356021 | AQ23: =H23/SUM(H$11:H$41) -> 0.048 | AR23: =I23/SUM(I$11:I$41) -> 0.081081081 | AS23: =J23/SUM(J$11:J$41) -> 0.031712474 | AT23: =K23/SUM(K$11:K$41) -> 0.031712474 | AU23: =L23/SUM(L$11:L$41) -> 0.019920319 | AV23: =M23/SUM(M$11:M$41) -> 0.021052632 | AW23: =N23/SUM(N$11:N$41) -> 0.038461538 | ... BT23: =AK23/SUM(AK$11:AK$41) -> 0.033898305
E24: Visually Confirm Fires | F24: =AVERAGE(AP24:BT24) -> 0.037248096 | G24: {=1/INDEX($H$11:$AK$11, 1, ROW(A13))} -> 0.5 | H24: {=1/INDEX($I$12:$AK$12, 1, ROW(A12))} -> 3 | I24: {=1/INDEX($J$13:$AK$13, 1, ROW(A11))} -> 2 | J24: {=1/INDEX($K$14:$AK$14, 1, ROW(A10))} -> 2 | K24: {=1/INDEX($L$15:$AK$15, 1, ROW(A9))} -> 2 | L24: {=1/INDEX($M$16:$AK$16, 1, ROW(A8))} -> 1 | M24: {=1/INDEX($N$17:$AK$17, 1, ROW(A7))} -> 2 | N24: {=1/INDEX($O$18:$AK$18, 1, ROW(A6))} -> 1 | O24: {=1/INDEX($P$19:$AK$19, 1, ROW(A5))} -> 2 | P24: {=1/INDEX($Q$20:$AK$20, 1, ROW(A4))} -> 1 | Q24: {=1/INDEX($R$21:$AK$21, 1, ROW(A3))} -> 1 | R24: {=1/INDEX($S$22:$AK$22, 1, ROW(A2))} -> 1 | S24: {=1/INDEX($T$23:$AK$23, 1, ROW(A1))} -> 0.5 | T24: 1 | U24: 1 | V24: 1 | W24: 1 | X24: 1 | Y24: 1 | Z24: 1 | AA24: 1 | AB24: 1 | AC24: 1 | AD24: 1 | AE24: 1 | AF24: 2 | AG24: 2 | AH24: 2 | AI24: 2 | AJ24: 2 | AK24: 3 | AM24: =E24 -> Visually Confirm Fires | AN24: =F24 -> 0.037248096 | AP24: =G24/SUM(G$11:G$41) -> 0.013089005 | AQ24: =H24/SUM(H$11:H$41) -> 0.072 | AR24: =I24/SUM(I$11:I$41) -> 0.054054054 | AS24: =J24/SUM(J$11:J$41) -> 0.063424947 | AT24: =K24/SUM(K$11:K$41) -> 0.063424947 | AU24: =L24/SUM(L$11:L$41) -> 0.019920319 | AV24: =M24/SUM(M$11:M$41) -> 0.042105263 | AW24: =N24/SUM(N$11:N$41) -> 0.038461538 | ... BT24: =AK24/SUM(AK$11:AK$41) -> 0.050847458
E25: Predict Fire Paths/Behavior | F25: =AVERAGE(AP25:BT25) -> 0.037095433 | G25: {=1/INDEX($H$11:$AK$11, 1, ROW(A14))} -> 2 | H25: {=1/INDEX($I$12:$AK$12, 1, ROW(A13))} -> 2 | I25: {=1/INDEX($J$13:$AK$13, 1, ROW(A12))} -> 2 | J25: {=1/INDEX($K$14:$AK$14, 1, ROW(A11))} -> 1 | K25: {=1/INDEX($L$15:$AK$15, 1, ROW(A10))} -> 1 | L25: {=1/INDEX($M$16:$AK$16, 1, ROW(A9))} -> 1 | M25: {=1/INDEX($N$17:$AK$17, 1, ROW(A8))} -> 1 | N25: {=1/INDEX($O$18:$AK$18, 1, ROW(A7))} -> 1 | O25: {=1/INDEX($P$19:$AK$19, 1, ROW(A6))} -> 1 | P25: {=1/INDEX($Q$20:$AK$20, 1, ROW(A5))} -> 0.5 | Q25: {=1/INDEX($R$21:$AK$21, 1, ROW(A4))} -> 0.33333333 | R25: {=1/INDEX($S$22:$AK$22, 1, ROW(A3))} -> 1 | S25: {=1/INDEX($T$23:$AK$23, 1, ROW(A2))} -> 0.5 | T25: {=1/INDEX($U$24:$AK$24, 1, ROW(A1))} -> 1 | U25: 1 | V25: =1/2 -> 0.5 | W25: 2 | X25: 2 | Y25: 2 | Z25: 2 | AA25: 2 | AB25: 2 | AC25: 2 | AD25: 2 | AE25: =1/2 -> 0.5 | AF25: 1 | AG25: =1/2 -> 0.5 | AH25: 2 | AI25: 2 | AJ25: 2 | AK25: 2 | AM25: =E25 -> Predict Fire Paths/Behavior | AN25: =F25 -> 0.037095433 | AP25: =G25/SUM(G$11:G$41) -> 0.052356021 | AQ25: =H25/SUM(H$11:H$41) -> 0.048 | AR25: =I25/SUM(I$11:I$41) -> 0.054054054 | AS25: =J25/SUM(J$11:J$41) -> 0.031712474 | AT25: =K25/SUM(K$11:K$41) -> 0.031712474 | AU25: =L25/SUM(L$11:L$41) -> 0.019920319 | AV25: =M25/SUM(M$11:M$41) -> 0.021052632 | AW25: =N25/SUM(N$11:N$41) -> 0.038461538 | ... BT25: =AK25/SUM(AK$11:AK$41) -> 0.033898305
E26: Strategically Monitor Fires | F26: =AVERAGE(AP26:BT26) -> 0.027178717 | G26: {=1/INDEX($H$11:$AK$11, 1, ROW(A15))} -> 1 | H26: {=1/INDEX($I$12:$AK$12, 1, ROW(A14))} -> 2 | I26: {=1/INDEX($J$13:$AK$13, 1, ROW(A13))} -> 1 | J26: {=1/INDEX($K$14:$AK$14, 1, ROW(A12))} -> 1 | K26: {=1/INDEX($L$15:$AK$15, 1, ROW(A11))} -> 1 | L26: {=1/INDEX($M$16:$AK$16, 1, ROW(A10))} -> 1 | M26: {=1/INDEX($N$17:$AK$17, 1, ROW(A9))} -> 1 | N26: {=1/INDEX($O$18:$AK$18, 1, ROW(A8))} -> 1 | O26: {=1/INDEX($P$19:$AK$19, 1, ROW(A7))} -> 1 | P26: {=1/INDEX($Q$20:$AK$20, 1, ROW(A6))} -> 1 | Q26: {=1/INDEX($R$21:$AK$21, 1, ROW(A5))} -> 1 | R26: {=1/INDEX($S$22:$AK$22, 1, ROW(A4))} -> 1 | S26: {=1/INDEX($T$23:$AK$23, 1, ROW(A3))} -> 0.5 | T26: {=1/INDEX($U$24:$AK$24, 1, ROW(A2))} -> 1 | U26: {=1/INDEX($V$25:$AK$25, 1, ROW(A1))} -> 2 | V26: 1 | W26: 2 | X26: 2 | Y26: =1/2 -> 0.5 | Z26: =1/3 -> 0.33333333 | AA26: =1/3 -> 0.33333333 | AB26: 1 | AC26: 1 | AD26: 1 | AE26: =1/2 -> 0.5 | AF26: =1/3 -> 0.33333333 | AG26: 1 | AH26: =1/5 -> 0.2 | AI26: =1/3 -> 0.33333333 | AJ26: =1/3 -> 0.33333333 | AK26: =1/3 -> 0.33333333 | AM26: =E26 -> Strategically Monitor Fires | AN26: =F26 -> 0.027178717 | AP26: =G26/SUM(G$11:G$41) -> 0.02617801 | AQ26: =H26/SUM(H$11:H$41) -> 0.048 | AR26: =I26/SUM(I$11:I$41) -> 0.027027027 | AS26: =J26/SUM(J$11:J$41) -> 0.031712474 | AT26: =K26/SUM(K$11:K$41) -> 0.031712474 | AU26: =L26/SUM(L$11:L$41) -> 0.019920319 | AV26: =M26/SUM(M$11:M$41) -> 0.021052632 | AW26: =N26/SUM(N$11:N$41) -> 0.038461538 | ... BT26: =AK26/SUM(AK$11:AK$41) -> 0.0056497175
E27: Gather Real Time Data from Assets | F27: =AVERAGE(AP27:BT27) -> 0.032488808 | G27: {=1/INDEX($H$11:$AK$11, 1, ROW(A16))} -> 1 | H27: {=1/INDEX($I$12:$AK$12, 1, ROW(A15))} -> 2 | I27: {=1/INDEX($J$13:$AK$13, 1, ROW(A14))} -> 1 | J27: {=1/INDEX($K$14:$AK$14, 1, ROW(A13))} -> 1 | K27: {=1/INDEX($L$15:$AK$15, 1, ROW(A12))} -> 1 | L27: {=1/INDEX($M$16:$AK$16, 1, ROW(A11))} -> 1 | M27: {=1/INDEX($N$17:$AK$17, 1, ROW(A10))} -> 1 | N27: {=1/INDEX($O$18:$AK$18, 1, ROW(A9))} -> 1 | O27: {=1/INDEX($P$19:$AK$19, 1, ROW(A8))} -> 1 | P27: {=1/INDEX($Q$20:$AK$20, 1, ROW(A7))} -> 1 | Q27: {=1/INDEX($R$21:$AK$21, 1, ROW(A6))} -> 1 | R27: {=1/INDEX($S$22:$AK$22, 1, ROW(A5))} -> 1 | S27: {=1/INDEX($T$23:$AK$23, 1, ROW(A4))} -> 1 | T27: {=1/INDEX($U$24:$AK$24, 1, ROW(A3))} -> 1 | U27: {=1/INDEX($V$25:$AK$25, 1, ROW(A2))} -> 0.5 | V27: {=1/INDEX($W$26:$AK$26, 1, ROW(A1))} -> 0.5 | W27: 1 | X27: 1 | Y27: =1/3 -> 0.33333333 | Z27: 1 | AA27: 1 | AB27: =1/2 -> 0.5 | AC27: =1/2 -> 0.5 | AD27: =1/2 -> 0.5 | AE27: =2 -> 2 | AF27: =3 -> 3 | AG27: =3 -> 3 | AH27: =3 -> 3 | AI27: =2 -> 2 | AJ27: =2 -> 2 | AK27: =2 -> 2 | AM27: =E27 -> Gather Real Time Data from Assets | AN27: =F27 -> 0.032488808 | AP27: =G27/SUM(G$11:G$41) -> 0.02617801 | AQ27: =H27/SUM(H$11:H$41) -> 0.048 | AR27: =I27/SUM(I$11:I$41) -> 0.027027027 | AS27: =J27/SUM(J$11:J$41) -> 0.031712474 | AT27: =K27/SUM(K$11:K$41) -> 0.031712474 | AU27: =L27/SUM(L$11:L$41) -> 0.019920319 | AV27: =M27/SUM(M$11:M$41) -> 0.021052632 | AW27: =N27/SUM(N$11:N$41) -> 0.038461538 | ... BT27: =AK27/SUM(AK$11:AK$41) -> 0.033898305
E28: Build Real Time Situational Awareness | F28: =AVERAGE(AP28:BT28) -> 0.053081244 | G28: {=1/INDEX($H$11:$AK$11, 1, ROW(A17))} -> 1 | H28: {=1/INDEX($I$12:$AK$12, 1, ROW(A16))} -> 2 | I28: {=1/INDEX($J$13:$AK$13, 1, ROW(A15))} -> 1 | J28: {=1/INDEX($K$14:$AK$14, 1, ROW(A14))} -> 1 | K28: {=1/INDEX($L$15:$AK$15, 1, ROW(A13))} -> 1 | L28: {=1/INDEX($M$16:$AK$16, 1, ROW(A12))} -> 1 | M28: {=1/INDEX($N$17:$AK$17, 1, ROW(A11))} -> 1 | N28: {=1/INDEX($O$18:$AK$18, 1, ROW(A10))} -> 1 | O28: {=1/INDEX($P$19:$AK$19, 1, ROW(A9))} -> 1 | P28: {=1/INDEX($Q$20:$AK$20, 1, ROW(A8))} -> 1 | Q28: {=1/INDEX($R$21:$AK$21, 1, ROW(A7))} -> 1 | R28: {=1/INDEX($S$22:$AK$22, 1, ROW(A6))} -> 1 | S28: {=1/INDEX($T$23:$AK$23, 1, ROW(A5))} -> 1 | T28: {=1/INDEX($U$24:$AK$24, 1, ROW(A4))} -> 1 | U28: {=1/INDEX($V$25:$AK$25, 1, ROW(A3))} -> 0.5 | V28: {=1/INDEX($W$26:$AK$26, 1, ROW(A2))} -> 0.5 | W28: {=1/INDEX($X$27:$AK$27, 1, ROW(A1))} -> 1 | X28: 1 | Y28: =3 -> 3 | Z28: =2 -> 2 | AA28: =2 -> 2 | AB28: =2 -> 2 | AC28: =2 -> 2 | AD28: =2 -> 2 | AE28: =4 -> 4 | AF28: =4 -> 4 | AG28: =6 -> 6 | AH28: =6 -> 6 | AI28: =6 -> 6 | AJ28: =5 -> 5 | AK28: =5 -> 5 | AM28: =E28 -> Build Real Time Situational Awareness | AN28: =F28 -> 0.053081244 | AP28: =G28/SUM(G$11:G$41) -> 0.02617801 | AQ28: =H28/SUM(H$11:H$41) -> 0.048 | AR28: =I28/SUM(I$11:I$41) -> 0.027027027 | AS28: =J28/SUM(J$11:J$41) -> 0.031712474 | AT28: =K28/SUM(K$11:K$41) -> 0.031712474 | AU28: =L28/SUM(L$11:L$41) -> 0.019920319 | AV28: =M28/SUM(M$11:M$41) -> 0.021052632 | AW28: =N28/SUM(N$11:N$41) -> 0.038461538 | ... BT28: =AK28/SUM(AK$11:AK$41) -> 0.084745763
E29: Coordinate Air & Ground Resources | F29: =AVERAGE(AP29:BT29) -> 0.034671264 | G29: {=1/INDEX($H$11:$AK$11, 1, ROW(A18))} -> 1 | H29: {=1/INDEX($I$12:$AK$12, 1, ROW(A17))} -> 2 | I29: {=1/INDEX($J$13:$AK$13, 1, ROW(A16))} -> 1 | J29: {=1/INDEX($K$14:$AK$14, 1, ROW(A15))} -> 1 | K29: {=1/INDEX($L$15:$AK$15, 1, ROW(A14))} -> 1 | L29: {=1/INDEX($M$16:$AK$16, 1, ROW(A13))} -> 1 | M29: {=1/INDEX($N$17:$AK$17, 1, ROW(A12))} -> 1 | N29: {=1/INDEX($O$18:$AK$18, 1, ROW(A11))} -> 1 | O29: {=1/INDEX($P$19:$AK$19, 1, ROW(A10))} -> 1 | P29: {=1/INDEX($Q$20:$AK$20, 1, ROW(A9))} -> 1 | Q29: {=1/INDEX($R$21:$AK$21, 1, ROW(A8))} -> 1 | R29: {=1/INDEX($S$22:$AK$22, 1, ROW(A7))} -> 1 | S29: {=1/INDEX($T$23:$AK$23, 1, ROW(A6))} -> 1 | T29: {=1/INDEX($U$24:$AK$24, 1, ROW(A5))} -> 1 | U29: {=1/INDEX($V$25:$AK$25, 1, ROW(A4))} -> 0.5 | V29: {=1/INDEX($W$26:$AK$26, 1, ROW(A3))} -> 2 | W29: {=1/INDEX($X$27:$AK$27, 1, ROW(A2))} -> 3 | X29: {=1/INDEX($Y$28:$AK$28, 1, ROW(A1))} -> 0.33333333 | Y29: 1 | Z29: =1/3 -> 0.33333333 | AA29: =1 -> 1 | AB29: =2 -> 2 | AC29: =2 -> 2 | AD29: =2 -> 2 | AE29: =1/2 -> 0.5 | AF29: =1/2 -> 0.5 | AG29: =1/2 -> 0.5 | AH29: =3 -> 3 | AI29: =3 -> 3 | AJ29: =3 -> 3 | AK29: =2 -> 2 | AM29: =E29 -> Coordinate Air & Ground Resources | AN29: =F29 -> 0.034671264 | AP29: =G29/SUM(G$11:G$41) -> 0.02617801 | AQ29: =H29/SUM(H$11:H$41) -> 0.048 | AR29: =I29/SUM(I$11:I$41) -> 0.027027027 | AS29: =J29/SUM(J$11:J$41) -> 0.031712474 | AT29: =K29/SUM(K$11:K$41) -> 0.031712474 | AU29: =L29/SUM(L$11:L$41) -> 0.019920319 | AV29: =M29/SUM(M$11:M$41) -> 0.021052632 | AW29: =N29/SUM(N$11:N$41) -> 0.038461538 | ... BT29: =AK29/SUM(AK$11:AK$41) -> 0.033898305
E30: Dynamically Allocate Resources | F30: =AVERAGE(AP30:BT30) -> 0.027769727 | G30: {=1/INDEX($H$11:$AK$11, 1, ROW(A19))} -> 1 | H30: {=1/INDEX($I$12:$AK$12, 1, ROW(A18))} -> 2 | I30: {=1/INDEX($J$13:$AK$13, 1, ROW(A17))} -> 1 | J30: {=1/INDEX($K$14:$AK$14, 1, ROW(A16))} -> 1 | K30: {=1/INDEX($L$15:$AK$15, 1, ROW(A15))} -> 1 | L30: {=1/INDEX($M$16:$AK$16, 1, ROW(A14))} -> 1 | M30: {=1/INDEX($N$17:$AK$17, 1, ROW(A13))} -> 1 | N30: {=1/INDEX($O$18:$AK$18, 1, ROW(A12))} -> 1 | O30: {=1/INDEX($P$19:$AK$19, 1, ROW(A11))} -> 1 | P30: {=1/INDEX($Q$20:$AK$20, 1, ROW(A10))} -> 1 | Q30: {=1/INDEX($R$21:$AK$21, 1, ROW(A9))} -> 1 | R30: {=1/INDEX($S$22:$AK$22, 1, ROW(A8))} -> 1 | S30: {=1/INDEX($T$23:$AK$23, 1, ROW(A7))} -> 1 | T30: {=1/INDEX($U$24:$AK$24, 1, ROW(A6))} -> 1 | U30: {=1/INDEX($V$25:$AK$25, 1, ROW(A5))} -> 0.5 | V30: {=1/INDEX($W$26:$AK$26, 1, ROW(A4))} -> 3 | W30: {=1/INDEX($X$27:$AK$27, 1, ROW(A3))} -> 1 | X30: {=1/INDEX($Y$28:$AK$28, 1, ROW(A2))} -> 0.5 | Y30: {=1/INDEX($Z$29:$AK$29, 1, ROW(A1))} -> 3 | Z30: 1 | AA30: =1/3 -> 0.33333333 | AB30: =1/2 -> 0.5 | AC30: 1 | AD30: 2 | AE30: =1/2 -> 0.5 | AF30: =1/3 -> 0.33333333 | AG30: =1/5 -> 0.2 | AH30: =1/3 -> 0.33333333 | AI30: =1/2 -> 0.5 | AJ30: =1/2 -> 0.5 | AK30: 1 | AM30: =E30 -> Dynamically Allocate Resources | AN30: =F30 -> 0.027769727 | AP30: =G30/SUM(G$11:G$41) -> 0.02617801 | AQ30: =H30/SUM(H$11:H$41) -> 0.048 | AR30: =I30/SUM(I$11:I$41) -> 0.027027027 | AS30: =J30/SUM(J$11:J$41) -> 0.031712474 | AT30: =K30/SUM(K$11:K$41) -> 0.031712474 | AU30: =L30/SUM(L$11:L$41) -> 0.019920319 | AV30: =M30/SUM(M$11:M$41) -> 0.021052632 | AW30: =N30/SUM(N$11:N$41) -> 0.038461538 | ... BT30: =AK30/SUM(AK$11:AK$41) -> 0.016949153
E31: Issue Commands to Assets | F31: =AVERAGE(AP31:BT31) -> 0.036661629 | G31: {=1/INDEX($H$11:$AK$11, 1, ROW(A20))} -> 2 | H31: {=1/INDEX($I$12:$AK$12, 1, ROW(A19))} -> 2 | I31: {=1/INDEX($J$13:$AK$13, 1, ROW(A18))} -> 1 | J31: {=1/INDEX($K$14:$AK$14, 1, ROW(A17))} -> 1 | K31: {=1/INDEX($L$15:$AK$15, 1, ROW(A16))} -> 1 | L31: {=1/INDEX($M$16:$AK$16, 1, ROW(A15))} -> 1 | M31: {=1/INDEX($N$17:$AK$17, 1, ROW(A14))} -> 1 | N31: {=1/INDEX($O$18:$AK$18, 1, ROW(A13))} -> 1 | O31: {=1/INDEX($P$19:$AK$19, 1, ROW(A12))} -> 1 | P31: {=1/INDEX($Q$20:$AK$20, 1, ROW(A11))} -> 1 | Q31: {=1/INDEX($R$21:$AK$21, 1, ROW(A10))} -> 1 | R31: {=1/INDEX($S$22:$AK$22, 1, ROW(A9))} -> 1 | S31: {=1/INDEX($T$23:$AK$23, 1, ROW(A8))} -> 1 | T31: {=1/INDEX($U$24:$AK$24, 1, ROW(A7))} -> 1 | U31: {=1/INDEX($V$25:$AK$25, 1, ROW(A6))} -> 0.5 | V31: {=1/INDEX($W$26:$AK$26, 1, ROW(A5))} -> 3 | W31: {=1/INDEX($X$27:$AK$27, 1, ROW(A4))} -> 1 | X31: {=1/INDEX($Y$28:$AK$28, 1, ROW(A3))} -> 0.5 | Y31: {=1/INDEX($Z$29:$AK$29, 1, ROW(A2))} -> 1 | Z31: {=1/INDEX($AA$30:$AK$30, 1, ROW(A1))} -> 3 | AA31: 1 | AB31: 2 | AC31: 3 | AD31: 4 | AE31: 2 | AF31: 2 | AG31: 1 | AH31: 0.33333333 | AI31: 0.25 | AJ31: 0.33333333 | AK31: 0.33333333 | AM31: =E31 -> Issue Commands to Assets | AN31: =F31 -> 0.036661629 | AP31: =G31/SUM(G$11:G$41) -> 0.052356021 | AQ31: =H31/SUM(H$11:H$41) -> 0.048 | AR31: =I31/SUM(I$11:I$41) -> 0.027027027 | AS31: =J31/SUM(J$11:J$41) -> 0.031712474 | AT31: =K31/SUM(K$11:K$41) -> 0.031712474 | AU31: =L31/SUM(L$11:L$41) -> 0.019920319 | AV31: =M31/SUM(M$11:M$41) -> 0.021052632 | AW31: =N31/SUM(N$11:N$41) -> 0.038461538 | ... BT31: =AK31/SUM(AK$11:AK$41) -> 0.0056497175
E32: Communicate to Resources | F32: =AVERAGE(AP32:BT32) -> 0.039361135 | G32: {=1/INDEX($H$11:$AK$11, 1, ROW(A21))} -> 2 | H32: {=1/INDEX($I$12:$AK$12, 1, ROW(A20))} -> 2 | I32: {=1/INDEX($J$13:$AK$13, 1, ROW(A19))} -> 1 | J32: {=1/INDEX($K$14:$AK$14, 1, ROW(A18))} -> 1 | K32: {=1/INDEX($L$15:$AK$15, 1, ROW(A17))} -> 1 | L32: {=1/INDEX($M$16:$AK$16, 1, ROW(A16))} -> 1 | M32: {=1/INDEX($N$17:$AK$17, 1, ROW(A15))} -> 1 | N32: {=1/INDEX($O$18:$AK$18, 1, ROW(A14))} -> 1 | O32: {=1/INDEX($P$19:$AK$19, 1, ROW(A13))} -> 1 | P32: {=1/INDEX($Q$20:$AK$20, 1, ROW(A12))} -> 1 | Q32: {=1/INDEX($R$21:$AK$21, 1, ROW(A11))} -> 1 | R32: {=1/INDEX($S$22:$AK$22, 1, ROW(A10))} -> 1 | S32: {=1/INDEX($T$23:$AK$23, 1, ROW(A9))} -> 1 | T32: {=1/INDEX($U$24:$AK$24, 1, ROW(A8))} -> 1 | U32: {=1/INDEX($V$25:$AK$25, 1, ROW(A7))} -> 0.5 | V32: {=1/INDEX($W$26:$AK$26, 1, ROW(A6))} -> 1 | W32: {=1/INDEX($X$27:$AK$27, 1, ROW(A5))} -> 2 | X32: {=1/INDEX($Y$28:$AK$28, 1, ROW(A4))} -> 0.5 | Y32: {=1/INDEX($Z$29:$AK$29, 1, ROW(A3))} -> 0.5 | Z32: {=1/INDEX($AA$30:$AK$30, 1, ROW(A2))} -> 2 | AA32: {=1/INDEX($AB$31:$AK$31, 1, ROW(A1))} -> 0.5 | AB32: 1 | AC32: =1/2 -> 0.5 | AD32: =1/3 -> 0.33333333 | AE32: =2 -> 2 | AF32: =3 -> 3 | AG32: =2 -> 2 | AH32: =5 -> 5 | AI32: =7 -> 7 | AJ32: =4 -> 4 | AK32: =3 -> 3 | AM32: =E32 -> Communicate to Resources | AN32: =F32 -> 0.039361135 | AP32: =G32/SUM(G$11:G$41) -> 0.052356021 | AQ32: =H32/SUM(H$11:H$41) -> 0.048 | AR32: =I32/SUM(I$11:I$41) -> 0.027027027 | AS32: =J32/SUM(J$11:J$41) -> 0.031712474 | AT32: =K32/SUM(K$11:K$41) -> 0.031712474 | AU32: =L32/SUM(L$11:L$41) -> 0.019920319 | AV32: =M32/SUM(M$11:M$41) -> 0.021052632 | AW32: =N32/SUM(N$11:N$41) -> 0.038461538 | ... BT32: =AK32/SUM(AK$11:AK$41) -> 0.050847458
E33: Maintain Communication Among Assets | F33: =AVERAGE(AP33:BT33) -> 0.033904731 | G33: {=1/INDEX($H$11:$AK$11, 1, ROW(A22))} -> 2 | H33: {=1/INDEX($I$12:$AK$12, 1, ROW(A21))} -> 2 | I33: {=1/INDEX($J$13:$AK$13, 1, ROW(A20))} -> 1 | J33: {=1/INDEX($K$14:$AK$14, 1, ROW(A19))} -> 1 | K33: {=1/INDEX($L$15:$AK$15, 1, ROW(A18))} -> 1 | L33: {=1/INDEX($M$16:$AK$16, 1, ROW(A17))} -> 1 | M33: {=1/INDEX($N$17:$AK$17, 1, ROW(A16))} -> 1 | N33: {=1/INDEX($O$18:$AK$18, 1, ROW(A15))} -> 0.5 | O33: {=1/INDEX($P$19:$AK$19, 1, ROW(A14))} -> 1 | P33: {=1/INDEX($Q$20:$AK$20, 1, ROW(A13))} -> 1 | Q33: {=1/INDEX($R$21:$AK$21, 1, ROW(A12))} -> 1 | R33: {=1/INDEX($S$22:$AK$22, 1, ROW(A11))} -> 1 | S33: {=1/INDEX($T$23:$AK$23, 1, ROW(A10))} -> 1 | T33: {=1/INDEX($U$24:$AK$24, 1, ROW(A9))} -> 1 | U33: {=1/INDEX($V$25:$AK$25, 1, ROW(A8))} -> 0.5 | V33: {=1/INDEX($W$26:$AK$26, 1, ROW(A7))} -> 1 | W33: {=1/INDEX($X$27:$AK$27, 1, ROW(A6))} -> 2 | X33: {=1/INDEX($Y$28:$AK$28, 1, ROW(A5))} -> 0.5 | Y33: {=1/INDEX($Z$29:$AK$29, 1, ROW(A4))} -> 0.5 | Z33: {=1/INDEX($AA$30:$AK$30, 1, ROW(A3))} -> 1 | AA33: {=1/INDEX($AB$31:$AK$31, 1, ROW(A2))} -> 0.33333333 | AB33: {=1/INDEX($AC$32:$AK$32, 1, ROW(A1))} -> 2 | AC33: 1 | AD33: =1/2 -> 0.5 | AE33: =2 -> 2 | AF33: =2 -> 2 | AG33: =2 -> 2 | AH33: =3 -> 3 | AI33: =3 -> 3 | AJ33: =2 -> 2 | AK33: =2 -> 2 | AM33: =E33 -> Maintain Communication Among Assets | AN33: =F33 -> 0.033904731 | AP33: =G33/SUM(G$11:G$41) -> 0.052356021 | AQ33: =H33/SUM(H$11:H$41) -> 0.048 | AR33: =I33/SUM(I$11:I$41) -> 0.027027027 | AS33: =J33/SUM(J$11:J$41) -> 0.031712474 | AT33: =K33/SUM(K$11:K$41) -> 0.031712474 | AU33: =L33/SUM(L$11:L$41) -> 0.019920319 | AV33: =M33/SUM(M$11:M$41) -> 0.021052632 | AW33: =N33/SUM(N$11:N$41) -> 0.019230769 | ... BT33: =AK33/SUM(AK$11:AK$41) -> 0.033898305
E34: Maintain Communication Between Assets and C3 | F34: =AVERAGE(AP34:BT34) -> 0.031354935 | G34: {=1/INDEX($H$11:$AK$11, 1, ROW(A23))} -> 3 | H34: {=1/INDEX($I$12:$AK$12, 1, ROW(A22))} -> 2 | I34: {=1/INDEX($J$13:$AK$13, 1, ROW(A21))} -> 1 | J34: {=1/INDEX($K$14:$AK$14, 1, ROW(A20))} -> 1 | K34: {=1/INDEX($L$15:$AK$15, 1, ROW(A19))} -> 1 | L34: {=1/INDEX($M$16:$AK$16, 1, ROW(A18))} -> 1 | M34: {=1/INDEX($N$17:$AK$17, 1, ROW(A17))} -> 1 | N34: {=1/INDEX($O$18:$AK$18, 1, ROW(A16))} -> 0.33333333 | O34: {=1/INDEX($P$19:$AK$19, 1, ROW(A15))} -> 1 | P34: {=1/INDEX($Q$20:$AK$20, 1, ROW(A14))} -> 1 | Q34: {=1/INDEX($R$21:$AK$21, 1, ROW(A13))} -> 1 | R34: {=1/INDEX($S$22:$AK$22, 1, ROW(A12))} -> 1 | S34: {=1/INDEX($T$23:$AK$23, 1, ROW(A11))} -> 1 | T34: {=1/INDEX($U$24:$AK$24, 1, ROW(A10))} -> 1 | U34: {=1/INDEX($V$25:$AK$25, 1, ROW(A9))} -> 0.5 | V34: {=1/INDEX($W$26:$AK$26, 1, ROW(A8))} -> 1 | W34: {=1/INDEX($X$27:$AK$27, 1, ROW(A7))} -> 2 | X34: {=1/INDEX($Y$28:$AK$28, 1, ROW(A6))} -> 0.5 | Y34: {=1/INDEX($Z$29:$AK$29, 1, ROW(A5))} -> 0.5 | Z34: {=1/INDEX($AA$30:$AK$30, 1, ROW(A4))} -> 0.5 | AA34: {=1/INDEX($AB$31:$AK$31, 1, ROW(A3))} -> 0.25 | AB34: {=1/INDEX($AC$32:$AK$32, 1, ROW(A2))} -> 3 | AC34: {=1/INDEX($AD$33:$AK$33, 1, ROW(A1))} -> 2 | AD34: 1 | AE34: =1/3 -> 0.33333333 | AF34: =1/3 -> 0.33333333 | AG34: =1/2 -> 0.5 | AH34: =1 -> 1 | AI34: =2 -> 2 | AJ34: =2 -> 2 | AK34: =3 -> 3 | AM34: =E34 -> Maintain Communication Between Assets and C3 | AN34: =F34 -> 0.031354935 | AP34: =G34/SUM(G$11:G$41) -> 0.078534031 | AQ34: =H34/SUM(H$11:H$41) -> 0.048 | AR34: =I34/SUM(I$11:I$41) -> 0.027027027 | AS34: =J34/SUM(J$11:J$41) -> 0.031712474 | AT34: =K34/SUM(K$11:K$41) -> 0.031712474 | AU34: =L34/SUM(L$11:L$41) -> 0.019920319 | AV34: =M34/SUM(M$11:M$41) -> 0.021052632 | AW34: =N34/SUM(N$11:N$41) -> 0.012820513 | ... BT34: =AK34/SUM(AK$11:AK$41) -> 0.050847458
E35: Deploy First Response Ground Assets | F35: =AVERAGE(AP35:BT35) -> 0.036581027 | G35: {=1/INDEX($H$11:$AK$11, 1, ROW(A24))} -> 1 | H35: {=1/INDEX($I$12:$AK$12, 1, ROW(A23))} -> 1 | I35: {=1/INDEX($J$13:$AK$13, 1, ROW(A22))} -> 1 | J35: {=1/INDEX($K$14:$AK$14, 1, ROW(A21))} -> 1 | K35: {=1/INDEX($L$15:$AK$15, 1, ROW(A20))} -> 1 | L35: {=1/INDEX($M$16:$AK$16, 1, ROW(A19))} -> 2 | M35: {=1/INDEX($N$17:$AK$17, 1, ROW(A18))} -> 2 | N35: {=1/INDEX($O$18:$AK$18, 1, ROW(A17))} -> 1 | O35: {=1/INDEX($P$19:$AK$19, 1, ROW(A16))} -> 1 | P35: {=1/INDEX($Q$20:$AK$20, 1, ROW(A15))} -> 1 | Q35: {=1/INDEX($R$21:$AK$21, 1, ROW(A14))} -> 1 | R35: {=1/INDEX($S$22:$AK$22, 1, ROW(A13))} -> 2 | S35: {=1/INDEX($T$23:$AK$23, 1, ROW(A12))} -> 0.5 | T35: {=1/INDEX($U$24:$AK$24, 1, ROW(A11))} -> 1 | U35: {=1/INDEX($V$25:$AK$25, 1, ROW(A10))} -> 2 | V35: {=1/INDEX($W$26:$AK$26, 1, ROW(A9))} -> 2 | W35: {=1/INDEX($X$27:$AK$27, 1, ROW(A8))} -> 0.5 | X35: {=1/INDEX($Y$28:$AK$28, 1, ROW(A7))} -> 0.25 | Y35: {=1/INDEX($Z$29:$AK$29, 1, ROW(A6))} -> 2 | Z35: {=1/INDEX($AA$30:$AK$30, 1, ROW(A5))} -> 2 | AA35: {=1/INDEX($AB$31:$AK$31, 1, ROW(A4))} -> 0.5 | AB35: {=1/INDEX($AC$32:$AK$32, 1, ROW(A3))} -> 0.5 | AC35: {=1/INDEX($AD$33:$AK$33, 1, ROW(A2))} -> 0.5 | AD35: {=1/INDEX($AE$34:$AK$34, 1, ROW(A1))} -> 3 | AE35: 1 | AF35: =2 -> 2 | AG35: =1/2 -> 0.5 | AH35: 2 | AI35: =4 -> 4 | AJ35: =3 -> 3 | AK35: 4 | AM35: =E35 -> Deploy First Response Ground Assets | AN35: =F35 -> 0.036581027 | AP35: =G35/SUM(G$11:G$41) -> 0.02617801 | AQ35: =H35/SUM(H$11:H$41) -> 0.024 | AR35: =I35/SUM(I$11:I$41) -> 0.027027027 | AS35: =J35/SUM(J$11:J$41) -> 0.031712474 | AT35: =K35/SUM(K$11:K$41) -> 0.031712474 | AU35: =L35/SUM(L$11:L$41) -> 0.039840637 | AV35: =M35/SUM(M$11:M$41) -> 0.042105263 | AW35: =N35/SUM(N$11:N$41) -> 0.038461538 | ... BT35: =AK35/SUM(AK$11:AK$41) -> 0.06779661
E36: Deploy Smokejumpers | F36: =AVERAGE(AP36:BT36) -> 0.030378516 | G36: {=1/INDEX($H$11:$AK$11, 1, ROW(A25))} -> 0.5 | H36: {=1/INDEX($I$12:$AK$12, 1, ROW(A24))} -> 1 | I36: {=1/INDEX($J$13:$AK$13, 1, ROW(A23))} -> 1 | J36: {=1/INDEX($K$14:$AK$14, 1, ROW(A22))} -> 1 | K36: {=1/INDEX($L$15:$AK$15, 1, ROW(A21))} -> 1 | L36: {=1/INDEX($M$16:$AK$16, 1, ROW(A20))} -> 1 | M36: {=1/INDEX($N$17:$AK$17, 1, ROW(A19))} -> 2 | N36: {=1/INDEX($O$18:$AK$18, 1, ROW(A18))} -> 0.5 | O36: {=1/INDEX($P$19:$AK$19, 1, ROW(A17))} -> 0.5 | P36: {=1/INDEX($Q$20:$AK$20, 1, ROW(A16))} -> 1 | Q36: {=1/INDEX($R$21:$AK$21, 1, ROW(A15))} -> 1 | R36: {=1/INDEX($S$22:$AK$22, 1, ROW(A14))} -> 2 | S36: {=1/INDEX($T$23:$AK$23, 1, ROW(A13))} -> 0.5 | T36: {=1/INDEX($U$24:$AK$24, 1, ROW(A12))} -> 0.5 | U36: {=1/INDEX($V$25:$AK$25, 1, ROW(A11))} -> 1 | V36: {=1/INDEX($W$26:$AK$26, 1, ROW(A10))} -> 3 | W36: {=1/INDEX($X$27:$AK$27, 1, ROW(A9))} -> 0.33333333 | X36: {=1/INDEX($Y$28:$AK$28, 1, ROW(A8))} -> 0.25 | Y36: {=1/INDEX($Z$29:$AK$29, 1, ROW(A7))} -> 2 | Z36: {=1/INDEX($AA$30:$AK$30, 1, ROW(A6))} -> 3 | AA36: {=1/INDEX($AB$31:$AK$31, 1, ROW(A5))} -> 0.5 | AB36: {=1/INDEX($AC$32:$AK$32, 1, ROW(A4))} -> 0.33333333 | AC36: {=1/INDEX($AD$33:$AK$33, 1, ROW(A3))} -> 0.5 | AD36: {=1/INDEX($AE$34:$AK$34, 1, ROW(A2))} -> 3 | AE36: {=1/INDEX($AF$35:$AK$35, 1, ROW(A1))} -> 0.5 | AF36: 1 | AG36: =1/2 -> 0.5 | AH36: 3 | AI36: 2 | AJ36: 2 | AK36: 2 | AM36: =E36 -> Deploy Smokejumpers | AN36: =F36 -> 0.030378516 | AP36: =G36/SUM(G$11:G$41) -> 0.013089005 | AQ36: =H36/SUM(H$11:H$41) -> 0.024 | AR36: =I36/SUM(I$11:I$41) -> 0.027027027 | AS36: =J36/SUM(J$11:J$41) -> 0.031712474 | AT36: =K36/SUM(K$11:K$41) -> 0.031712474 | AU36: =L36/SUM(L$11:L$41) -> 0.019920319 | AV36: =M36/SUM(M$11:M$41) -> 0.042105263 | AW36: =N36/SUM(N$11:N$41) -> 0.019230769 | ... BT36: =AK36/SUM(AK$11:AK$41) -> 0.033898305
E37: Activate MAFFS | F37: =AVERAGE(AP37:BT37) -> 0.03073345 | G37: {=1/INDEX($H$11:$AK$11, 1, ROW(A26))} -> 0.33333333 | H37: {=1/INDEX($I$12:$AK$12, 1, ROW(A25))} -> 1 | I37: {=1/INDEX($J$13:$AK$13, 1, ROW(A24))} -> 1 | J37: {=1/INDEX($K$14:$AK$14, 1, ROW(A23))} -> 1 | K37: {=1/INDEX($L$15:$AK$15, 1, ROW(A22))} -> 1 | L37: {=1/INDEX($M$16:$AK$16, 1, ROW(A21))} -> 1 | M37: {=1/INDEX($N$17:$AK$17, 1, ROW(A20))} -> 1 | N37: {=1/INDEX($O$18:$AK$18, 1, ROW(A19))} -> 0.5 | O37: {=1/INDEX($P$19:$AK$19, 1, ROW(A18))} -> 0.5 | P37: {=1/INDEX($Q$20:$AK$20, 1, ROW(A17))} -> 1 | Q37: {=1/INDEX($R$21:$AK$21, 1, ROW(A16))} -> 1 | R37: {=1/INDEX($S$22:$AK$22, 1, ROW(A15))} -> 0.5 | S37: {=1/INDEX($T$23:$AK$23, 1, ROW(A14))} -> 0.5 | T37: {=1/INDEX($U$24:$AK$24, 1, ROW(A13))} -> 0.5 | U37: {=1/INDEX($V$25:$AK$25, 1, ROW(A12))} -> 2 | V37: {=1/INDEX($W$26:$AK$26, 1, ROW(A11))} -> 1 | W37: {=1/INDEX($X$27:$AK$27, 1, ROW(A10))} -> 0.33333333 | X37: {=1/INDEX($Y$28:$AK$28, 1, ROW(A9))} -> 0.16666667 | Y37: {=1/INDEX($Z$29:$AK$29, 1, ROW(A8))} -> 2 | Z37: {=1/INDEX($AA$30:$AK$30, 1, ROW(A7))} -> 5 | AA37: {=1/INDEX($AB$31:$AK$31, 1, ROW(A6))} -> 1 | AB37: {=1/INDEX($AC$32:$AK$32, 1, ROW(A5))} -> 0.5 | AC37: {=1/INDEX($AD$33:$AK$33, 1, ROW(A4))} -> 0.5 | AD37: {=1/INDEX($AE$34:$AK$34, 1, ROW(A3))} -> 2 | AE37: {=1/INDEX($AF$35:$AK$35, 1, ROW(A2))} -> 2 | AF37: {=1/INDEX($AG$36:$AK$36, 1, ROW(A1))} -> 2 | AG37: 1 | AH37: =1 -> 1 | AI37: 2 | AJ37: =2 -> 2 | AK37: =2 -> 2 | AM37: =E37 -> Activate MAFFS | AN37: =F37 -> 0.03073345 | AP37: =G37/SUM(G$11:G$41) -> 0.0087260035 | AQ37: =H37/SUM(H$11:H$41) -> 0.024 | AR37: =I37/SUM(I$11:I$41) -> 0.027027027 | AS37: =J37/SUM(J$11:J$41) -> 0.031712474 | AT37: =K37/SUM(K$11:K$41) -> 0.031712474 | AU37: =L37/SUM(L$11:L$41) -> 0.019920319 | AV37: =M37/SUM(M$11:M$41) -> 0.021052632 | AW37: =N37/SUM(N$11:N$41) -> 0.019230769 | ... BT37: =AK37/SUM(AK$11:AK$41) -> 0.033898305
E38: Refuel Airborne Assets | F38: =AVERAGE(AP38:BT38) -> 0.026263482 | G38: {=1/INDEX($H$11:$AK$11, 1, ROW(A27))} -> 0.5 | H38: {=1/INDEX($I$12:$AK$12, 1, ROW(A26))} -> 0.5 | I38: {=1/INDEX($J$13:$AK$13, 1, ROW(A25))} -> 1 | J38: {=1/INDEX($K$14:$AK$14, 1, ROW(A24))} -> 0.33333333 | K38: {=1/INDEX($L$15:$AK$15, 1, ROW(A23))} -> 0.33333333 | L38: {=1/INDEX($M$16:$AK$16, 1, ROW(A22))} -> 1 | M38: {=1/INDEX($N$17:$AK$17, 1, ROW(A21))} -> 1 | N38: {=1/INDEX($O$18:$AK$18, 1, ROW(A20))} -> 0.5 | O38: {=1/INDEX($P$19:$AK$19, 1, ROW(A19))} -> 1 | P38: {=1/INDEX($Q$20:$AK$20, 1, ROW(A18))} -> 1 | Q38: {=1/INDEX($R$21:$AK$21, 1, ROW(A17))} -> 1 | R38: {=1/INDEX($S$22:$AK$22, 1, ROW(A16))} -> 2 | S38: {=1/INDEX($T$23:$AK$23, 1, ROW(A15))} -> 0.5 | T38: {=1/INDEX($U$24:$AK$24, 1, ROW(A14))} -> 0.5 | U38: {=1/INDEX($V$25:$AK$25, 1, ROW(A13))} -> 0.5 | V38: {=1/INDEX($W$26:$AK$26, 1, ROW(A12))} -> 5 | W38: {=1/INDEX($X$27:$AK$27, 1, ROW(A11))} -> 0.33333333 | X38: {=1/INDEX($Y$28:$AK$28, 1, ROW(A10))} -> 0.16666667 | Y38: {=1/INDEX($Z$29:$AK$29, 1, ROW(A9))} -> 0.33333333 | Z38: {=1/INDEX($AA$30:$AK$30, 1, ROW(A8))} -> 3 | AA38: {=1/INDEX($AB$31:$AK$31, 1, ROW(A7))} -> 3 | AB38: {=1/INDEX($AC$32:$AK$32, 1, ROW(A6))} -> 0.2 | AC38: {=1/INDEX($AD$33:$AK$33, 1, ROW(A5))} -> 0.33333333 | AD38: {=1/INDEX($AE$34:$AK$34, 1, ROW(A4))} -> 1 | AE38: {=1/INDEX($AF$35:$AK$35, 1, ROW(A3))} -> 0.5 | AF38: {=1/INDEX($AG$36:$AK$36, 1, ROW(A2))} -> 0.33333333 | AG38: {=1/INDEX($AH$37:$AK$37, 1, ROW(A1))} -> 1 | AH38: 1 | AI38: =3 -> 3 | AJ38: =2 -> 2 | AK38: =1/2 -> 0.5 | AM38: =E38 -> Refuel Airborne Assets | AN38: =F38 -> 0.026263482 | AP38: =G38/SUM(G$11:G$41) -> 0.013089005 | AQ38: =H38/SUM(H$11:H$41) -> 0.012 | AR38: =I38/SUM(I$11:I$41) -> 0.027027027 | AS38: =J38/SUM(J$11:J$41) -> 0.010570825 | AT38: =K38/SUM(K$11:K$41) -> 0.010570825 | AU38: =L38/SUM(L$11:L$41) -> 0.019920319 | AV38: =M38/SUM(M$11:M$41) -> 0.021052632 | AW38: =N38/SUM(N$11:N$41) -> 0.019230769 | ... BT38: =AK38/SUM(AK$11:AK$41) -> 0.0084745763
E39: Provide MRO for Assets | F39: =AVERAGE(AP39:BT39) -> 0.022408033 | G39: {=1/INDEX($H$11:$AK$11, 1, ROW(A28))} -> 0.33333333 | H39: {=1/INDEX($I$12:$AK$12, 1, ROW(A27))} -> 0.5 | I39: {=1/INDEX($J$13:$AK$13, 1, ROW(A26))} -> 1 | J39: {=1/INDEX($K$14:$AK$14, 1, ROW(A25))} -> 0.33333333 | K39: {=1/INDEX($L$15:$AK$15, 1, ROW(A24))} -> 0.33333333 | L39: {=1/INDEX($M$16:$AK$16, 1, ROW(A23))} -> 1 | M39: {=1/INDEX($N$17:$AK$17, 1, ROW(A22))} -> 1 | N39: {=1/INDEX($O$18:$AK$18, 1, ROW(A21))} -> 1 | O39: {=1/INDEX($P$19:$AK$19, 1, ROW(A20))} -> 1 | P39: {=1/INDEX($Q$20:$AK$20, 1, ROW(A19))} -> 1 | Q39: {=1/INDEX($R$21:$AK$21, 1, ROW(A18))} -> 1 | R39: {=1/INDEX($S$22:$AK$22, 1, ROW(A17))} -> 2 | S39: {=1/INDEX($T$23:$AK$23, 1, ROW(A16))} -> 0.5 | T39: {=1/INDEX($U$24:$AK$24, 1, ROW(A15))} -> 0.5 | U39: {=1/INDEX($V$25:$AK$25, 1, ROW(A14))} -> 0.5 | V39: {=1/INDEX($W$26:$AK$26, 1, ROW(A13))} -> 3 | W39: {=1/INDEX($X$27:$AK$27, 1, ROW(A12))} -> 0.5 | X39: {=1/INDEX($Y$28:$AK$28, 1, ROW(A11))} -> 0.16666667 | Y39: {=1/INDEX($Z$29:$AK$29, 1, ROW(A10))} -> 0.33333333 | Z39: {=1/INDEX($AA$30:$AK$30, 1, ROW(A9))} -> 2 | AA39: {=1/INDEX($AB$31:$AK$31, 1, ROW(A8))} -> 4 | AB39: {=1/INDEX($AC$32:$AK$32, 1, ROW(A7))} -> 0.14285714 | AC39: {=1/INDEX($AD$33:$AK$33, 1, ROW(A6))} -> 0.33333333 | AD39: {=1/INDEX($AE$34:$AK$34, 1, ROW(A5))} -> 0.5 | AE39: {=1/INDEX($AF$35:$AK$35, 1, ROW(A4))} -> 0.25 | AF39: {=1/INDEX($AG$36:$AK$36, 1, ROW(A3))} -> 0.5 | AG39: {=1/INDEX($AH$37:$AK$37, 1, ROW(A2))} -> 0.5 | AH39: {=1/INDEX($AI$38:$AK$38, 1, ROW(A1))} -> 0.33333333 | AI39: 1 | AJ39: =1/2 -> 0.5 | AK39: =1/3 -> 0.33333333 | AM39: =E39 -> Provide MRO for Assets | AN39: =F39 -> 0.022408033 | AP39: =G39/SUM(G$11:G$41) -> 0.0087260035 | AQ39: =H39/SUM(H$11:H$41) -> 0.012 | AR39: =I39/SUM(I$11:I$41) -> 0.027027027 | AS39: =J39/SUM(J$11:J$41) -> 0.010570825 | AT39: =K39/SUM(K$11:K$41) -> 0.010570825 | AU39: =L39/SUM(L$11:L$41) -> 0.019920319 | AV39: =M39/SUM(M$11:M$41) -> 0.021052632 | AW39: =N39/SUM(N$11:N$41) -> 0.038461538 | ... BT39: =AK39/SUM(AK$11:AK$41) -> 0.0056497175
E40: Refill Water and Fire Retardants | F40: =AVERAGE(AP40:BT40) -> 0.02325298 | G40: {=1/INDEX($H$11:$AK$11, 1, ROW(A29))} -> 0.33333333 | H40: {=1/INDEX($I$12:$AK$12, 1, ROW(A28))} -> 0.5 | I40: {=1/INDEX($J$13:$AK$13, 1, ROW(A27))} -> 1 | J40: {=1/INDEX($K$14:$AK$14, 1, ROW(A26))} -> 0.5 | K40: {=1/INDEX($L$15:$AK$15, 1, ROW(A25))} -> 0.5 | L40: {=1/INDEX($M$16:$AK$16, 1, ROW(A24))} -> 1 | M40: {=1/INDEX($N$17:$AK$17, 1, ROW(A23))} -> 1 | N40: {=1/INDEX($O$18:$AK$18, 1, ROW(A22))} -> 1 | O40: {=1/INDEX($P$19:$AK$19, 1, ROW(A21))} -> 1 | P40: {=1/INDEX($Q$20:$AK$20, 1, ROW(A20))} -> 1 | Q40: {=1/INDEX($R$21:$AK$21, 1, ROW(A19))} -> 1 | R40: {=1/INDEX($S$22:$AK$22, 1, ROW(A18))} -> 2 | S40: {=1/INDEX($T$23:$AK$23, 1, ROW(A17))} -> 0.5 | T40: {=1/INDEX($U$24:$AK$24, 1, ROW(A16))} -> 0.5 | U40: {=1/INDEX($V$25:$AK$25, 1, ROW(A15))} -> 0.5 | V40: {=1/INDEX($W$26:$AK$26, 1, ROW(A14))} -> 3 | W40: {=1/INDEX($X$27:$AK$27, 1, ROW(A13))} -> 0.5 | X40: {=1/INDEX($Y$28:$AK$28, 1, ROW(A12))} -> 0.2 | Y40: {=1/INDEX($Z$29:$AK$29, 1, ROW(A11))} -> 0.33333333 | Z40: {=1/INDEX($AA$30:$AK$30, 1, ROW(A10))} -> 2 | AA40: {=1/INDEX($AB$31:$AK$31, 1, ROW(A9))} -> 3 | AB40: {=1/INDEX($AC$32:$AK$32, 1, ROW(A8))} -> 0.25 | AC40: {=1/INDEX($AD$33:$AK$33, 1, ROW(A7))} -> 0.5 | AD40: {=1/INDEX($AE$34:$AK$34, 1, ROW(A6))} -> 0.5 | AE40: {=1/INDEX($AF$35:$AK$35, 1, ROW(A5))} -> 0.33333333 | AF40: {=1/INDEX($AG$36:$AK$36, 1, ROW(A4))} -> 0.5 | AG40: {=1/INDEX($AH$37:$AK$37, 1, ROW(A3))} -> 0.5 | AH40: {=1/INDEX($AI$38:$AK$38, 1, ROW(A2))} -> 0.5 | AI40: {=1/INDEX($AJ$39:$AK$39, 1, ROW(A1))} -> 2 | AJ40: 1 | AK40: 0.5 | AM40: =E40 -> Refill Water and Fire Retardants | AN40: =F40 -> 0.02325298 | AP40: =G40/SUM(G$11:G$41) -> 0.0087260035 | AQ40: =H40/SUM(H$11:H$41) -> 0.012 | AR40: =I40/SUM(I$11:I$41) -> 0.027027027 | AS40: =J40/SUM(J$11:J$41) -> 0.015856237 | AT40: =K40/SUM(K$11:K$41) -> 0.015856237 | AU40: =L40/SUM(L$11:L$41) -> 0.019920319 | AV40: =M40/SUM(M$11:M$41) -> 0.021052632 | AW40: =N40/SUM(N$11:N$41) -> 0.038461538 | ... BT40: =AK40/SUM(AK$11:AK$41) -> 0.0084745763
E41: Provide Logistic Support to Crews | F41: =AVERAGE(AP41:BT41) -> 0.023586871 | G41: {=1/INDEX($H$11:$AK$11, 1, ROW(A30))} -> 0.2 | H41: {=1/INDEX($I$12:$AK$12, 1, ROW(A29))} -> 0.33333333 | I41: {=1/INDEX($J$13:$AK$13, 1, ROW(A28))} -> 0.5 | J41: {=1/INDEX($K$14:$AK$14, 1, ROW(A27))} -> 0.33333333 | K41: {=1/INDEX($L$15:$AK$15, 1, ROW(A26))} -> 0.33333333 | L41: {=1/INDEX($M$16:$AK$16, 1, ROW(A25))} -> 2 | M41: {=1/INDEX($N$17:$AK$17, 1, ROW(A24))} -> 1 | N41: {=1/INDEX($O$18:$AK$18, 1, ROW(A23))} -> 0.5 | O41: {=1/INDEX($P$19:$AK$19, 1, ROW(A22))} -> 1 | P41: {=1/INDEX($Q$20:$AK$20, 1, ROW(A21))} -> 1 | Q41: {=1/INDEX($R$21:$AK$21, 1, ROW(A20))} -> 1 | R41: {=1/INDEX($S$22:$AK$22, 1, ROW(A19))} -> 2 | S41: {=1/INDEX($T$23:$AK$23, 1, ROW(A18))} -> 0.5 | T41: {=1/INDEX($U$24:$AK$24, 1, ROW(A17))} -> 0.33333333 | U41: {=1/INDEX($V$25:$AK$25, 1, ROW(A16))} -> 0.5 | V41: {=1/INDEX($W$26:$AK$26, 1, ROW(A15))} -> 3 | W41: {=1/INDEX($X$27:$AK$27, 1, ROW(A14))} -> 0.5 | X41: {=1/INDEX($Y$28:$AK$28, 1, ROW(A13))} -> 0.2 | Y41: {=1/INDEX($Z$29:$AK$29, 1, ROW(A12))} -> 0.5 | Z41: {=1/INDEX($AA$30:$AK$30, 1, ROW(A11))} -> 1 | AA41: {=1/INDEX($AB$31:$AK$31, 1, ROW(A10))} -> 3 | AB41: {=1/INDEX($AC$32:$AK$32, 1, ROW(A9))} -> 0.33333333 | AC41: {=1/INDEX($AD$33:$AK$33, 1, ROW(A8))} -> 0.5 | AD41: {=1/INDEX($AE$34:$AK$34, 1, ROW(A7))} -> 0.33333333 | AE41: {=1/INDEX($AF$35:$AK$35, 1, ROW(A6))} -> 0.25 | AF41: {=1/INDEX($AG$36:$AK$36, 1, ROW(A5))} -> 0.5 | AG41: {=1/INDEX($AH$37:$AK$37, 1, ROW(A4))} -> 0.5 | AH41: {=1/INDEX($AI$38:$AK$38, 1, ROW(A3))} -> 2 | AI41: {=1/INDEX($AJ$39:$AK$39, 1, ROW(A2))} -> 3 | AJ41: {=1/INDEX($AK$40:$AK$40, 1, ROW(A1))} -> 2 | AK41: 1 | AM41: =E41 -> Provide Logistic Support to Crews | AN41: =F41 -> 0.023586871 | AP41: =G41/SUM(G$11:G$41) -> 0.0052356021 | AQ41: =H41/SUM(H$11:H$41) -> 0.008 | AR41: =I41/SUM(I$11:I$41) -> 0.013513514 | AS41: =J41/SUM(J$11:J$41) -> 0.010570825 | AT41: =K41/SUM(K$11:K$41) -> 0.010570825 | AU41: =L41/SUM(L$11:L$41) -> 0.039840637 | AV41: =M41/SUM(M$11:M$41) -> 0.021052632 | AW41: =N41/SUM(N$11:N$41) -> 0.019230769 | ... BT41: =AK41/SUM(AK$11:AK$41) -> 0.016949153
F42: =SUM(F11:F41) -> 1

Sheet Function Categorization
A1: Category Types (Enabler, Execution, Support)
A3: Type | B3: Definition | D3: Function | E3: Category | F3: Justification | H3: Function | I3: Value
A4: Enabler | B4: These initiate, coordinate, or enable execution functions. | D4: Deploy Air Assets | E4: Enabler | F4: Enables airborne suppression; assets must be in place before any aerial action. | H4: ='Function Criticality'!E28 -> Build Real Time Situational Awareness | I4: ='Function Criticality'!F28 -> 0.053081244
A5: Execution | B5: These directly act on the fire or mission-critical operations. | D5: Lead Tankers | E5: Enabler | F5: Provides targeting and coordination for aerial suppression drops. | H5: ='Function Criticality'!E23 -> Detect Fires | I5: ='Function Criticality'!F23 -> 0.041210309
A6: Support | B6: These maintain and sustain operations. | D6: Supervise Air Attacks (AAGs) | E6: Enabler | F6: Ensures safe and coordinated air attacks during fire response. | H6: ='Function Criticality'!E32 -> Communicate to Resources | I6: ='Function Criticality'!F32 -> 0.039361135
D7: Deploy Ground Assets | E7: Enabler | F7: Initiates ground-level firefighting efforts by placing resources in the field. | H7: ='Function Criticality'!E24 -> Visually Confirm Fires | I7: ='Function Criticality'!F24 -> 0.037248096
A8: Note: | B8: Enablers usually rank slightly higher because without them, execution never occurs. | D8: Predict New Fires | E8: Enabler | F8: Supports proactive planning by identifying potential new fire outbreaks. | H8: ='Function Criticality'!E25 -> Predict Fire Paths/Behavior | I8: ='Function Criticality'!F25 -> 0.037095433
D9: Predict Fire Paths/Behavior | E9: Enabler | F9: Used to forecast fire behavior, aiding in positioning and response strategy. | H9: ='Function Criticality'!E31 -> Issue Commands to Assets | I9: ='Function Criticality'!F31 -> 0.036661629
D10: Coordinate Air & Ground Resources | E10: Enabler | F10: Synchronizes multi-domain (air/ground) operations for effectiveness. | H10: ='Function Criticality'!E35 -> Deploy First Response Ground Assets | I10: ='Function Criticality'!F35 -> 0.036581027
D11: Dynamically Allocate Resources | E11: Enabler | F11: Adjusts resources in real-time based on evolving fire conditions. | H11: ='Function Criticality'!E18 -> Deploy Ground Assets | I11: ='Function Criticality'!F18 -> 0.036459978
D12: Issue Commands to Assets | E12: Enabler | F12: Delivers real-time instructions that drive operational execution. | H12: ='Function Criticality'!E11 -> Deploy Air Assets | I12: ='Function Criticality'!F11 -> 0.035885211
D13: Maintain Communication Between Assets and C3 | E13: Enabler | F13: Allows coordination between field units and central command. | H13: ='Function Criticality'!E15 -> Drop Fire Retardant | I13: ='Function Criticality'!F15 -> 0.034905052
D14: Deploy First Response Ground Assets | E14: Enabler | F14: Enables rapid deployment of teams during initial response window. | H14: ='Function Criticality'!E14 -> Drop Water | I14: ='Function Criticality'!F14 -> 0.034905052
D15: Deploy Smokejumpers | E15: Enabler | F15: Delivers fast-response units into inaccessible or remote areas. | H15: ='Function Criticality'!E12 -> Lead Tankers | I15: ='Function Criticality'!F12 -> 0.034871282
D16: Activate MAFFS | E16: Enabler | F16: Converts military transports into suppression-capable aircraft. | H16: ='Function Criticality'!E29 -> Coordinate Air & Ground Resources | I16: ='Function Criticality'!F29 -> 0.034671264
D17: Drop Water | E17: Execution | F17: Primary method of aerial fire suppression using water. | H17: ='Function Criticality'!E33 -> Maintain Communication Among Assets | I17: ='Function Criticality'!F33 -> 0.033904731
D18: Drop Fire Retardant | E18: Execution | F18: Primary suppression method using chemical retardants. | H18: ='Function Criticality'!E21 -> Tactically Monitor Fires | I18: ='Function Criticality'!F21 -> 0.033290765
D19: Perform Post-Drop Assessment | E19: Execution | F19: Evaluates the effectiveness of suppression drops post-action. | H19: ='Function Criticality'!E27 -> Gather Real Time Data from Assets | I19: ='Function Criticality'!F27 -> 0.032488808
D20: Establish Containment Lines | E20: Execution | F20: Creates physical boundaries to contain and stop fire spread. | H20: ='Function Criticality'!E19 -> Establish Containment Lines | I20: ='Function Criticality'!F19 -> 0.032282337
D21: Spill Water from Ground Assets | E21: Execution | F21: Used by ground units for direct fire suppression on-site. | H21: ='Function Criticality'!E20 -> Spill Water from Ground Assets | I21: ='Function Criticality'!F20 -> 0.031946995
D22: Tactically Monitor Fires | E22: Execution | F22: Informs real-time decisions through local fire monitoring. | H22: ='Function Criticality'!E34 -> Maintain Communication Between Assets and C3 | I22: ='Function Criticality'!F34 -> 0.031354935
D23: Detect Fires | E23: Execution | F23: Initiates the response system by detecting wildfire presence. | H23: ='Function Criticality'!E37 -> Activate MAFFS | I23: ='Function Criticality'!F37 -> 0.03073345
D24: Visually Confirm Fires | E24: Execution | F24: Confirms presence and location of fire for further action. | H24: ='Function Criticality'!E36 -> Deploy Smokejumpers | I24: ='Function Criticality'!F36 -> 0.030378516
D25: Strategically Monitor Fires | E25: Execution | F25: Guides suppression efforts through wide-area fire tracking. | H25: ='Function Criticality'!E30 -> Dynamically Allocate Resources | I25: ='Function Criticality'!F30 -> 0.027769727
D26: Gather Real Time Data from Assets | E26: Execution | F26: Feeds command with current field conditions to guide actions. | H26: ='Function Criticality'!E13 -> Supervise Air Attacks (AAGs) | I26: ='Function Criticality'!F13 -> 0.027309127
D27: Build Real Time Situational Awareness | E27: Execution | F27: Synthesizes incoming data for holistic fire status tracking. | H27: ='Function Criticality'!E26 -> Strategically Monitor Fires | I27: ='Function Criticality'!F26 -> 0.027178717
D28: Dispatch To Reloading Base | E28: Support | F28: Redirects aircraft to base to prepare for subsequent drops. | H28: ='Function Criticality'!E22 -> Predict New Fires | I28: ='Function Criticality'!F22 -> 0.026479119
D29: Communicate to Resources | E29: Support | F29: Ensures responders receive critical information for action. | H29: ='Function Criticality'!E38 -> Refuel Airborne Assets | I29: ='Function Criticality'!F38 -> 0.026263482
D30: Maintain Communication Among Assets | E30: Support | F30: Prevents miscoordination by keeping responders in sync. | H30: ='Function Criticality'!E16 -> Perform Post-Drop Assessment | I30: ='Function Criticality'!F16 -> 0.024850734
D31: Refuel Airborne Assets | E31: Support | F31: Sustains aircraft availability through fuel replenishment. | H31: ='Function Criticality'!E41 -> Provide Logistic Support to Crews | I31: ='Function Criticality'!F41 -> 0.023586871
D32: Provide MRO for Assets | E32: Support | F32: Maintains asset functionality for continued operations. | H32: ='Function Criticality'!E40 -> Refill Water and Fire Retardants | I32: ='Function Criticality'!F40 -> 0.02325298
D33: Refill Water and Fire Retardants | E33: Support | F33: Replenishes key suppression materials between missions. | H33: ='Function Criticality'!E39 -> Provide MRO for Assets | I33: ='Function Criticality'!F39 -> 0.022408033
D34: Provide Logistic Support to Crews | E34: Support | F34: Ensures crews have supplies and logistics to operate effectively. | H34: ='Function Criticality'!E17 -> Dispatch To Reloading Base | I34: ='Function Criticality'!F17 -> 0.021583962

Sheet Utility AHP
B2: Rankings | E2: Key Note:
B3: Importance | C3: Definition | E3: Type metric name in gray
B4: 1 | C4: Equal Importance | E4: Only type comparison values in white areas
B5: 3 | C5: Moderate Importance
B6: 5 | C6: Strong Importance | E6: You have to open in the desktop app to copy and paste with the formulas
B7: 7 | C7: Very Strong Importance
B8: 9 | C8: Extreme Importance
E10: California Fire | F10: Criticality Weights | G10: =E11 -> Detection Time | H10: =E12 -> Operational Availability | I10: =E13 -> Response Time | J10: =E14 -> Resolution Time | K10: =E15 -> Interdomain Coordination Latency | L10: =E16 -> Fire Supression Cost Efficiency | M10: =E17 -> CO2 Emissions | O10: Interface | P10: Importance
E11: Detection Time | F11: =AVERAGE(R11:X11) -> 0.20240212 | G11: 1 | H11: 1 | I11: 3 | J11: =1/3 -> 0.33333333 | K11: 9 | L11: 7 | M11: 7 | O11: =E11 -> Detection Time | P11: =F11 -> 0.20240212 | R11: =G11/SUM(G$11:G$17) -> 0.17451524 | S11: =H11/SUM(H$11:H$17) -> 0.17451524 | T11: =I11/SUM(I$11:I$17) -> 0.23725835 | U11: =J11/SUM(J$11:J$17) -> 0.14935989 | V11: =K11/SUM(K$11:K$17) -> 0.23978686 | W11: =L11/SUM(L$11:L$17) -> 0.24137931 | X11: =M11/SUM(M$11:M$17) -> 0.2
E12: Operational Availability | F12: =AVERAGE(R12:X12) -> 0.20240212 | G12: {=1/INDEX($H$11:$M$11, 1, ROW(A1))} -> 1 | H12: 1 | I12: 3 | J12: =1/3 -> 0.33333333 | K12: 9 | L12: 7 | M12: 7 | O12: =E12 -> Operational Availability | P12: =F12 -> 0.20240212 | R12: =G12/SUM(G$11:G$17) -> 0.17451524 | S12: =H12/SUM(H$11:H$17) -> 0.17451524 | T12: =I12/SUM(I$11:I$17) -> 0.23725835 | U12: =J12/SUM(J$11:J$17) -> 0.14935989 | V12: =K12/SUM(K$11:K$17) -> 0.23978686 | W12: =L12/SUM(L$11:L$17) -> 0.24137931 | X12: =M12/SUM(M$11:M$17) -> 0.2
E13: Response Time | F13: =AVERAGE(R13:X13) -> 0.11016254 | G13: {=1/INDEX($H$11:$M$11, 1, ROW(A2))} -> 0.33333333 | H13: {=1/INDEX($I$12:$M$12, 1, ROW(A1))} -> 0.33333333 | I13: 1 | J13: =1/5 -> 0.2 | K13: 9 | L13: 3 | M13: 5 | O13: =E13 -> Response Time | P13: =F13 -> 0.11016254 | R13: =G13/SUM(G$11:G$17) -> 0.058171745 | S13: =H13/SUM(H$11:H$17) -> 0.058171745 | T13: =I13/SUM(I$11:I$17) -> 0.079086116 | U13: =J13/SUM(J$11:J$17) -> 0.089615932 | V13: =K13/SUM(K$11:K$17) -> 0.23978686 | W13: =L13/SUM(L$11:L$17) -> 0.10344828 | X13: =M13/SUM(M$11:M$17) -> 0.14285714
E14: Resolution Time | F14: =AVERAGE(R14:X14) -> 0.37555867 | G14: {=1/INDEX($H$11:$M$11, 1, ROW(A3))} -> 3 | H14: {=1/INDEX($I$12:$M$12, 1, ROW(A2))} -> 3 | I14: {=1/INDEX($J$13:$M$13, 1, ROW(A1))} -> 5 | J14: 1 | K14: 9 | L14: 7 | M14: 9 | O14: =E14 -> Resolution Time | P14: =F14 -> 0.37555867 | R14: =G14/SUM(G$11:G$17) -> 0.52354571 | S14: =H14/SUM(H$11:H$17) -> 0.52354571 | T14: =I14/SUM(I$11:I$17) -> 0.39543058 | U14: =J14/SUM(J$11:J$17) -> 0.44807966 | V14: =K14/SUM(K$11:K$17) -> 0.23978686 | W14: =L14/SUM(L$11:L$17) -> 0.24137931 | X14: =M14/SUM(M$11:M$17) -> 0.25714286
E15: Interdomain Coordination Latency | F15: =AVERAGE(R15:X15) -> 0.052900506 | G15: {=1/INDEX($H$11:$M$11, 1, ROW(A4))} -> 0.11111111 | H15: {=1/INDEX($I$12:$M$12, 1, ROW(A3))} -> 0.11111111 | I15: {=1/INDEX($J$13:$M$13, 1, ROW(A2))} -> 0.11111111 | J15: {=1/INDEX($K$14:$M$14, 1, ROW(A1))} -> 0.11111111 | K15: 1 | L15: 3 | M15: 5 | O15: =E15 -> Interdomain Coordination Latency | P15: =F15 -> 0.052900506 | R15: =G15/SUM(G$11:G$17) -> 0.019390582 | S15: =H15/SUM(H$11:H$17) -> 0.019390582 | T15: =I15/SUM(I$11:I$17) -> 0.0087873462 | U15: =J15/SUM(J$11:J$17) -> 0.049786629 | V15: =K15/SUM(K$11:K$17) -> 0.026642984 | W15: =L15/SUM(L$11:L$17) -> 0.10344828 | X15: =M15/SUM(M$11:M$17) -> 0.14285714
E16: Fire Supression Cost Efficiency | F16: =AVERAGE(R16:X16) -> 0.030310014 | G16: {=1/INDEX($H$11:$M$11, 1, ROW(A5))} -> 0.14285714 | H16: {=1/INDEX($I$12:$M$12, 1, ROW(A4))} -> 0.14285714 | I16: {=1/INDEX($J$13:$M$13, 1, ROW(A3))} -> 0.33333333 | J16: {=1/INDEX($K$14:$M$14, 1, ROW(A2))} -> 0.14285714 | K16: {=1/INDEX($L$15:$M$15, 1, ROW(A1))} -> 0.33333333 | L16: 1 | M16: 1 | O16: =E16 -> Fire Supression Cost Efficiency | P16: =F16 -> 0.030310014 | R16: =G16/SUM(G$11:G$17) -> 0.024930748 | S16: =H16/SUM(H$11:H$17) -> 0.024930748 | T16: =I16/SUM(I$11:I$17) -> 0.026362039 | U16: =J16/SUM(J$11:J$17) -> 0.06401138 | V16: =K16/SUM(K$11:K$17) -> 0.0088809947 | W16: =L16/SUM(L$11:L$17) -> 0.034482759 | X16: =M16/SUM(M$11:M$17) -> 0.028571429
E17: CO2 Emissions | F17: =AVERAGE(R17:X17) -> 0.026264019 | G17: {=1/INDEX($H$11:$M$11, 1, ROW(A6))} -> 0.14285714 | H17: {=1/INDEX($I$12:$M$12, 1, ROW(A5))} -> 0.14285714 | I17: {=1/INDEX($J$13:$M$13, 1, ROW(A4))} -> 0.2 | J17: {=1/INDEX($K$14:$M$14, 1, ROW(A3))} -> 0.11111111 | K17: {=1/INDEX($L$15:$M$15, 1, ROW(A2))} -> 0.2 | L17: {=1/INDEX($M$16:$M$16, 1, ROW(A1))} -> 1 | M17: 1 | O17: =E17 -> CO2 Emissions | P17: =F17 -> 0.026264019 | R17: =G17/SUM(G$11:G$17) -> 0.024930748 | S17: =H17/SUM(H$11:H$17) -> 0.024930748 | T17: =I17/SUM(I$11:I$17) -> 0.015817223 | U17: =J17/SUM(J$11:J$17) -> 0.049786629 | V17: =K17/SUM(K$11:K$17) -> 0.0053285968 | W17: =L17/SUM(L$11:L$17) -> 0.034482759 | X17: =M17/SUM(M$11:M$17) -> 0.028571429
F18: =SUM(F11:F17) -> 1
E23: International Collaboration Fire | F23: Criticality Weights | G23: =E24 -> Detection Time | H23: =E25 -> Operational Availability | I23: =E26 -> Response Time | J23: =E27 -> Resolution Time | K23: =E28 -> Interdomain Coordination Latency | L23: =E29 -> Fire Supression Cost Efficiency | M23: =E30 -> CO2 Emissions | O23: Interface | P23: Importance
E24: Detection Time | F24: =AVERAGE(R24:X24) -> 0.12379143 | G24: 1 | H24: 1 | I24: 3 | J24: =1/5 -> 0.2 | K24: =1/5 -> 0.2 | L24: 9 | M24: 3 | O24: =E24 -> Detection Time | P24: =F24 -> 0.12379143 | R24: =G24/SUM(G$24:G$30) -> 0.07826087 | S24: =H24/SUM(H$24:H$30) -> 0.215311 | T24: =I24/SUM(I$24:I$30) -> 0.14018692 | U24: =J24/SUM(J$24:J$30) -> 0.073170732 | V24: =K24/SUM(K$24:K$30) -> 0.025392987 | W24: =L24/SUM(L$24:L$30) -> 0.23076923 | X24: =M24/SUM(M$24:M$30) -> 0.10344828
E25: Operational Availability | F25: =AVERAGE(R25:X25) -> 0.21304328 | G25: {=1/INDEX($H$24:$M$24, 1, ROW(A1))} -> 1 | H25: 1 | I25: 5 | J25: 1 | K25: 1 | L25: 9 | M25: 3 | O25: =E25 -> Operational Availability | P25: =F25 -> 0.21304328 | R25: =G25/SUM(H$24:H$30) -> 0.215311 | S25: =H25/SUM(H$24:H$30) -> 0.215311 | T25: =I25/SUM(I$24:I$30) -> 0.23364486 | U25: =J25/SUM(J$24:J$30) -> 0.36585366 | V25: =K25/SUM(K$24:K$30) -> 0.12696493 | W25: =L25/SUM(L$24:L$30) -> 0.23076923 | X25: =M25/SUM(M$24:M$30) -> 0.10344828
E26: Response Time | F26: =AVERAGE(R26:X26) -> 0.071352729 | G26: {=1/INDEX($H$24:$M$24, 1, ROW(A2))} -> 0.33333333 | H26: {=1/INDEX($I$25:$M$25, 1, ROW(A1))} -> 0.2 | I26: 1 | J26: =1/9 -> 0.11111111 | K26: =1/3 -> 0.33333333 | L26: 5 | M26: 5 | O26: =E26 -> Response Time | P26: =F26 -> 0.071352729 | R26: =G26/SUM(G$24:G$30) -> 0.026086957 | S26: =H26/SUM(H$24:H$30) -> 0.043062201 | T26: =I26/SUM(I$24:I$30) -> 0.046728972 | U26: =J26/SUM(J$24:J$30) -> 0.040650407 | V26: =K26/SUM(K$24:K$30) -> 0.042321644 | W26: =L26/SUM(L$24:L$30) -> 0.12820513 | X26: =M26/SUM(M$24:M$30) -> 0.17241379
E27: Resolution Time | F27: =AVERAGE(R27:X27) -> 0.3669955 | G27: {=1/INDEX($H$24:$M$24, 1, ROW(A3))} -> 5 | H27: {=1/INDEX($I$25:$M$25, 1, ROW(A2))} -> 1 | I27: {=1/INDEX($J$26:$M$26, 1, ROW(A1))} -> 9 | J27: 1 | K27: 5 | L27: 9 | M27: 9 | O27: =E27 -> Resolution Time | P27: =F27 -> 0.3669955 | R27: =G27/SUM(G$24:G$30) -> 0.39130435 | S27: =H27/SUM(H$24:H$30) -> 0.215311 | T27: =I27/SUM(I$24:I$30) -> 0.42056075 | U27: =J27/SUM(J$24:J$30) -> 0.36585366 | V27: =K27/SUM(K$24:K$30) -> 0.63482467 | W27: =L27/SUM(L$24:L$30) -> 0.23076923 | X27: =M27/SUM(M$24:M$30) -> 0.31034483
E28: Interdomain Coordination Latency | F28: =AVERAGE(R28:X28) -> 0.18807462 | G28: {=1/INDEX($H$24:$M$24, 1, ROW(A4))} -> 5 | H28: {=1/INDEX($I$25:$M$25, 1, ROW(A3))} -> 1 | I28: {=1/INDEX($J$26:$M$26, 1, ROW(A2))} -> 3 | J28: {=1/INDEX($K$27:$M$27, 1, ROW(A1))} -> 0.2 | K28: 1 | L28: 5 | M28: 7 | O28: =E28 -> Interdomain Coordination Latency | P28: =F28 -> 0.18807462 | R28: =G28/SUM(G$24:G$30) -> 0.39130435 | S28: =H28/SUM(H$24:H$30) -> 0.215311 | T28: =I28/SUM(I$24:I$30) -> 0.14018692 | U28: =J28/SUM(J$24:J$30) -> 0.073170732 | V28: =K28/SUM(K$24:K$30) -> 0.12696493 | W28: =L28/SUM(L$24:L$30) -> 0.12820513 | X28: =M28/SUM(M$24:M$30) -> 0.24137931
E29: Fire Supression Cost Efficiency | F29: =AVERAGE(R29:X29) -> 0.024018867 | G29: {=1/INDEX($H$24:$M$24, 1, ROW(A5))} -> 0.11111111 | H29: {=1/INDEX($I$25:$M$25, 1, ROW(A4))} -> 0.11111111 | I29: {=1/INDEX($J$26:$M$26, 1, ROW(A3))} -> 0.2 | J29: {=1/INDEX($K$27:$M$27, 1, ROW(A2))} -> 0.11111111 | K29: {=1/INDEX($L$28:$M$28, 1, ROW(A1))} -> 0.2 | L29: 1 | M29: 1 | O29: =E29 -> Fire Supression Cost Efficiency | P29: =F29 -> 0.024018867 | R29: =G29/SUM(G$24:G$30) -> 0.0086956522 | S29: =H29/SUM(H$24:H$30) -> 0.023923445 | T29: =I29/SUM(I$24:I$30) -> 0.0093457944 | U29: =J29/SUM(J$24:J$30) -> 0.040650407 | V29: =K29/SUM(K$24:K$30) -> 0.025392987 | W29: =L29/SUM(L$24:L$30) -> 0.025641026 | X29: =M29/SUM(M$24:M$30) -> 0.034482759
E30: CO2 Emissions | F30: =AVERAGE(R30:X30) -> 0.032302161 | G30: {=1/INDEX($H$24:$M$24, 1, ROW(A6))} -> 0.33333333 | H30: {=1/INDEX($I$25:$M$25, 1, ROW(A5))} -> 0.33333333 | I30: {=1/INDEX($J$26:$M$26, 1, ROW(A4))} -> 0.2 | J30: {=1/INDEX($K$27:$M$27, 1, ROW(A3))} -> 0.11111111 | K30: {=1/INDEX($L$28:$M$28, 1, ROW(A2))} -> 0.14285714 | L30: {=1/INDEX($M$29:$M$29, 1, ROW(A1))} -> 1 | M30: 1 | O30: =E30 -> CO2 Emissions | P30: =F30 -> 0.032302161 | R30: =G30/SUM(G$24:G$30) -> 0.026086957 | S30: =H30/SUM(H$24:H$30) -> 0.071770335 | T30: =I30/SUM(I$24:I$30) -> 0.0093457944 | U30: =J30/SUM(J$24:J$30) -> 0.040650407 | V30: =K30/SUM(K$24:K$30) -> 0.018137848 | W30: =L30/SUM(L$24:L$30) -> 0.025641026 | X30: =M30/SUM(M$24:M$30) -> 0.034482759
F31: =SUM(F24:F30) -> 1.0195786
E40: Underdeveloped Country Fire | F40: Criticality Weights | G40: =E41 -> Detection Time | H40: =E42 -> Operational Availability | I40: =E43 -> Response Time | J40: =E44 -> Resolution Time | K40: =E45 -> Interdomain Coordination Latency | L40: =E46 -> Fire Supression Cost Efficiency | M40: =E47 -> CO2 Emissions | O40: Interface | P40: Importance
E41: Detection Time | F41: =AVERAGE(R41:X41) -> 0.13712475 | G41: 1 | H41: 1 | I41: 1 | J41: 1 | K41: 3 | L41: =1/7 -> 0.14285714 | M41: 9 | O41: =E41 -> Detection Time | P41: =F41 -> 0.13712475 | R41: =G41/SUM(G$41:G$47) -> 0.087378641 | S41: =H41/SUM(H$41:H$47) -> 0.19033233 | T41: =I41/SUM(I$41:I$47) -> 0.19033233 | U41: =J41/SUM(J$41:J$47) -> 0.19033233 | V41: =K41/SUM(K$41:K$47) -> 0.10671937 | W41: =L41/SUM(L$41:L$47) -> 0.031141869 | X41: =M41/SUM(M$41:M$47) -> 0.16363636
E42: Operational Availability | F42: =AVERAGE(R42:X42) -> 0.18414527 | G42: {=1/INDEX($H$41:$M$41, 1, ROW(A1))} -> 1 | H42: 1 | I42: 1 | J42: 1 | K42: 7 | L42: 1 | M42: 9 | O42: =E42 -> Operational Availability | P42: =F42 -> 0.18414527 | R42: =G42/SUM(G$41:G$47) -> 0.087378641 | S42: =H42/SUM(H$41:H$47) -> 0.19033233 | T42: =I42/SUM(I$41:I$47) -> 0.19033233 | U42: =J42/SUM(J$41:J$47) -> 0.19033233 | V42: =K42/SUM(K$41:K$47) -> 0.24901186 | W42: =L42/SUM(L$41:L$47) -> 0.21799308 | X42: =M42/SUM(M$41:M$47) -> 0.16363636
E43: Response Time | F43: =AVERAGE(R43:X43) -> 0.18414527 | G43: {=1/INDEX($H$41:$M$41, 1, ROW(A2))} -> 1 | H43: {=1/INDEX($I$42:$M$42, 1, ROW(A1))} -> 1 | I43: 1 | J43: 1 | K43: 7 | L43: 1 | M43: 9 | O43: =E43 -> Response Time | P43: =F43 -> 0.18414527 | R43: =G43/SUM(G$41:G$47) -> 0.087378641 | S43: =H43/SUM(H$41:H$47) -> 0.19033233 | T43: =I43/SUM(I$41:I$47) -> 0.19033233 | U43: =J43/SUM(J$41:J$47) -> 0.19033233 | V43: =K43/SUM(K$41:K$47) -> 0.24901186 | W43: =L43/SUM(L$41:L$47) -> 0.21799308 | X43: =M43/SUM(M$41:M$47) -> 0.16363636
E44: Resolution Time | F44: =AVERAGE(R44:X44) -> 0.18414527 | G44: {=1/INDEX($H$41:$M$41, 1, ROW(A3))} -> 1 | H44: {=1/INDEX($I$42:$M$42, 1, ROW(A2))} -> 1 | I44: {=1/INDEX($J$43:$M$43, 1, ROW(A1))} -> 1 | J44: 1 | K44: 7 | L44: 1 | M44: 9 | O44: =E44 -> Resolution Time | P44: =F44 -> 0.18414527 | R44: =G44/SUM(G$41:G$47) -> 0.087378641 | S44: =H44/SUM(H$41:H$47) -> 0.19033233 | T44: =I44/SUM(I$41:I$47) -> 0.19033233 | U44: =J44/SUM(J$41:J$47) -> 0.19033233 | V44: =K44/SUM(K$41:K$47) -> 0.24901186 | W44: =L44/SUM(L$41:L$47) -> 0.21799308 | X44: =M44/SUM(M$41:M$47) -> 0.16363636
E45: Interdomain Coordination Latency | F45: =AVERAGE(R45:X45) -> 0.054653008 | G45: {=1/INDEX($H$41:$M$41, 1, ROW(A4))} -> 0.33333333 | H45: {=1/INDEX($I$42:$M$42, 1, ROW(A3))} -> 0.14285714 | I45: {=1/INDEX($J$43:$M$43, 1, ROW(A2))} -> 0.14285714 | J45: {=1/INDEX($K$44:$M$44, 1, ROW(A1))} -> 0.14285714 | K45: 1 | L45: =1/3 -> 0.33333333 | M45: 9 | O45: =E45 -> Interdomain Coordination Latency | P45: =F45 -> 0.054653008 | R45: =G45/SUM(G$41:G$47) -> 0.029126214 | S45: =H45/SUM(H$41:H$47) -> 0.027190332 | T45: =I45/SUM(I$41:I$47) -> 0.027190332 | U45: =J45/SUM(J$41:J$47) -> 0.027190332 | V45: =K45/SUM(K$41:K$47) -> 0.035573123 | W45: =L45/SUM(L$41:L$47) -> 0.07266436 | X45: =M45/SUM(M$41:M$47) -> 0.16363636
E46: Fire Supression Cost Efficiency | F46: =AVERAGE(R46:X46) -> 0.23871375 | G46: {=1/INDEX($H$41:$M$41, 1, ROW(A5))} -> 7 | H46: {=1/INDEX($I$42:$M$42, 1, ROW(A4))} -> 1 | I46: {=1/INDEX($J$43:$M$43, 1, ROW(A3))} -> 1 | J46: {=1/INDEX($K$44:$M$44, 1, ROW(A2))} -> 1 | K46: {=1/INDEX($L$45:$M$45, 1, ROW(A1))} -> 3 | L46: 1 | M46: 9 | O46: =E46 -> Fire Supression Cost Efficiency | P46: =F46 -> 0.23871375 | R46: =G46/SUM(G$41:G$47) -> 0.61165049 | S46: =H46/SUM(H$41:H$47) -> 0.19033233 | T46: =I46/SUM(I$41:I$47) -> 0.19033233 | U46: =J46/SUM(J$41:J$47) -> 0.19033233 | V46: =K46/SUM(K$41:K$47) -> 0.10671937 | W46: =L46/SUM(L$41:L$47) -> 0.21799308 | X46: =M46/SUM(M$41:M$47) -> 0.16363636
E47: CO2 Emissions | F47: =AVERAGE(R47:X47) -> 0.01707267 | G47: {=1/INDEX($H$41:$M$41, 1, ROW(A6))} -> 0.11111111 | H47: {=1/INDEX($I$42:$M$42, 1, ROW(A5))} -> 0.11111111 | I47: {=1/INDEX($J$43:$M$43, 1, ROW(A4))} -> 0.11111111 | J47: {=1/INDEX($K$44:$M$44, 1, ROW(A3))} -> 0.11111111 | K47: {=1/INDEX($L$45:$M$45, 1, ROW(A2))} -> 0.11111111 | L47: {=1/INDEX($M$46:$M$46, 1, ROW(A1))} -> 0.11111111 | M47: 1 | O47: =E47 -> CO2 Emissions | P47: =F47 -> 0.01707267 | R47: =G47/SUM(G$41:G$47) -> 0.0097087379 | S47: =H47/SUM(H$41:H$47) -> 0.021148036 | T47: =I47/SUM(I$41:I$47) -> 0.021148036 | U47: =J47/SUM(J$41:J$47) -> 0.021148036 | V47: =K47/SUM(K$41:K$47) -> 0.0039525692 | W47: =L47/SUM(L$41:L$47) -> 0.024221453 | X47: =M47/SUM(M$41:M$47) -> 0.018181818
F48: =SUM(F41:F47) -> 1

Sheet Utility AHP (2)
B2: Rankings | E2: Key Note:
B3: Importance | C3: Definition | E3: Type metric name in gray
B4: 1 | C4: Equal Importance | E4: Only type comparison values in white areas
B5: 3 | C5: Moderate Importance
B6: 5 | C6: Strong Importance | E6: You have to open in the desktop app to copy and paste with the formulas
B7: 7 | C7: Very Strong Importance
B8: 9 | C8: Extreme Importance
E10: High Resource Fire | F10: Criticality Weights | G10: =E11 -> Resolution Time | H10: =E12 -> Burn Burden | I10: =E13 -> Total Cost | J10: =E14 -> CO2 Emissions | L10: Interface | M10: Importance
E11: Resolution Time | F11: =AVERAGE(O11:R11) -> 0.45913462 | G11: 1 | H11: 1 | I11: 5 | J11: 9 | L11: =E11 -> Resolution Time | M11: =F11 -> 0.45913462 | O11: =G11/SUM(G$11:G$14) -> 0.43269231 | P11: =H11/SUM(H$11:H$14) -> 0.40384615 | Q11: =I11/SUM(I$11:I$14) -> 0.35714286 | R11: =J11/SUM(J$11:J$14) -> 0.64285714
E12: Burn Burden | F12: =AVERAGE(O12:R12) -> 0.38770604 | G12: {=1/INDEX($H$11:$J$11, 1, ROW(A1))} -> 1 | H12: 1 | I12: 7 | J12: 3 | L12: =E12 -> Burn Burden | M12: =F12 -> 0.38770604 | O12: =G12/SUM(G$11:G$14) -> 0.43269231 | P12: =H12/SUM(H$11:H$14) -> 0.40384615 | Q12: =I12/SUM(I$11:I$14) -> 0.5 | R12: =J12/SUM(J$11:J$14) -> 0.21428571
E13: Total Cost | F13: =AVERAGE(O13:R13) -> 0.071771978 | G13: {=1/INDEX($H$11:$J$11, 1, ROW(A2))} -> 0.2 | H13: {=1/INDEX($I$12:$J$12, 1, ROW(A1))} -> 0.14285714 | I13: 1 | J13: 1 | L13: =E13 -> Total Cost | M13: =F13 -> 0.071771978 | O13: =G13/SUM(G$11:G$14) -> 0.086538462 | P13: =H13/SUM(H$11:H$14) -> 0.057692308 | Q13: =I13/SUM(I$11:I$14) -> 0.071428571 | R13: =J13/SUM(J$11:J$14) -> 0.071428571
E14: CO2 Emissions | F14: =AVERAGE(O14:R14) -> 0.081387363 | G14: {=1/INDEX($H$11:$J$11, 1, ROW(A3))} -> 0.11111111 | H14: {=1/INDEX($I$12:$J$12, 1, ROW(A2))} -> 0.33333333 | I14: {=1/INDEX($J$13:$J$13, 1, ROW(A1))} -> 1 | J14: 1 | L14: =E14 -> CO2 Emissions | M14: =F14 -> 0.081387363 | O14: =G14/SUM(G$11:G$14) -> 0.048076923 | P14: =H14/SUM(H$11:H$14) -> 0.13461538 | Q14: =I14/SUM(I$11:I$14) -> 0.071428571 | R14: =J14/SUM(J$11:J$14) -> 0.071428571
F15: =SUM(F11:F14) -> 1
E20: International Collaboration Fire | F20: Criticality Weights | G20: =E21 -> Resolution Time | H20: =E22 -> Burn Burden | I20: =E23 -> Total Cost | J20: =E24 -> CO2 Emissions | L20: Interface | M20: Importance
E21: Resolution Time | F21: =AVERAGE(O21:R21) -> 0.38266254 | G21: 1 | H21: 1 | I21: 3 | J21: 5 | L21: =E21 -> Resolution Time | M21: =F21 -> 0.38266254 | O21: =G21/SUM(G$21:G$24) -> 0.39473684 | P21: =H21/SUM(H$21:H$24) -> 0.39473684 | Q21: =I21/SUM(I$21:I$24) -> 0.3 | R21: =J21/SUM(J$21:J$24) -> 0.44117647
E22: Burn Burden | F22: =AVERAGE(O22:R22) -> 0.38266254 | G22: {=1/INDEX($H$21:$J$21, 1, ROW(A1))} -> 1 | H22: 1 | I22: 3 | J22: 5 | L22: =E22 -> Burn Burden | M22: =F22 -> 0.38266254 | O22: =G22/SUM(G$21:G$24) -> 0.39473684 | P22: =H22/SUM(H$21:H$24) -> 0.39473684 | Q22: =I22/SUM(I$21:I$24) -> 0.3 | R22: =J22/SUM(J$21:J$24) -> 0.44117647
E23: Total Cost | F23: =AVERAGE(O23:R23) -> 0.098142415 | G23: {=1/INDEX($H$21:$J$21, 1, ROW(A2))} -> 0.33333333 | H23: {=1/INDEX($I$22:$J$22, 1, ROW(A1))} -> 0.33333333 | I23: 1 | J23: =1/3 -> 0.33333333 | L23: =E23 -> Total Cost | M23: =F23 -> 0.098142415 | O23: =G23/SUM(G$21:G$24) -> 0.13157895 | P23: =H23/SUM(H$21:H$24) -> 0.13157895 | Q23: =I23/SUM(I$21:I$24) -> 0.1 | R23: =J23/SUM(J$21:J$24) -> 0.029411765
E24: CO2 Emissions | F24: =AVERAGE(O24:R24) -> 0.13653251 | G24: {=1/INDEX($H$21:$J$21, 1, ROW(A3))} -> 0.2 | H24: {=1/INDEX($I$22:$J$22, 1, ROW(A2))} -> 0.2 | I24: {=1/INDEX($J$23:$J$23, 1, ROW(A1))} -> 3 | J24: 1 | L24: =E24 -> CO2 Emissions | M24: =F24 -> 0.13653251 | O24: =G24/SUM(G$21:G$24) -> 0.078947368 | P24: =H24/SUM(H$21:H$24) -> 0.078947368 | Q24: =I24/SUM(I$21:I$24) -> 0.3 | R24: =J24/SUM(J$21:J$24) -> 0.088235294
F25: =SUM(F21:F24) -> 1
E34: Underdeveloped Country Fire | F34: Criticality Weights | G34: =E35 -> Resolution Time | H34: =E36 -> Burn Burden | I34: =E37 -> Total Cost | J34: =E38 -> CO2 Emissions | L34: Interface | M34: Importance
E35: Resolution Time | F35: =AVERAGE(O35:R35) -> 0.45549591 | G35: 1 | H35: 1 | I35: 9 | J35: 9 | L35: =E35 -> Resolution Time | M35: =F35 -> 0.45549591 | O35: =G35/SUM(G$35:G$38) -> 0.45 | P35: =H35/SUM(H$35:H$38) -> 0.44366197 | Q35: =I35/SUM(I$35:I$38) -> 0.51923077 | R35: =J35/SUM(J$35:J$38) -> 0.40909091
E36: Burn Burden | F36: =AVERAGE(O36:R36) -> 0.42664976 | G36: {=1/INDEX($H$35:$J$35, 1, ROW(A1))} -> 1 | H36: 1 | I36: 7 | J36: 9 | L36: =E36 -> Burn Burden | M36: =F36 -> 0.42664976 | O36: =G36/SUM(G$35:G$38) -> 0.45 | P36: =H36/SUM(H$35:H$38) -> 0.44366197 | Q36: =I36/SUM(I$35:I$38) -> 0.40384615 | R36: =J36/SUM(J$35:J$38) -> 0.40909091
E37: Total Cost | F37: =AVERAGE(O37:R37) -> 0.076859056 | G37: {=1/INDEX($H$35:$J$35, 1, ROW(A2))} -> 0.11111111 | H37: {=1/INDEX($I$36:$J$36, 1, ROW(A1))} -> 0.14285714 | I37: 1 | J37: 3 | L37: =E37 -> Total Cost | M37: =F37 -> 0.076859056 | O37: =G37/SUM(G$35:G$38) -> 0.05 | P37: =H37/SUM(H$35:H$38) -> 0.063380282 | Q37: =I37/SUM(I$35:I$38) -> 0.057692308 | R37: =J37/SUM(J$35:J$38) -> 0.13636364
E38: CO2 Emissions | F38: =AVERAGE(O38:R38) -> 0.040995272 | G38: {=1/INDEX($H$35:$J$35, 1, ROW(A3))} -> 0.11111111 | H38: {=1/INDEX($I$36:$J$36, 1, ROW(A2))} -> 0.11111111 | I38: {=1/INDEX($J$37:$J$37, 1, ROW(A1))} -> 0.33333333 | J38: 1 | L38: =E38 -> CO2 Emissions | M38: =F38 -> 0.040995272 | O38: =G38/SUM(G$35:G$38) -> 0.05 | P38: =H38/SUM(H$35:H$38) -> 0.049295775 | Q38: =I38/SUM(I$35:I$38) -> 0.019230769 | R38: =J38/SUM(J$35:J$38) -> 0.045454545
F39: =SUM(F35:F38) -> 1

Sheet Deploy Smokejumpers
A1: Compared Function | B1: Score (Saaty Scale) | C1: Justification
A2: Activate MAFFS | B2: =3 -> 3 | C2: Deploy Smokejumpers often access terrain unreachable by MAFFS aircraft, representing a more direct and high-priority engagement. | E2: =3 -> 3 | F2: =5 -> 5 | G2: =5 -> 5 | H2: =4 -> 4 | I2: =4 -> 4
A3: Refuel Airborne Assets | B3: =5 -> 5 | C3: Direct deployment of personnel into wildfires is a more critical and immediate function than logistical refueling.
A4: Provide MRO for Assets | B4: =5 -> 5 | C4: Maintenance supports long-term capability, while deploying smokejumpers addresses acute, time-sensitive needs.
A5: Refill Water and Fire Retardants | B5: =4 -> 4 | C5: While refilling is essential for suppression, smokejumpers are a first-response force for rapid containment.
A6: Provide Logistic Support to Crews | B6: =4 -> 4 | C6: Logistics sustain operations, but smokejumpers engage fires at the frontline, offering direct impact.

Sheet Refuel Airborne Assets
A1: Compared Function | B1: Score (Saaty Scale) | C1: Justification
A2: Provide MRO for Assets | B2: =3 -> 3 | C2: Refueling airborne assets is moderately more critical as it directly enables continued flight operations. | E2: =3 -> 3 | F2: =2 -> 2 | G2: =1/2 -> 0.5
A3: Refill Water and Fire Retardants | B3: =2 -> 2 | C3: Refueling is slightly more immediate than refilling fire retardants due to aircraft operation dependency.
A4: Provide Logistic Support to Crews | B4: =1/2 -> 0.5 | C4: Crew support has slightly broader systemic importance compared to refueling alone.

Sheet Provide MRO for Assets
A1: Compared Function | B1: Score (Saaty Scale) | C1: Justification
A2: Refill Water and Fire Retardants | B2: =1/2 -> 0.5 | C2: MRO ensures readiness and performance of equipment long-term, whereas water/retardant refill is a frequent operational necessity. MRO has slightly more impact on sustained asset utility. | E2: =1/2 -> 0.5 | F2: =1/3 -> 0.33333333
A3: Provide Logistic Support to Crews | B3: =1/3 -> 0.33333333 | C3: While logistics supports personnel well-being, MRO directly sustains asset operability, which has a more direct effect on mission execution.

Sheet Refill Water and Fire Retardant
A1: Compared Function | B1: Score (Saaty Scale) | C1: Justification
A2: Provide Logistic Support to Crews | B2: =1/2 -> 0.5 | C2: Refilling water and fire retardants is more operationally urgent for direct fire suppression, but logistic support enables sustained operations, so it is slightly less critical. | E2: =0.5 -> 0.5

Sheet Activate MAFFS
A1: Compared Function | B1: Score (Saaty Scale) | C1: Justification
A2: Refuel Airborne Assets | B2: =1 -> 1 | C2: Both functions support aerial assets, but MAFFS activation is equally critical as refueling for suppression effectiveness. | E2: =1 -> 1 | F2: =3 -> 3 | G2: =2 -> 2 | H2: =2 -> 2
A3: Provide MRO for Assets | B3: =3 -> 3 | C3: MAFFS provides direct suppression while MRO is indirect; MAFFS is moderately more important.
A4: Refill Water and Fire Retardants | B4: =2 -> 2 | C4: MAFFS enables active fire suppression whereas refill is a support function; thus MAFFS is slightly more important.
A5: Provide Logistic Support to Crews | B5: =2 -> 2 | C5: MAFFS directly contributes to containment, while logistics are background enablers; MAFFS slightly more important.

Sheet Issue Commands to Assets
A1: Compared Function | B1: Score (Saaty Scale) | C1: Justification
A2: Communicate to Resources | B2: 2 | C2: Issuing commands is a more directive control action, but relies on effective communication to be actionable. | E2: 2 | F2: 3 | G2: 4 | H2: 2 | I2: 2 | J2: 1 | K2: 0.33333333 | L2: 0.25 | M2: 0.33333333 | N2: 0.33333333
A3: Maintain Communication Among Assets | B3: 3 | C3: Command issuance benefits from consistent asset-to-asset communication to ensure decentralized execution.
A4: Maintain Communication Between Assets and C3 | B4: 4 | C4: Commanding assets depends more critically on centralized C3 communication for situational clarity and authority.
A5: Deploy First Response Ground Assets | B5: 2 | C5: Deployment precedes and enables command issuance but is operationally distinct from command logic.
A6: Deploy Smokejumpers | B6: 2 | C6: Commands may direct smokejumper activity, but the specialized nature of deployment is separate from command structure.
A7: Activate MAFFS | B7: 1 | C7: Commanding MAFFS is a very specific instance of issuing operational instructions—nearly equivalent in function.
A8: Refuel Airborne Assets | B8: 0.33333333 | C8: While necessary for mission readiness, refueling is a support function with indirect connection to command issuance.
A9: Provide MRO for Assets | B9: 0.25 | C9: Maintenance supports asset health but has minimal interaction with active command structures.
A10: Refill Water and Fire Retardants | B10: 0.33333333 | C10: A logistics task that supports execution but isn’t a direct counterpart to issuing commands.
A11: Provide Logistic Support to Crews | B11: 0.33333333 | C11: Indirectly influences operational capability, but has limited overlap with the act of commanding.

Sheet Communicate to Resources
A1: Compared Function | B1: Score (Saaty Scale) | C1: Justification
A2: Maintain Communication Among Assets | B2: =1/2 -> 0.5 | C2: Communicating to specific units is slightly more critical than general inter-asset updates. | E2: =1/2 -> 0.5 | F2: =1/3 -> 0.33333333 | G2: =2 -> 2 | H2: =3 -> 3 | I2: =2 -> 2 | J2: =5 -> 5 | K2: =7 -> 7 | L2: =4 -> 4 | M2: =3 -> 3
A3: Maintain Communication Between Assets and C3 | B3: =1/3 -> 0.33333333 | C3: C3 communication is important, but issuing direct instructions to field resources is slightly more vital.
A4: Deploy First Response Ground Assets | B4: =2 -> 2 | C4: Direct communication to units enables deployment, but the command itself is more important.
A5: Deploy Smokejumpers | B5: =3 -> 3 | C5: Direct communication is moderately more important since it enables and guides deployment.
A6: Activate MAFFS | B6: =2 -> 2 | C6: Activating air resources requires communication, but coordination takes precedence.
A7: Refuel Airborne Assets | B7: =5 -> 5 | C7: Communicating actively to resources is significantly more critical to real-time response.
A8: Provide MRO for Assets | B8: =7 -> 7 | C8: Communication is very strongly more important than maintenance in active response phases.
A9: Refill Water and Fire Retardants | B9: =4 -> 4 | C9: Communication is strongly more important for real-time tactical operations.
A10: Provide Logistic Support to Crews | B10: =3 -> 3 | C10: Communication is moderately more important as it enables logistical coordination.

Sheet Maintain Communication Assets
A1: Compared Function | B1: Score (Saaty Scale) | C1: Justification
A2: Maintain Communication Between Assets and C3 | B2: =1/2 -> 0.5 | C2: Maintaining communication among assets is slightly less important than between assets and C3, as C3 coordination directs broader operations. | E2: =1/2 -> 0.5 | F2: =2 -> 2 | G2: =2 -> 2 | H2: =2 -> 2 | I2: =3 -> 3 | J2: =3 -> 3 | K2: =2 -> 2 | L2: =2 -> 2
A3: Deploy First Response Ground Assets | B3: =2 -> 2 | C3: Communication among assets is more important as it ensures cohesive action post-deployment.
A4: Deploy Smokejumpers | B4: =2 -> 2 | C4: Ensuring communication among already deployed units is slightly more important for real-time tactical adaptation.
A5: Activate MAFFS | B5: =2 -> 2 | C5: Maintaining communication supports coordination of airborne and ground suppression once MAFFS is activated.
A6: Refuel Airborne Assets | B6: =3 -> 3 | C6: Coordination among assets directly affects real-time operations, which is moderately more critical than refueling support.
A7: Provide MRO for Assets | B7: =3 -> 3 | C7: While MRO ensures long-term readiness, communication ensures short-term operational execution.
A8: Refill Water and Fire Retardants | B8: =2 -> 2 | C8: Communication keeps operations synchronized, which is slightly more important than static resupply.
A9: Provide Logistic Support to Crews | B9: =2 -> 2 | C9: Maintaining coordination in the field during operations is more directly tied to immediate mission success than general logistics.

Sheet Maintain Comm Assets and C3
A1: Compared Function | B1: Score (Saaty Scale) | C1: Justification
A2: Deploy First Response Ground Assets | B2: =1/3 -> 0.33333333 | C2: Ground deployment occurs after command & communication structure is established. | E2: =1/3 -> 0.33333333 | F2: =1/3 -> 0.33333333 | G2: =1/2 -> 0.5 | H2: =1 -> 1 | I2: =2 -> 2 | J2: =2 -> 2 | K2: =3 -> 3
A3: Deploy Smokejumpers | B3: =1/3 -> 0.33333333 | C3: Communication channels need to be in place before deploying remote/airborne crews.
A4: Activate MAFFS | B4: =1/2 -> 0.5 | C4: Activating MAFFS relies on pre-existing C3 to coordinate with air traffic and firefighting ops.
A5: Refuel Airborne Assets | B5: =1 -> 1 | C5: Refueling logistics are separate but somewhat dependent on coordinated communication.
A6: Provide MRO for Assets | B6: =2 -> 2 | C6: Maintenance operations depend on communication but to a lesser degree than live ops.
A7: Refill Water and Fire Retardants | B7: =2 -> 2 | C7: Supply refills rely on communicated needs but not central to C3 system.
A8: Provide Logistic Support to Crews | B8: =3 -> 3 | C8: C3 precedes and enables logistics deployment to support crews.

Sheet Deploy First Response Assets
A1: Compared Function | B1: Score (Saaty Scale) | C1: Justification
A2: Deploy Smokejumpers | B2: =2 -> 2 | C2: Ground response is slightly more critical as it often establishes the initial containment perimeter. | E2: =2 -> 2 | F2: =1/2 -> 0.5 | G2: =3 -> 3 | H2: =4 -> 4 | I2: =3 -> 3 | J2: =2 -> 2
A3: Activate MAFFS | B3: =1/2 -> 0.5 | C3: MAFFS offers large-scale suppression, which is slightly more impactful than ground response alone.
A4: Refuel Airborne Assets | B4: =3 -> 3 | C4: Ground response directly fights fire, whereas refueling is a supporting task.
A5: Provide MRO for Assets | B5: =4 -> 4 | C5: Ground response has higher immediate impact on fire containment than maintenance.
A6: Refill Water and Fire Retardants | B6: =3 -> 3 | C6: Initial deployment is more urgent than ongoing resupply tasks.
A7: Provide Logistic Support to Crews | B7: =2 -> 2 | C7: Logistics is necessary for sustainment, but immediate deployment holds higher criticality.

Sheet Coordinate Air & Ground Res
A1: Compared Function | B1: Score (Saaty Scale) | C1: Justification
A2: Dynamically Allocate Resources | B2: =1/3 -> 0.33333333 | C2: Resource coordination informs but is distinct from dynamic allocation, which is more adaptive. | E2: =1/3 -> 0.33333333 | F2: =1 -> 1 | G2: =2 -> 2 | H2: =2 -> 2 | I2: =2 -> 2 | J2: =1/2 -> 0.5 | K2: =1/2 -> 0.5 | L2: =1/2 -> 0.5 | M2: =3 -> 3 | N2: =3 -> 3 | O2: =3 -> 3 | P2: =2 -> 2
A3: Issue Commands to Assets | B3: =1 -> 1 | C3: Coordination includes command issuance, placing both on equal strategic footing.
A4: Communicate to Resources | B4: =2 -> 2 | C4: Coordination implies higher-level planning and integration than simple communication.
A5: Maintain Communication Among Assets | B5: =2 -> 2 | C5: While coordination requires asset communication, its scope is broader.
A6: Maintain Communication Between Assets and C3 | B6: =2 -> 2 | C6: Coordination extends beyond C3 communication to include task synchronization.
A7: Deploy First Response Ground Assets | B7: =1/2 -> 0.5 | C7: Coordination sets the stage for deployment but is one step removed from direct action.
A8: Deploy Smokejumpers | B8: =1/2 -> 0.5 | C8: Coordination supports this deployment but does not inherently involve execution.
A9: Activate MAFFS | B9: =1/2 -> 0.5 | C9: Resource coordination enables activation but is strategically broader.
A10: Refuel Airborne Assets | B10: =3 -> 3 | C10: Coordination has higher-level strategic importance than refueling logistics.
A11: Provide MRO for Assets | B11: =3 -> 3 | C11: Coordination takes precedence over backend support like maintenance.
A12: Refill Water and Fire Retardants | B12: =3 -> 3 | C12: Coordination is strategically more critical than this support function.
A13: Provide Logistic Support to Crews | B13: =2 -> 2 | C13: Coordination relies on logistics but involves broader tactical decisions.

Sheet Dynamically Allocate Resources
A1: Compared Function | B1: Score (Saaty Scale) | C1: Justification
A2: Issue Commands to Assets | B2: =1/3 -> 0.33333333 | C2: Dynamic allocation precedes and guides specific command issuance | E2: =1/3 -> 0.33333333 | F2: =1/2 -> 0.5 | G2: 1 | H2: 2 | I2: =1/2 -> 0.5 | J2: =1/3 -> 0.33333333 | K2: =1/5 -> 0.2 | L2: =1/3 -> 0.33333333 | M2: =1/2 -> 0.5 | N2: =1/2 -> 0.5 | O2: 1
A3: Communicate to Resources | B3: =1/2 -> 0.5 | C3: Allocation requires awareness of available resources and communication to execute
A4: Maintain Communication Among Assets | B4: 1 | C4: Equal importance in enabling coordinated execution
A5: Maintain Communication Between Assets and C3 | B5: 2 | C5: Communication with command centers is essential to inform dynamic reallocation
A6: Deploy First Response Ground Assets | B6: =1/2 -> 0.5 | C6: Allocation directs but is dependent on deployment mechanisms
A7: Deploy Smokejumpers | B7: =1/3 -> 0.33333333 | C7: Specialized deployment activity guided by broader resource strategy
A8: Activate MAFFS | B8: =1/5 -> 0.2 | C8: Specific aerial suppression task less strategic than resource planning
A9: Refuel Airborne Assets | B9: =1/3 -> 0.33333333 | C9: A logistical function guided by resource planning
A10: Provide MRO for Assets | B10: =1/2 -> 0.5 | C10: Maintenance sustains assets needed for allocation, but less dynamic
A11: Refill Water and Fire Retardants | B11: =1/2 -> 0.5 | C11: Supports execution, but doesn’t determine dynamic shifts
A12: Provide Logistic Support to Crews | B12: 1 | C12: Allocation strategy and crew support equally essential to operational success

Sheet Strategically Monitor Fires
A1: Function Compared To | B1: Score | C1: Justification
A2: Gather Real Time Data from Assets | B2: 2 | C2: Strategic monitoring provides context for incoming real-time data. | E2: 2 | F2: 2 | G2: =1/2 -> 0.5 | H2: =1/3 -> 0.33333333 | I2: =1/3 -> 0.33333333 | J2: 1 | K2: 1 | L2: 1 | M2: =1/2 -> 0.5 | N2: =1/3 -> 0.33333333 | O2: =1/5 -> 0.2 | P2: =1/5 -> 0.2 | Q2: =1/3 -> 0.33333333 | R2: =1/3 -> 0.33333333 | S2: =1/3 -> 0.33333333
A3: Build Real Time Situational Awareness | B3: 2 | C3: Strategic context enables interpretation of evolving fire awareness.
A4: Coordinate Air & Ground Resources | B4: =1/2 -> 0.5 | C4: Direct coordination is often more impactful than passive oversight.
A5: Dynamically Allocate Resources | B5: =1/3 -> 0.33333333 | C5: Resource allocation directly affects suppression effectiveness.
A6: Issue Commands to Assets | B6: =1/3 -> 0.33333333 | C6: Asset tasking typically has higher operational leverage.
A7: Communicate to Resources | B7: 1 | C7: Strategic monitoring and direct comms are often equally weighted.
A8: Maintain Communication Among Assets | B8: 1 | C8: Both enable synchronized, safe firefighting operations.
A9: Maintain Communication Between Assets and C3 | B9: 1 | C9: Monitoring and C3 coordination are foundational and codependent.
A10: Deploy First Response Ground Assets | B10: =1/2 -> 0.5 | C10: Ground asset deployment often has more immediate tactical effect.
A11: Deploy Smokejumpers | B11: =1/3 -> 0.33333333 | C11: Smokejumpers provide fast suppression response, often prioritized.
A12: Activate MAFFS | B12: =1/5 -> 0.2 | C12: Aerial suppression from MAFFS can be mission-critical.
A13: Refuel Airborne Assets | B13: =1/5 -> 0.2 | C13: Airtanker readiness (fuel) directly affects sortie rate.
A14: Provide MRO for Assets | B14: =1/3 -> 0.33333333 | C14: Maintenance is vital for safety but less urgent tactically.
A15: Refill Water and Fire Retardants | B15: =1/3 -> 0.33333333 | C15: Water/retardant resupply sustains ops but isn’t proactive like monitoring.
A16: Provide Logistic Support to Crews | B16: =1/3 -> 0.33333333 | C16: Crew logistics are important, but not time-dominant during suppression.

Sheet Gather Real Time Data
A1: Compared To | B1: AHP Value | C1: Justification
A2: Build Real Time Situational Awareness | B2: =1/3 -> 0.33333333 | C2: Situational awareness is more integrative and decision-focused than raw data gathering. | E2: =1/3 -> 0.33333333 | F2: =1/3 -> 0.33333333 | G2: =1/2 -> 0.5 | H2: =1/2 -> 0.5 | I2: =1/2 -> 0.5 | J2: =1/2 -> 0.5 | K2: =1/2 -> 0.5 | L2: =2 -> 2 | M2: =3 -> 3 | N2: =3 -> 3 | O2: =3 -> 3 | P2: =2 -> 2 | Q2: =2 -> 2 | R2: =2 -> 2
A3: Coordinate Air & Ground Resources | B3: =1/3 -> 0.33333333 | C3: Air-ground coordination requires a broader view than data provision alone.
A4: Dynamically Allocate Resources | B4: =1/2 -> 0.5 | C4: Resource allocation relies on interpreted data, not raw sensor feeds.
A5: Issue Commands to Assets | B5: =1/2 -> 0.5 | C5: Commanding assets is downstream of analysis — raw data alone isn’t actionable.
A6: Communicate to Resources | B6: =1/2 -> 0.5 | C6: Data helps, but direct communication addresses real-time needs.
A7: Maintain Communication Among Assets | B7: =1/2 -> 0.5 | C7: Maintaining comms ensures team cohesion during ops, beyond just sensor updates.
A8: Maintain Communication Between Assets and C3 | B8: =1/2 -> 0.5 | C8: Communication with C3 reflects strategic alignment, not just tactical insight.
A9: Deploy First Response Ground Assets | B9: =2 -> 2 | C9: First response relies partially on sensing, but data alone doesn’t deploy crews.
A10: Deploy Smokejumpers | B10: =3 -> 3 | C10: Specialized rapid insertion (smokejumpers) is more labor-intensive than data gathering.
A11: Activate MAFFS | B11: =3 -> 3 | C11: MAFFS activation is a significant operational act, beyond just detecting.
A12: Refuel Airborne Assets | B12: =3 -> 3 | C12: Refueling aircraft is a logistics-heavy task with high operational cost.
A13: Provide MRO for Assets | B13: =2 -> 2 | C13: MRO involves repair/maintenance planning — more complex than sensing.
A14: Refill Water and Fire Retardants | B14: =2 -> 2 | C14: Supplying retardant is action-oriented, resource-intensive.
A15: Provide Logistic Support to Crews | B15: =2 -> 2 | C15: Crew logistics is vital for long-term support — sensing plays only a small part.

Sheet Build Real Time SA
A1: Compared Function | B1: Score (Saaty Scale) | C1: Justification
A2: Coordinate Air & Ground Resources | B2: =3 -> 3 | C2: Situational awareness precedes coordination of air and ground responses. | E2: =3 -> 3 | F2: =2 -> 2 | G2: =2 -> 2 | H2: =2 -> 2 | I2: =2 -> 2 | J2: =2 -> 2 | K2: =4 -> 4 | L2: =4 -> 4 | M2: =6 -> 6 | N2: =6 -> 6 | O2: =6 -> 6 | P2: =5 -> 5 | Q2: =5 -> 5
A3: Dynamically Allocate Resources | B3: =2 -> 2 | C3: Dynamic allocation depends on situational awareness input.
A4: Issue Commands to Assets | B4: =2 -> 2 | C4: Issuing commands requires synthesized situational context.
A5: Communicate to Resources | B5: =2 -> 2 | C5: Communicating to resources benefits from updated situational awareness.
A6: Maintain Communication Among Assets | B6: =2 -> 2 | C6: Asset coordination requires knowledge of evolving conditions.
A7: Maintain Communication Between Assets and C3 | B7: =2 -> 2 | C7: C3 communication frameworks are dependent on real-time awareness.
A8: Deploy First Response Ground Assets | B8: =4 -> 4 | C8: Deployment of ground assets is guided by situational insight.
A9: Deploy Smokejumpers | B9: =4 -> 4 | C9: Smokejumper operations rely on current understanding of fire progression.
A10: Activate MAFFS | B10: =6 -> 6 | C10: Activating MAFFS is more reactionary and tactical, needing situational triggers.
A11: Refuel Airborne Assets | B11: =6 -> 6 | C11: Refueling supports air asset longevity, less dependent on real-time data.
A12: Provide MRO for Assets | B12: =6 -> 6 | C12: Maintenance is backend support, less influenced by situational change.
A13: Refill Water and Fire Retardants | B13: =5 -> 5 | C13: Refill ops are logistical support, less prioritized over awareness.
A14: Provide Logistic Support to Crews | B14: =5 -> 5 | C14: Logistics support is planning-based and less dynamic than situational updates.

Sheet Predict Fire Paths Behavior
A1: Compared To | B1: AHP Score | C1: Justification
A2: Strategically Monitor Fires | B2: =1/2 -> 0.5 | C2: Strategic monitoring supports predictive modeling but is broader in scope. | E2: =1/2 -> 0.5 | F2: 3 | G2: 2 | H2: 2 | I2: 2 | J2: 3 | K2: 4 | L2: 3 | M2: 3 | N2: =1/2 -> 0.5 | O2: 1 | P2: =1/2 -> 0.5 | Q2: 2 | R2: 2 | S2: 2 | T2: 2
A3: Gather Real Time Data from Assets | B3: 3 | C3: Prediction depends on data, but adds processing and modeling.
A4: Build Real Time Situational Awareness | B4: 2 | C4: Prediction is a subset of SA, but more proactive.
A5: Coordinate Air & Ground Resources | B5: 2 | C5: Coordination supports execution, while prediction supports planning.
A6: Dynamically Allocate Resources | B6: 2 | C6: Prediction informs allocation, but allocation is operational.
A7: Issue Commands to Assets | B7: 3 | C7: Prediction is higher-level planning, commands are downstream execution.
A8: Communicate to Resources | B8: 4 | C8: Prediction has higher analytical value than one-way communication.
A9: Maintain Communication Among Assets | B9: 3 | C9: Prediction supports coordination, whereas comms just enable it.
A10: Maintain Communication Between Assets and C3 | B10: 3 | C10: Prediction enables C3 decision making, comms enable reach.
A11: Deploy First Response Ground Assets | B11: =1/2 -> 0.5 | C11: Initial ground response is critical, even without predictive insight.
A12: Deploy Smokejumpers | B12: 1 | C12: Both are highly specialized and contextually critical.
A13: Activate MAFFS | B13: =1/2 -> 0.5 | C13: MAFFS activation is valuable for suppression; prediction helps pre-position.
A14: Refuel Airborne Assets | B14: 2 | C14: Prediction supports resource optimization, refueling supports mission continuity.
A15: Provide MRO for Assets | B15: 2 | C15: Prediction supports forward planning, MRO ensures long-term operability.
A16: Refill Water and Fire Retardants | B16: 2 | C16: Refill is a support task, prediction optimizes its use.
A17: Provide Logistic Support to Crews | B17: 2 | C17: Prediction affects logistics timing and efficiency.

Sheet Visually Confirm Fires
A1: Compared Function | B1: Score (Saaty Scale) | C1: Justification
A2: Predict Fire Paths/Behavior | B2: 1 | C2: Both are proactive fire analysis tools — equal importance in early-phase operations. | E2: 1 | F2: 1 | G2: 1 | H2: 1 | I2: 1 | J2: 1 | K2: 1 | L2: 1 | M2: 1 | N2: 1 | O2: =1*1/2 -> 0.5 | P2: =1*1/2 -> 0.5 | Q2: =1*1/2 -> 0.5 | R2: =1*1/2 -> 0.5 | S2: =1*1/2 -> 0.5 | T2: =1*1/2 -> 0.5 | U2: =1*1/2 -> 0.5
A3: Strategically Monitor Fires | B3: 1 | C3: Strategic oversight validates visual confirmation and vice versa — co-dependent functions.
A4: Gather Real Time Data from Assets | B4: 1 | C4: Confirmation feeds into data collection efforts — same operational loop.
A5: Build Real Time Situational Awareness | B5: 1 | C5: Situational awareness includes on-the-ground validation — equal system inputs.
A6: Coordinate Air & Ground Resources | B6: 1 | C6: Visual confirmation enables coordination validation — both guide response.
A7: Dynamically Allocate Resources | B7: 1 | C7: Allocation decisions require known/confirmed targets — equally vital.
A8: Issue Commands to Assets | B8: 1 | C8: Commands are more meaningful with accurate field intel — equal importance.
A9: Communicate to Resources | B9: 1 | C9: Confirmation gives feedback to operational decisions — same impact tier.
A10: Maintain Communication Among Assets | B10: 1 | C10: Communications must reflect ground truth — which confirmation provides.
A11: Maintain Communication Between Assets and C3 | B11: 1 | C11: Feedback to C3 from visual confirmation improves operational accuracy — equally essential.
A12: Deploy First Response Ground Assets | B12: =1*1/2 -> 0.5 | C12: Initial deployment happens after confirmation — confirmation slightly less urgent.
A13: Deploy Smokejumpers | B13: =1*1/2 -> 0.5 | C13: Smokejumpers are sent in after confirmed fire presence — operational timing higher.
A14: Activate MAFFS | B14: =1*1/2 -> 0.5 | C14: MAFFS is activated based on fire severity — confirmation is prior input.
A15: Refuel Airborne Assets | B15: =1*1/2 -> 0.5 | C15: Refueling supports execution post-confirmation — slightly more downstream.
A16: Provide MRO for Assets | B16: =1*1/2 -> 0.5 | C16: MRO sustains system capacity — confirmation precedes usage.
A17: Refill Water and Fire Retardants | B17: =1*1/2 -> 0.5 | C17: Refill occurs in suppression phase — confirmation comes earlier.
A18: Provide Logistic Support to Crews | B18: =1*1/2 -> 0.5 | C18: Logistics sustain confirmed mission profiles — slightly more indirect than field validation.

Sheet Detect Fires
A1: Compared Function | B1: Score (Saaty Scale) | C1: Justification
A2: Visually Confirm Fires | B2: 2 | C2: Detection initiates the response; confirmation validates — detection is more fundamental. | E2: 2 | F2: 2 | G2: 2 | H2: 1 | I2: 1 | J2: 1 | K2: 1 | L2: 1 | M2: 1 | N2: 1 | O2: 1 | P2: 2 | Q2: 2 | R2: 2 | S2: 2 | T2: 2 | U2: 2 | V2: 2
A3: Predict Fire Paths/Behavior | B3: 2 | C3: Prediction models behavior post-detection — detection is prerequisite.
A4: Strategically Monitor Fires | B4: 2 | C4: Monitoring relies on a fire being detected — detection comes first.
A5: Gather Real Time Data from Assets | B5: 1 | C5: Detection and data are co-dependent — detection feeds data streams.
A6: Build Real Time Situational Awareness | B6: 1 | C6: Situational awareness is built upon detection — equal partnership.
A7: Coordinate Air & Ground Resources | B7: 1 | C7: Coordination starts once a fire is known — detection triggers it.
A8: Dynamically Allocate Resources | B8: 1 | C8: Allocation requires known fires — detection precedes decision making.
A9: Issue Commands to Assets | B9: 1 | C9: Command flow begins in response to detection — equal importance operationally.
A10: Communicate to Resources | B10: 1 | C10: Resources are communicated to based on fire detection — functionally equal.
A11: Maintain Communication Among Assets | B11: 1 | C11: Maintains field awareness once fire is detected — dependent, but equal.
A12: Maintain Communication Between Assets and C3 | B12: 1 | C12: C3 systems depend on fire detection input — same tier of importance.
A13: Deploy First Response Ground Assets | B13: 2 | C13: First response launches upon detection — detection enables deployment.
A14: Deploy Smokejumpers | B14: 2 | C14: Smokejumpers are dispatched based on detection — detection is enabling.
... A19: Provide Logistic Support to Crews | B19: 2 | C19: Logistics support all missions, but detection is the trigger for the mission to exist.

Sheet Tactically Monitor Fires
A1: Compared Function | B1: Score (Saaty Scale) | C1: Justification
A2: Predict New Fires | B2: 2 | C2: Tactical monitoring acts on current fires; prediction is strategic — tactical is more urgent. | E2: 2 | F2: 2 | G2: 2 | H2: 2 | I2: 1 | J2: 1 | K2: 1 | L2: 1 | M2: 1 | N2: 1 | O2: 1 | P2: 1 | Q2: 1 | R2: 1 | S2: 1 | T2: 1 | U2: 1 | V2: 1 | W2: 1 | X2: 1
A3: Detect Fires | B3: 2 | C3: Monitoring is used in real-time to direct suppression; detection starts the chain — monitoring is more persistent.
A4: Visually Confirm Fires | B4: 2 | C4: Confirmation validates a fire, but tactical monitoring helps guide operations continuously.
A5: Predict Fire Paths/Behavior | B5: 2 | C5: Fire path prediction is a planning tool — monitoring supports dynamic adjustments.
A6: Strategically Monitor Fires | B6: 1 | C6: Strategic view and tactical monitoring operate at different altitudes — equal value.
A7: Gather Real Time Data from Assets | B7: 1 | C7: Both involve real-time information that feeds suppression action — equal.
A8: Build Real Time Situational Awareness | B8: 1 | C8: Awareness and monitoring are complementary — both sustain fireground understanding.
A9: Coordinate Air & Ground Resources | B9: 1 | C9: Coordination is facilitated by tactical input — equally necessary.
A10: Dynamically Allocate Resources | B10: 1 | C10: Allocation decisions depend on field insight — co-functioning roles.
A11: Issue Commands to Assets | B11: 1 | C11: Commands are implemented using tactical fire monitoring — operational pairing.
A12: Communicate to Resources | B12: 1 | C12: Communication helps execute what tactical monitoring reveals — equally critical.
A13: Maintain Communication Among Assets | B13: 1 | C13: Communication between field units enables full use of tactical monitoring — same tier.
A14: Maintain Communication Between Assets and C3 | B14: 1 | C14: Field-to-C3 links allow use of tactical data — co-dependent functions.
... A21: Provide Logistic Support to Crews | B21: 1 | C21: Logistics supports all tactical field functions, including monitoring — equal support level.

Sheet Predict New Fires
A1: Compared Function | B1: Score (Saaty Scale) | C1: Justification
A2: Detect Fires | B2: =1*1/2 -> 0.5 | C2: Prediction is strategic and proactive; detection is reactive and event-driven — detection slightly more urgent. | E2: =1*1/2 -> 0.5 | F2: 1 | G2: 1 | H2: 1 | I2: 1 | J2: 1 | K2: 1 | L2: 1 | M2: 1 | N2: 1 | O2: 1 | P2: 1 | Q2: =1*1/2 -> 0.5 | R2: =1*1/2 -> 0.5 | S2: =1*1/2 -> 0.5 | T2: =1*1/2 -> 0.5 | U2: =1*1/2 -> 0.5 | V2: =1*1/2 -> 0.5 | W2: =1*1/2 -> 0.5
A3: Visually Confirm Fires | B3: 1 | C3: Both are validation functions used early in the fire lifecycle — equally useful.
A4: Predict Fire Paths/Behavior | B4: 1 | C4: Path prediction and new fire forecasting both help with forward planning — equal tier.
A5: Strategically Monitor Fires | B5: 1 | C5: Strategic monitoring and prediction both guide macro-level decision making.
A6: Gather Real Time Data from Assets | B6: 1 | C6: Both involve analyzing sensor data for proactive planning — same level of importance.
A7: Build Real Time Situational Awareness | B7: 1 | C7: Situational awareness includes prediction as one layer — equal system value.
A8: Coordinate Air & Ground Resources | B8: 1 | C8: Planning fire response benefits equally from prediction and coordination.
A9: Dynamically Allocate Resources | B9: 1 | C9: Allocation is driven by awareness of potential fire zones — equally important.
A10: Issue Commands to Assets | B10: 1 | C10: Prediction helps initiate commands for prevention and readiness — equivalent weight.
A11: Communicate to Resources | B11: 1 | C11: Communication keeps forecast alerts flowing — same operational priority.
A12: Maintain Communication Among Assets | B12: 1 | C12: Asset sync ensures forecasted risks are met with coordinated response — equal tier.
A13: Maintain Communication Between Assets and C3 | B13: 1 | C13: C3 integration ensures that fire prediction becomes operational — same value.
A14: Deploy First Response Ground Assets | B14: =1*1/2 -> 0.5 | C14: First response reacts to fires; prediction prevents or mitigates escalation — slightly less urgent.
A15: Deploy Smokejumpers | B15: =1*1/2 -> 0.5 | C15: Smokejumpers act fast on known fires — prediction prevents surprise — tactical trumps strategic here.
A16: Activate MAFFS | B16: =1*1/2 -> 0.5 | C16: MAFFS acts during fires; prediction can’t replace suppression — less critical short-term.
A17: Refuel Airborne Assets | B17: =1*1/2 -> 0.5 | C17: Aircraft refueling sustains ops; prediction reduces surprise — ops support takes slight precedence.
A18: Provide MRO for Assets | B18: =1*1/2 -> 0.5 | C18: MRO sustains readiness; prediction is forecasting — both enable longer-term impact.
A19: Refill Water and Fire Retardants | B19: =1*1/2 -> 0.5 | C19: Refill is needed immediately during a fire — prediction is helpful beforehand.
A20: Provide Logistic Support to Crews | B20: =1*1/2 -> 0.5 | C20: Logistics supports all ops — prediction shapes planning — slightly less urgent operationally.

Sheet Spill Water from Ground Assets
A1: Compared Function | B1: Score (Saaty Scale) | C1: Justification
A2: Tactically Monitor Fires | B2: 1 | C2: Monitoring guides where to spill water — equally essential in execution.
A3: Predict New Fires | B3: 2 | C3: Prediction helps pre-position, but water application is tactical execution. | E3: 1 | F3: 2 | G3: 2 | H3: 2 | I3: 2 | J3: 1 | K3: 1 | L3: 1 | M3: 1 | N3: 1 | O3: 1 | P3: 1 | Q3: 1 | R3: 1 | S3: 1 | T3: 1 | U3: 1 | V3: 1 | W3: 1 | X3: 1 | Y3: 1
A4: Detect Fires | B4: 2 | C4: Detection enables initiation, but spill is part of real suppression.
A5: Visually Confirm Fires | B5: 2 | C5: Confirmation validates target, spill acts on it — greater operational role.
A6: Predict Fire Paths/Behavior | B6: 2 | C6: Path modeling helps aim assets; spill acts to stop fire physically.
A7: Strategically Monitor Fires | B7: 1 | C7: Strategic oversight complements field action — equally vital in coordination.
A8: Gather Real Time Data from Assets | B8: 1 | C8: Data guides operations, but spill is execution — same level of necessity.
A9: Build Real Time Situational Awareness | B9: 1 | C9: Awareness and field action both directly influence mission outcomes.
A10: Coordinate Air & Ground Resources | B10: 1 | C10: Coordination ensures proper spill use — neither functions without the other.
A11: Dynamically Allocate Resources | B11: 1 | C11: Allocation dictates where to act; spill is the action — both are operational.
A12: Issue Commands to Assets | B12: 1 | C12: Orders and action are linked; one directs, one executes.
A13: Communicate to Resources | B13: 1 | C13: Communication enables effective suppression — both are critical during ops.
A14: Maintain Communication Among Assets | B14: 1 | C14: Keeps team effectiveness high — supports field suppression actions.
A15: Maintain Communication Between Assets and C3 | B15: 1 | C15: Provides macro-level support from C3 — equal operational importance.
... A22: Provide Logistic Support to Crews | B22: 1 | C22: Logistics keeps spill units running effectively — core support function.

Sheet Establish Containment Lines
A1: Compared Function | B1: Score (Saaty Scale) | C1: Justification
A2: Spill Water from Ground Assets | B2: 1 | C2: Spill and containment both directly suppress fire — same tier of impact. | E2: 1 | F2: 1 | G2: 2 | H2: 2 | I2: 2 | J2: 2 | K2: 1 | L2: 1 | M2: 1 | N2: 1 | O2: 1 | P2: 1 | Q2: 1 | R2: 1 | S2: 1 | T2: 1 | U2: 1 | V2: 1 | W2: 1 | X2: 1 | Y2: 1 | Z2: 1
A3: Tactically Monitor Fires | B3: 1 | C3: Monitoring helps guide tactics but doesn’t physically halt fire spread — containment is equally important.
A4: Predict New Fires | B4: 2 | C4: Prediction supports pre-positioning; containment is actual fireline defense — more tactical.
A5: Detect Fires | B5: 2 | C5: Detection is the trigger but doesn’t act on the fire — containment has operational value.
A6: Visually Confirm Fires | B6: 2 | C6: Confirmation ensures fire presence; containment actively mitigates spread.
A7: Predict Fire Paths/Behavior | B7: 2 | C7: Path prediction supports planning; containment limits actual spread — more immediately tactical.
A8: Strategically Monitor Fires | B8: 1 | C8: Strategic monitoring guides action; containment executes it.
A9: Gather Real Time Data from Assets | B9: 1 | C9: Data informs suppression action; containment is the action.
A10: Build Real Time Situational Awareness | B10: 1 | C10: Situational awareness helps assess and guide where to build lines — operational partners.
A11: Coordinate Air & Ground Resources | B11: 1 | C11: Coordination ensures resources work together; containment contributes physical control.
A12: Dynamically Allocate Resources | B12: 1 | C12: Allocation decides who acts where; containment is one of those actions.
A13: Issue Commands to Assets | B13: 1 | C13: Commands initiate action; containment is a core tactical result.
A14: Communicate to Resources | B14: 1 | C14: Communication keeps ops functioning; containment is the outcome of coordinated effort.
... A23: Provide Logistic Support to Crews | B23: 1 | C23: Logistics sustains those building lines — same systemic function tier.

Sheet Deploy Ground Assets
A1: Compared Function | B1: Score (Saaty Scale) | C1: Justification
A2: Establish Containment Lines | B2: 1 | C2: Ground deployment enables fireline work; containment is one of their primary tasks — equal.
A3: Spill Water from Ground Assets | B3: 1 | C3: Water delivery is an execution function post-deployment — same priority tier. | E3: 1 | F3: 1 | G3: 1 | H3: =1*1/2 -> 0.5 | I3: =1*1/2 -> 0.5 | J3: 1 | K3: =1*1/2 -> 0.5 | L3: 1 | M3: 1 | N3: 1 | O3: 1 | P3: 1 | Q3: 1 | R3: 1 | S3: 1 | T3: 1 | U3: 1 | V3: 1 | W3: 1 | X3: 1 | Y3: 1 | Z3: 1 | AA3: 1
A4: Tactically Monitor Fires | B4: 1 | C4: Monitoring informs action; deployment places the assets to act — equal.
A5: Predict New Fires | B5: =1*1/2 -> 0.5 | C5: Prediction is strategic; deployment is operational — deployment slightly more critical.
A6: Detect Fires | B6: =1*1/2 -> 0.5 | C6: Detection is the trigger, but deployment acts on the fire — operational impact is slightly higher.
A7: Visually Confirm Fires | B7: 1 | C7: Visual confirmation validates fires, but deployment enables response — equal importance.
A8: Predict Fire Paths/Behavior | B8: =1*1/2 -> 0.5 | C8: Fire path modeling informs where to deploy, but the act of deploying has more tactical immediacy.
A9: Strategically Monitor Fires | B9: 1 | C9: Strategic monitoring supports deployment decisions — but both have sustained operational value.
A10: Gather Real Time Data from Assets | B10: 1 | C10: Real-time data and field ops are directly linked — both are operational priorities.
A11: Build Real Time Situational Awareness | B11: 1 | C11: Awareness enables targeting and placement — equally vital as being able to act.
A12: Coordinate Air & Ground Resources | B12: 1 | C12: Coordination ensures that deployment is effective — symbiotic relationship.
A13: Dynamically Allocate Resources | B13: 1 | C13: Allocation affects where ground assets go — both are operationally enabling.
A14: Issue Commands to Assets | B14: 1 | C14: Commands activate deployment — same functional importance.
A15: Communicate to Resources | B15: 1 | C15: Communication sustains field effectiveness post-deployment — equally important.
A16: Maintain Communication Among Assets | B16: 1 | C16: Maintaining communication ensures safe and coordinated ground actions — co-equal.
A17: Maintain Communication Between Assets and C3 | B17: 1 | C17: Communication to C3 enables deployment decisions and feedback — mission-critical link.
A18: Deploy First Response Ground Assets | B18: 1 | C18: First response is an initial instantiation of deployment — same tier of urgency.
A19: Deploy Smokejumpers | B19: 1 | C19: Smokejumpers and ground assets act early, under different profiles — same impact tier.
A20: Activate MAFFS | B20: 1 | C20: MAFFS supports air assets; ground deployment operates independently — equal domain impact.
... A24: Provide Logistic Support to Crews | B24: 1 | C24: Crew logistics sustain deployed teams — both are enablers of effective field presence.

Sheet Dispatch to Reloading Base
A1: Compared Function | B1: Score (Saaty Scale) | C1: Justification
A2: Deploy Ground Assets | B2: =1*1/3 -> 0.33333333 | C2: Deployment acts directly on the fire; reloading supports ongoing action — slightly less critical. | E2: =1*1/3 -> 0.33333333 | F2: =1*1/3 -> 0.33333333 | G2: =1*1/2 -> 0.5 | H2: =1*1/2 -> 0.5 | I2: 1 | J2: 1 | K2: 1 | L2: 1 | M2: 1 | N2: 1 | O2: 1 | P2: 1 | Q2: 1 | R2: 1 | S2: 1 | T2: 1 | U2: 1 | V2: =1*1/2 -> 0.5 | W2: =1*1/2 -> 0.5 | X2: 1 | Y2: 1 | Z2: 1 | AA2: 1 | AB2: 1
A3: Establish Containment Lines | B3: =1*1/3 -> 0.33333333 | C3: Containment is a suppression method; reloading is prep for future action.
A4: Spill Water from Ground Assets | B4: =1*1/2 -> 0.5 | C4: Spill is a suppression activity; reloading enables continuation — slightly less critical.
A5: Tactically Monitor Fires | B5: =1*1/2 -> 0.5 | C5: Monitoring guides targeting; reloading supports repetition of targeting.
A6: Predict New Fires | B6: 1 | C6: Prediction and prep are both strategic — equal importance.
A7: Detect Fires | B7: 1 | C7: Detection starts the mission, reloading continues it — both are enablers.
A8: Visually Confirm Fires | B8: 1 | C8: Confirmation ensures targets are valid — equals the role of prepping for future sorties.
A9: Predict Fire Paths/Behavior | B9: 1 | C9: Fire path modeling and reload planning are both proactive.
A10: Strategically Monitor Fires | B10: 1 | C10: Strategic view supports coordination; reloading sustains fire engagement.
A11: Gather Real Time Data from Assets | B11: 1 | C11: Data and fuel are both inputs for continued operations.
A12: Build Real Time Situational Awareness | B12: 1 | C12: Awareness and readiness are both essential for effectiveness.
A13: Coordinate Air & Ground Resources | B13: 1 | C13: Coordination ensures reloads are optimized — coequal in mission support.
A14: Dynamically Allocate Resources | B14: 1 | C14: Reload location and resource allocation work together.
A15: Issue Commands to Assets | B15: 1 | C15: Orders determine who reloads and when — intertwined.
A16: Communicate to Resources | B16: 1 | C16: Reloads and field comms sustain continuity — equal in execution.
A17: Maintain Communication Among Assets | B17: 1 | C17: Asset communication helps ensure timing/safety — co-functioning with rearming.
A18: Maintain Communication Between Assets and C3 | B18: 1 | C18: Communication with C3 helps assign reload tasks — equal function.
A19: Deploy First Response Ground Assets | B19: =1*1/2 -> 0.5 | C19: Initial deployment is the tip of the spear — slightly more critical.
A20: Deploy Smokejumpers | B20: =1*1/2 -> 0.5 | C20: Smokejumpers are high-risk, rapid-response; reloading supports volume not surprise.
A21: Activate MAFFS | B21: 1 | C21: MAFFS enables capacity; reloading feeds it — slightly less critical.
A22: Refuel Airborne Assets | B22: 1 | C22: Reload and refuel are operational twins — equal in scope.
A23: Provide MRO for Assets | B23: 1 | C23: MRO ensures readiness long term, reloading is short-term cycle — equally needed.
A24: Refill Water and Fire Retardants | B24: 1 | C24: Reloading directly precedes refill — equal function in sortie loop.
A25: Provide Logistic Support to Crews | B25: 1 | C25: Crew support ensures reloading happens effectively — same tier.

Sheet Perform Post Drop Assessment
A1: Compared Function | B1: Score (Saaty Scale) | C1: Justification
A2: Dispatch To Reloading Base | B2: =1*1/2 -> 0.5 | C2: Reloading sustains operations, assessment evaluates prior effectiveness — slightly more operational.
A3: Deploy Ground Assets | B3: =1*1/3 -> 0.33333333 | C3: Ground deployment acts on the fire, while assessment is retrospective. | E3: =1*1/2 -> 0.5 | F3: =1*1/3 -> 0.33333333 | G3: =1*1/3 -> 0.33333333 | H3: =1*1/2 -> 0.5 | I3: =1*1/2 -> 0.5 | J3: 1 | K3: 1 | L3: 1 | M3: 1 | N3: 1 | O3: 1 | P3: 1 | Q3: 1 | R3: 1 | S3: 1 | T3: 1 | U3: 1 | V3: 1 | W3: =1*1/2 -> 0.5 | X3: =1*1/2 -> 0.5 | Y3: 1 | Z3: 1 | AA3: 1 | AB3: 1 | AC3: =1*1/2 -> 0.5
A4: Establish Containment Lines | B4: =1*1/3 -> 0.33333333 | C4: Containment lines are direct suppression tactics; assessment is analysis.
A5: Spill Water from Ground Assets | B5: =1*1/2 -> 0.5 | C5: Both occur post-action but water spill acts on fire, assessment reviews results.
A6: Tactically Monitor Fires | B6: =1*1/2 -> 0.5 | C6: Monitoring guides future action; assessment reflects past outcomes.
A7: Predict New Fires | B7: 1 | C7: Prediction and assessment are both planning tools — equal weight.
A8: Detect Fires | B8: 1 | C8: Detection is an initiating action; assessment follows execution — equal in planning use.
A9: Visually Confirm Fires | B9: 1 | C9: Confirmation and assessment validate fire conditions — similar utility.
A10: Predict Fire Paths/Behavior | B10: 1 | C10: Behavior modeling and impact evaluation support future strategy — same importance.
A11: Strategically Monitor Fires | B11: 1 | C11: Strategic monitoring and assessment shape long-term planning.
A12: Gather Real Time Data from Assets | B12: 1 | C12: Real-time data and post-event analysis are both used to refine tactics.
A13: Build Real Time Situational Awareness | B13: 1 | C13: Situational awareness and assessment provide mission insights.
A14: Coordinate Air & Ground Resources | B14: 1 | C14: Coordination is real-time enabling; assessment is retrospective — both planning aids.
A15: Dynamically Allocate Resources | B15: 1 | C15: Allocation is proactive; assessment informs future allocations.
A16: Issue Commands to Assets | B16: 1 | C16: Commands drive action; assessment drives improvement.
A17: Communicate to Resources | B17: 1 | C17: Communication sustains ops; assessment refines effectiveness.
A18: Maintain Communication Among Assets | B18: 1 | C18: Both enable learning and cohesion across mission.
A19: Maintain Communication Between Assets and C3 | B19: 1 | C19: Assessment results feed into C3 updates and decisions.
A20: Deploy First Response Ground Assets | B20: =1*1/2 -> 0.5 | C20: First responders take immediate action; assessment is follow-up.
A21: Deploy Smokejumpers | B21: =1*1/2 -> 0.5 | C21: Smokejumpers act tactically; assessment looks backward.
A22: Activate MAFFS | B22: 1 | C22: MAFFS expands capacity; assessment measures success.
A23: Refuel Airborne Assets | B23: 1 | C23: Both are supportive functions, one ongoing and one post-action.
A24: Provide MRO for Assets | B24: 1 | C24: Maintenance keeps assets running; assessment improves strategy.
A25: Refill Water and Fire Retardants | B25: 1 | C25: Refill enables repeat actions; assessment evaluates last action.
A26: Provide Logistic Support to Crews | B26: =1*1/2 -> 0.5 | C26: Assessment informs logistics, which support sustained operations.

Sheet Drop Fire Retardant
A1: Compared Function | B1: Score (Saaty Scale) | C1: Justification
A2: Perform Post-Drop Assessment | B2: 5 | C2: Retardant application suppresses fire; assessment is post-action.
A3: Dispatch To Reloading Base | B3: 3 | C3: Reloading supports continued use but is not suppression itself. | E3: 5 | F3: 3 | G3: 1 | H3: 1 | I3: 2 | J3: 1 | K3: =1*1/3 -> 0.33333333 | L3: =1*1/3 -> 0.33333333 | M3: =1*1/2 -> 0.5 | N3: =1*1/2 -> 0.5 | O3: 1 | P3: 1 | Q3: 1 | R3: 1 | S3: 1 | T3: 1 | U3: 1 | V3: 1 | W3: 1 | X3: 1 | Y3: 1 | Z3: 1 | AA3: 2 | AB3: 3 | AC3: 1 | AD3: 3
A4: Deploy Ground Assets | B4: 1 | C4: Ground and aerial assets are parallel in frontline importance.
A5: Establish Containment Lines | B5: 1 | C5: Creating boundaries and aerial suppression are complementary tactics.
A6: Spill Water from Ground Assets | B6: 2 | C6: Ground delivery is more limited than aerial retardant coverage.
A7: Tactically Monitor Fires | B7: 1 | C7: Monitoring supports targeting; equally important in tactical scope.
A8: Predict New Fires | B8: =1*1/3 -> 0.33333333 | C8: Prediction supports allocation, but retardant executes suppression.
A9: Detect Fires | B9: =1*1/3 -> 0.33333333 | C9: Detection initiates response, but retardant suppresses active fire.
A10: Visually Confirm Fires | B10: =1*1/2 -> 0.5 | C10: Confirmation is informational, not suppressive.
A11: Predict Fire Paths/Behavior | B11: =1*1/2 -> 0.5 | C11: Path prediction helps targeting but doesn’t act on fire.
A12: Strategically Monitor Fires | B12: 1 | C12: Broad monitoring informs strategy; retardant acts tactically.
A13: Gather Real Time Data from Assets | B13: 1 | C13: Data supports targeting; execution is just as essential.
A14: Build Real Time Situational Awareness | B14: 1 | C14: Awareness shapes mission, but retardant does the direct suppression.
A15: Coordinate Air & Ground Resources | B15: 1 | C15: Coordination makes retardant deployment effective.
A16: Dynamically Allocate Resources | B16: 1 | C16: Allocation and suppression go hand in hand.
A17: Issue Commands to Assets | B17: 1 | C17: Commands direct retardant use — same level of importance.
A18: Communicate to Resources | B18: 1 | C18: Communication enables effective execution.
A19: Maintain Communication Among Assets | B19: 1 | C19: Maintains coordination between actors during suppression.
A20: Maintain Communication Between Assets and C3 | B20: 1 | C20: Syncs airborne ops with C3 — critical for timely drops.
A21: Deploy First Response Ground Assets | B21: 1 | C21: Ground first responders are equivalent in tactical timing.
A22: Deploy Smokejumpers | B22: 1 | C22: Rapid ground insertion is tactically similar to aerial drops.
A23: Activate MAFFS | B23: 1 | C23: MAFFS enables retardant deployment — equal in mission value.
... A27: Provide Logistic Support to Crews | B27: 3 | C27: Indirect impact; doesn’t act on the fire like retardant does.

Sheet Deploy Air Assets
A1: Compared Function | B1: Score | C1: Justification
A2: Deploy Air Assets | B2: 1 | C2: Reference function; compared to itself, importance is equal (1).
A3: Lead Tankers | B3: 3 | C3: Lead Tankers rely on deployed assets to function. Deployment is a precursor.
A4: Supervise Air Attacks (AAGs) | B4: 3 | C4: Supervision requires assets to already be airborne; deployment comes first.
A5: Drop Water | B5: =1/3 -> 0.33333333 | C5: You can’t drop water without deployed aircraft — deployment is upstream.
A6: Drop Fire Retardant | B6: =1/3 -> 0.33333333 | C6: Same as above. Execution relies on prior deployment.
A7: Perform Post-Drop Assessment | B7: =1/5 -> 0.2 | C7: Evaluation is helpful but comes only after suppression. Deployment is more time-critical.
A8: Dispatch To Reloading Base | B8: 2 | C8: Resets aircraft for future deployment — slightly less critical than the initial deployment.
A9: Deploy Ground Assets | B9: 1 | C9: Ground and air assets are complementary. Both are critical and parallel.
A10: Establish Containment Lines | B10: 1 | C10: Ground operation, but tactically equal in importance to air deployment.
A11: Spill Water from Ground Assets | B11: =1/3 -> 0.33333333 | C11: Ground execution depends on prior deployment. Slightly less impactful than aerial deployment.
A12: Tactically Monitor Fires | B12: 0.5 | C12: Informs drops and safety, but less direct impact than deploying suppression assets.
A13: Predict New Fires | B13: 0.33333333 | C13: Prediction supports proactive planning but doesn’t directly suppress fires.
A14: Detect Fires | B14: 0.33333333 | C14: Triggers response but does not directly suppress. Slightly less critical operationally.
A15: Visually Confirm Fires | B15: 0.33333333 | C15: Valuable validation step, but lower in hierarchy than acting on the fire.
A16: Predict Fire Paths/Behavior | B16: 0.33333333 | C16: Important for planning drops, but still depends on asset availability.
A17: Strategically Monitor Fires | B17: 0.5 | C17: Strategic awareness supports deployment decisions, but not a substitute for action.
A18: Gather Real Time Data from Assets | B18: 0.33333333 | C18: Supports situational awareness. Not mission-executing on its own.
A19: Build Real Time Situational Awareness | B19: 0.33333333 | C19: Synthesizes inputs to inform decision-makers. Not a suppression action.
A20: Coordinate Air & Ground Resources | B20: 1 | C20: Coordination maximizes effectiveness, but neither supersedes deployment.
A21: Dynamically Allocate Resources | B21: 1 | C21: Allocation and deployment work hand in hand; both enable mission execution.
A22: Issue Commands to Assets | B22: 0.5 | C22: Orders are important but assume assets exist and are ready. Deployment is slightly more operational.
A23: Communicate to Resources | B23: 0.5 | C23: Keeps operations moving, but less impactful than getting assets airborne.
... A32: Provide Logistic Support to Crews | B32: 5 | C32: Indirect contributor to fire suppression; deployment is far more mission-immediate.

Sheet Lead Tankers
A1: Compared Function | B1: Score (Saaty Scale) | C1: Justification
A2: Deploy Air Assets | B2: =1*1/3 -> 0.33333333 | C2: Lead tankers depend on the existence of deployed aircraft to operate. | E2: =1*1/2 -> 0.5 | F2: 1 | G2: 1 | H2: 3 | I2: 3 | J2: =1*1/2 -> 0.5 | K2: =1*1/2 -> 0.5 | L2: 2 | M2: 1 | N2: =1*1/5 -> 0.2 | O2: =1*1/4 -> 0.25 | P2: =1*1/3 -> 0.33333333 | Q2: =1*1/3 -> 0.33333333 | R2: =1*1/2 -> 0.5 | S2: =1*1/3 -> 0.33333333 | T2: =1*1/3 -> 0.33333333 | U2: =1*1/2 -> 0.5 | V2: =1*1/2 -> 0.5 | W2: =1*1/2 -> 0.5 | X2: =1*1/2 -> 0.5 | Y2: =1*1/2 -> 0.5 | Z2: =1*1/2 -> 0.5 | AA2: 1 | AB2: 1 | AC2: =1*1/2 -> 0.5 | AD2: =1*1/2 -> 0.5 | AE2: 2 | AF2: 1 | AG2: 3
A3: Lead Tankers | B3: 1 | C3: Reference function; compared to itself, importance is equal (1).
A4: Supervise Air Attacks (AAGs) | B4: =1*1/2 -> 0.5 | C4: AAGs coordinate multiple aircraft; slightly more influential across operations.
A5: Drop Water | B5: 1 | C5: Tankers guide drops; both are tightly coupled in suppression.
A6: Drop Fire Retardant | B6: 1 | C6: Same as above — tankers directly support this operation.
A7: Perform Post-Drop Assessment | B7: 3 | C7: Guiding drops is more operationally impactful than later evaluation.
A8: Dispatch To Reloading Base | B8: 3 | C8: Leading the drop is more mission-critical than returning to base.
A9: Deploy Ground Assets | B9: =1*1/2 -> 0.5 | C9: Lead tankers affect aerial ops only; ground asset deployment has broader scope.
A10: Establish Containment Lines | B10: =1*1/2 -> 0.5 | C10: Ground containment shapes the fire boundary, slightly more strategic.
A11: Spill Water from Ground Assets | B11: 2 | C11: Aerial lead tankers typically have more coverage and impact per operation.
A12: Tactically Monitor Fires | B12: 1 | C12: Tankers use tactical monitoring data to operate. Equally important.
A13: Predict New Fires | B13: =1*1/5 -> 0.2 | C13: Prediction is strategic, but tankers act on immediate threats.
A14: Detect Fires | B14: =1*1/4 -> 0.25 | C14: Detection initiates the chain, but lead tankers are part of execution.
A15: Visually Confirm Fires | B15: =1*1/3 -> 0.33333333 | C15: Confirmation precedes deployment, but is less critical in suppression.
A16: Predict Fire Paths/Behavior | B16: =1*1/3 -> 0.33333333 | C16: Planning support — helpful, but not directly tied to action like tankers.
A17: Strategically Monitor Fires | B17: =1*1/2 -> 0.5 | C17: Monitoring supports wide-area coordination; slightly more strategic.
A18: Gather Real Time Data from Assets | B18: =1*1/3 -> 0.33333333 | C18: Tankers act on this data — more downstream but more operational.
A19: Build Real Time Situational Awareness | B19: =1*1/3 -> 0.33333333 | C19: Awareness guides targeting, but tankers execute suppression.
A20: Coordinate Air & Ground Resources | B20: =1*1/2 -> 0.5 | C20: Coordination drives overall effectiveness; slightly more critical.
A21: Dynamically Allocate Resources | B21: =1*1/2 -> 0.5 | C21: Allocation shapes when and where tankers go — slightly more enabling.
A22: Issue Commands to Assets | B22: =1*1/2 -> 0.5 | C22: Command directs tankers; enabler with broader control.
A23: Communicate to Resources | B23: =1*1/2 -> 0.5 | C23: Communication enables tankers but is not sufficient on its own.
A24: Maintain Communication Among Assets | B24: =1*1/2 -> 0.5 | C24: Supports coordination; tankers depend on this but act on suppression.
A25: Maintain Communication Between Assets and C3 | B25: =1*1/2 -> 0.5 | C25: Enables tactical updates and direction; broader scope than tankers.
A26: Deploy First Response Ground Assets | B26: 1 | C26: Both are initial responders — parallel in importance.
A27: Deploy Smokejumpers | B27: 1 | C27: Same rationale — first-in assets with rapid tactical impact.
A28: Activate MAFFS | B28: =1*1/2 -> 0.5 | C28: MAFFS extends aerial fleet; lead tankers still enable targeting.
A29: Refuel Airborne Assets | B29: =1*1/2 -> 0.5 | C29: Keeps aircraft in the air — supportive but not mission-targeting.
A30: Provide MRO for Assets | B30: 2 | C30: MRO ensures readiness, but tankers execute live missions.
A31: Refill Water and Fire Retardants | B31: 1 | C31: Mutually dependent — no point in tanking without fire suppressant.
A32: Provide Logistic Support to Crews | B32: 3 | C32: Less direct; enables humans to function but not tied to mission-critical ops.

Sheet Supervise Air Attacks
A1: Compared Function | B1: Score (Saaty Scale) | C1: Justification
A2: Deploy Air Assets | B2: =1/3 -> 0.33333333 | C2: AAGs coordinate after assets are deployed. Deployment is a prerequisite.
A3: Lead Tankers | B3: 2 | C3: Lead tankers are tactically directed by AAGs; AAGs have broader command role. | F3: 1 | G3: 1 | H3: 3 | I3: 2 | J3: 1 | K3: 1 | L3: 2 | M3: 1 | N3: =1*1/4 -> 0.25 | O3: =1*1/3 -> 0.33333333 | P3: =1*1/2 -> 0.5 | Q3: =1*1/2 -> 0.5 | R3: 1 | S3: 1 | T3: 1 | U3: 1 | V3: 1 | W3: 1 | X3: 1 | Y3: 1 | Z3: 1 | AA3: 1 | AB3: 1 | AC3: 1 | AD3: 2 | AE3: 3 | AF3: 2 | AG3: 3
A4: Supervise Air Attacks (AAGs) | B4: 1 | C4: Reference function; compared to itself, importance is equal (1).
A5: Drop Water | B5: 1 | C5: AAGs depend on drop assets, but determine optimal use. Equal importance.
A6: Drop Fire Retardant | B6: 1 | C6: Same rationale—both roles are part of coordinated aerial attack.
A7: Perform Post-Drop Assessment | B7: 3 | C7: Evaluation follows execution; AAGs operate in-the-moment.
A8: Dispatch To Reloading Base | B8: 2 | C8: Reloading supports continuity, AAGs drive suppression logic.
A9: Deploy Ground Assets | B9: 1 | C9: Ground and air deployment serve different but parallel roles.
A10: Establish Containment Lines | B10: 1 | C10: Containment lines and aerial supervision are tactically aligned in impact.
A11: Spill Water from Ground Assets | B11: 2 | C11: Spilling water is reactive; AAGs are proactive coordinators.
A12: Tactically Monitor Fires | B12: 1 | C12: AAGs use this info for tactical decisions; same tier.
A13: Predict New Fires | B13: =1*1/4 -> 0.25 | C13: Prediction is helpful but not operationally urgent during attack.
